Workbook
Name Total_Daily_Visitors: Model!$C$6
Name Percentage_Locals_Init: Model!$C$7
Name Total_Daily_AudioTour: Model!$C$8
Name AudioTour_Price: Model!$C$9
Name Local_AudioTour_Rate_Init: Model!$C$10
Name Local_AudioTour_Rate_PWYW: Model!$C$11
Name PWYW_Suggested_Price: Model!$C$12
Name PWYW_Payment_Ratio: Model!$C$13
Name Payment_Fade_Total: Model!$C$14
Name Fade_Timescale_Days: Model!$C$15
Name GiftShop_Net_Spend_Local: Model!$C$16
Name GiftShop_Spillover: Model!$C$17
Name Marketing_Spend: Model!$C$18
Name Locals_Share_Ceiling: Model!$C$19
Name Marketing_Saturation_Spend: Model!$C$20
Name Campaign_Days: Model!$C$21
Name Headset_Cost: Model!$C$22
Name Card_Fee_Rate: Model!$C$23
Name Card_Fee_Museum_Share: Model!$C$24
Name Device_Capacity: Model!$C$25
Name Device_Block_Size: Model!$C$26
Name Device_Block_Cost: Model!$C$27
Name Device_Amort_Days: Model!$C$28
Name Tourists_Base: Model!$C$31
Name Locals_Base: Model!$C$32
Name AudioLocal_Base: Model!$C$33
Name AudioTourist_Base: Model!$C$34
Name Fee_Keep: Model!$C$35
Name Average_PWYW_Start: Model!$C$36
Name Fade_Multiplier: Model!$C$37
Name Average_PWYW: Model!$C$38
Name Awareness: Model!$C$39
Name Percentage_Locals_Final: Model!$C$40

Sheet Model
B2: Pay-What-You-Want Audio Tour: Profitability Model
B3: Museum is free. Locals pay what they want for the audio tour (normally $7); tourists still pay $7. Yellow cells with blue text are inputs. Everything else recalculates.
B4: Structure: capabilities/economic-research/spec.md. PLACEHOLDER = not yet backed by a verified source; results that depend on one are only as good as that number.
B5: INPUTS (the named contract) | C5: Value | D5: Unit | F5: Source / status
B6: Total_Daily_Visitors | C6: 5000 | D6: people/day | F6: Spec: assumed.
B7: Percentage_Locals_Init | C7: 0.075 | D7: % of visitors | F7: You: 5-10%. Midpoint used.
B8: Total_Daily_AudioTour | C8: 250 | D8: people/day | F8: Spec: assumed. Includes the locals who already take the tour.
B9: AudioTour_Price | C9: 7 | D9: $ | F9: Spec (written there as Audio_Tour_Cost; this is the price tourists pay).
B10: Local_AudioTour_Rate_Init | C10: 0.1 | D10: % of locals | F10: You: 10% of locals take the audio tour today.
B11: Local_AudioTour_Rate_PWYW | C11: 0.2 | D11: % of locals | F11: PLACEHOLDER. You expect take-up to rise under PWYW. Test 10-50%.
B12: PWYW_Suggested_Price | C12: 7 | D12: $ | F12: Recommended price shown to locals.
B13: PWYW_Payment_Ratio | C13: 0.6 | D13: payment / suggested | F13: PLACEHOLDER. Day-1 average payment as a share of the suggested price, including $0 payers. Test 40-80%.
B14: Payment_Fade_Total | C14: 0.15 | D14: % decline | F14: PLACEHOLDER. Fall in the average payment from day 1 to the end of the campaign.
B15: Fade_Timescale_Days | C15: 30 | D15: days | F15: PLACEHOLDER. How fast the fade happens; the decline slows over time. Smaller = faster early drop.
B16: GiftShop_Net_Spend_Local | C16: 5 | D16: $/incremental local | F16: You: $5 or $10. Net contribution per NEW local visitor. See break-even below.
B17: GiftShop_Spillover | C17: 0 | D17: $/existing local | F17: PLACEHOLDER. Extra net spend by an aware existing local who takes the PWYW tour. 0 is conservative.
... B28: Device_Amort_Days | C28: 365 | D28: days | F28: You: amortize over one year. Only the campaign's share is charged here.
B30: DERIVED INPUTS
B31: Tourists_Base | C31: =Total_Daily_Visitors*(1-Percentage_Locals_Init) | F31: Total_Daily_Tourists in the spec.
B32: Locals_Base | C32: =Total_Daily_Visitors*Percentage_Locals_Init | F32: Total_Daily_Locals in the spec.
B33: AudioLocal_Base | C33: =Locals_Base*Local_AudioTour_Rate_Init | F33: Locals who take the tour today (and pay $7).
B34: AudioTourist_Base | C34: =Total_Daily_AudioTour-AudioLocal_Base | F34: Remainder of the 250 are tourists.
B35: Fee_Keep | C35: =1-Card_Fee_Rate*Card_Fee_Museum_Share | F35: Share of each local audio-tour payment the museum keeps after any card fee it bears.
B36: Average_PWYW_Start | C36: =PWYW_Suggested_Price*PWYW_Payment_Ratio | F36: Day-1 average payment per aware local audio-tour user.
B37: Fade_Multiplier | C37: =1-Payment_Fade_Total*((1-(Fade_Timescale_Days/Campaign_Days)*(1-EXP(-Campaign_Days/Fade_Timescale_Days)))/(1-EXP(-Campaign_Days/Fade_Timescale_Days))) | F37: Average of the fading payment over the campaign, as a share of day 1. Fade shape: 1 - e^(-t/timescale), scaled to reach the total decline on the last day.
B38: Average_PWYW | C38: =Average_PWYW_Start*Fade_Multiplier | F38: Campaign-average payment per aware local audio-tour user.
B39: Awareness | C39: =1-EXP(-Marketing_Spend/Marketing_Saturation_Spend) | F39: Share of the achievable marketing effect reached: 1 - e^(-spend / saturation). 0 at $0 spend. Also the share of existing locals who know PWYW exists.
B40: Percentage_Locals_Final | C40: =Percentage_Locals_Init+(Locals_Share_Ceiling-Percentage_Locals_Init)*Awareness | F40: Init + (ceiling - Init) x Awareness. Diminishing returns on marketing.
B42: DAILY VIEW (campaign average day) | C42: Baseline | D42: Campaign | E42: Change | F42: Notes
B43: Local visitors | C43: =Locals_Base | D43: =Tourists_Base*Percentage_Locals_Final/(1-Percentage_Locals_Final) | E43: =D43-C43 | F43: Final share is of ALL visitors, so locals = tourists x final / (1 - final). Tourists do not change.
B44: Tourist visitors | C44: =Tourists_Base | D44: =Tourists_Base | E44: =D44-C44
B45: Local share of visitors | C45: =Percentage_Locals_Init | D45: =Percentage_Locals_Final | E45: =D45-C45
B46: Local audio-tour users | C46: =AudioLocal_Base | D46: =Locals_Base*(1-Awareness)*Local_AudioTour_Rate_Init+(D43-Locals_Base*(1-Awareness))*Local_AudioTour_Rate_PWYW | E46: =D46-C46 | F46: Unaware existing locals behave as today (10%, pay $7). Aware locals, incl. all new ones, take the tour at the PWYW rate and pay Average_PWYW.
B47: Tourist audio-tour users | C47: =AudioTourist_Base | D47: =AudioTourist_Base | E47: =D47-C47 | F47: Tourists keep paying $7.
B48: Total audio-tour users | C48: =C46+C47 | D48: =D46+D47 | E48: =D48-C48
B49: Avg payment per local audio user ($) | C49: =AudioTour_Price | D49: =IF(D46=0,0,(Locals_Base*(1-Awareness)*Local_AudioTour_Rate_Init*AudioTour_Price+(D43-Locals_Base*(1-Awareness))*Local_AudioTour_Rate_PWYW*Average_PWYW)/D46) | E49: =D49-C49 | F49: Blend of unaware locals paying $7 and aware locals paying the campaign-average PWYW payment.
B50: Audio-tour revenue ($) | C50: =C46*C49+C47*AudioTour_Price | D50: =D46*D49+D47*AudioTour_Price | E50: =D50-C50 | F50: Change includes the $7 revenue lost when an aware existing local moves to PWYW.
B51: Card fee borne by museum ($) | C51: =-Card_Fee_Rate*Card_Fee_Museum_Share*C46*C49 | D51: =-Card_Fee_Rate*Card_Fee_Museum_Share*D46*D49 | E51: =D51-C51 | F51: On local audio-tour payments only. 0 while the customer pays the fee.
B52: Headset cost ($) | C52: =-C48*Headset_Cost | D52: =-D48*Headset_Cost | E52: =D52-C52 | F52: $1 per audio-tour user, including those who pay $0.
B53: Extra device blocks needed | C53: =MAX(0,ROUNDUP((C48-Device_Capacity)/Device_Block_Size,0)) | D53: =MAX(0,ROUNDUP((D48-Device_Capacity)/Device_Block_Size,0)) | E53: =D53-C53 | F53: Blocks of 25 above the 500 capacity.
B54: Device cost, amortized per day ($) | C54: =-C53*Device_Block_Cost/Device_Amort_Days | D54: =-D53*Device_Block_Cost/Device_Amort_Days | E54: =D54-C54 | F54: Block cost spread over the amortization period.
B55: Gift shop contribution, incremental ($) | C55: 0 | D55: =E43*GiftShop_Net_Spend_Local+Locals_Base*Awareness*Local_AudioTour_Rate_PWYW*GiftShop_Spillover | E55: =D55-C55 | F55: New locals x net spend, plus spillover from aware existing locals. Baseline gift shop is not modeled (increments only).
B56: Daily contribution ($) | C56: =C50+C51+C52+C54+C55 | D56: =D50+D51+D52+D54+D55 | E56: =D56-C56 | F56: Revenue less card fee, headsets and devices, before marketing.
B58: CAMPAIGN RESULTS
B59: Incremental contribution over the campaign ($) | C59: =E56*Campaign_Days | F59: Daily change x campaign days.
B60: Marketing spend ($) | C60: =-Marketing_Spend
B61: NET PROFIT ($) | C61: =C59+C60 | F61: Positive = the PWYW program pays for itself within the campaign.
B62: ROI (%) | C62: =IF(Marketing_Spend=0,"n/a",C61/Marketing_Spend) | F62: Net profit / marketing spend.
B63: Break-even gift shop spend per incremental local ($) | C63: =IF(E43<=0,"n/a",GiftShop_Net_Spend_Local-C61/(E43*Campaign_Days)) | F63: Spend at which net profit = 0, holding everything else. Negative means it is profitable even at $0 of gift shop spend.
B64: Break-even campaign-average PWYW payment ($) | C64: =IF((D43-Locals_Base*(1-Awareness))*Local_AudioTour_Rate_PWYW<=0,"n/a",Average_PWYW-C61/((D43-Locals_Base*(1-Awareness))*Local_AudioTour_Rate_PWYW*Fee_Keep*Campaign_Days)) | F64: Average payment by aware locals at which net profit = 0, holding everything else.
B65: as % of suggested price | C65: =IF(ISNUMBER(C64),C64/PWYW_Suggested_Price,"n/a")
B66: Net profit with the gift shop effect removed ($) | C66: =C61-E55*Campaign_Days | F66: Audio tour only: revenue, headsets, devices and marketing. Shows how much of the result depends on gift shop spend.
B67: Gift shop share of campaign contribution | C67: =IF(C59<=0,"n/a",E55*Campaign_Days/C59)
B68: Verdict | C68: =IF(C61>0,"PROFITABLE under these inputs","NOT PROFITABLE under these inputs")
B70: BREAK-EVEN DRAW (how many added locals per day does PWYW need?)
B71: Existing locals: price effect ($/day) | C71: =Locals_Base*Awareness*Local_AudioTour_Rate_Init*Fee_Keep*(Average_PWYW-AudioTour_Price) | F71: Aware existing locals who already took the tour now pay the PWYW average instead of $7. Cannibalization.
B72: Existing locals: extra tour takers, net ($/day) | C72: =Locals_Base*Awareness*(Local_AudioTour_Rate_PWYW-Local_AudioTour_Rate_Init)*(Fee_Keep*Average_PWYW-Headset_Cost) | F72: Aware existing locals who newly take the tour, net of the headset.
B73: Existing locals: gift shop spillover ($/day) | C73: =Locals_Base*Awareness*Local_AudioTour_Rate_PWYW*GiftShop_Spillover
B74: Existing-local effect, total ($/day) | C74: =C71+C72+C73 | F74: Usually negative: this is what the added locals must overcome.
B75: Contribution per added local ($/day) | C75: =Local_AudioTour_Rate_PWYW*(Fee_Keep*Average_PWYW-Headset_Cost)+GiftShop_Net_Spend_Local | F75: Tour take-up x (payment net of fee and headset) + gift shop spend per new local.
B76: BREAK-EVEN added locals per day | C76: =IF(C75<=0,"n/a",(Marketing_Spend/Campaign_Days-C74)/C75) | F76: Added locals/day at which net profit over the campaign = 0, at this marketing spend. n/a = each added local loses money.
B77: as % of today's local visitors | C77: =IF(ISNUMBER(C76),C76/Locals_Base,"n/a") | F77: The rise in local visitors PWYW has to produce.
B78: as % of all daily visitors | C78: =IF(ISNUMBER(C76),C76/Total_Daily_Visitors,"n/a")
B79: Added locals per day this model assumes | C79: =E43 | F79: From the marketing response (ceiling and saturation placeholders).
B80: Assumed draw / required draw | C80: =IF(ISNUMBER(C76),IF(C76<=0,"n/a",C79/C76),"n/a") | F80: Above 1.0x the assumed draw clears break-even. This ratio is the real test of the first falsifier.
B81: Extra devices needed at the break-even draw? | C81: =IF(ISNUMBER(C76),IF(Total_Daily_AudioTour+Locals_Base*Awareness*(Local_AudioTour_Rate_PWYW-Local_AudioTour_Rate_Init)+C76*Local_AudioTour_Rate_PWYW>Device_Capacity,"YES: break-even is understated","No"),"n/a")
B83: CHECKS
B84: Tourist audio users are not negative | C84: =IF(AudioTourist_Base>=0,"OK","FAIL")
B85: Baseline audio revenue = daily audio users x price | C85: =IF(ABS(C50-Total_Daily_AudioTour*AudioTour_Price)<0.005,"OK","FAIL")
B86: Final local share is between initial share and 100% | C86: =IF(AND(Percentage_Locals_Final>=Percentage_Locals_Init,Percentage_Locals_Final<1),"OK","FAIL")
B87: Fade multiplier is between 0 and 100% | C87: =IF(AND(Fade_Multiplier>0,Fade_Multiplier<=1),"OK","FAIL")
B88: Break-even gift shop spend zeroes net profit | C88: =IF(ISNUMBER(C63),IF(ABS(C61+(C63-GiftShop_Net_Spend_Local)*E43*Campaign_Days)<0.01,"OK","FAIL"),"n/a")
B89: Break-even PWYW payment zeroes net profit | C89: =IF(ISNUMBER(C64),IF(ABS(C61+(C64-Average_PWYW)*(D43-Locals_Base*(1-Awareness))*Local_AudioTour_Rate_PWYW*Fee_Keep*Campaign_Days)<0.01,"OK","FAIL"),"n/a")
B90: Engine base scenario matches this sheet's net profit | C90: =IF(ABS(Engine!R2-C61)<0.01,"OK","FAIL")
B91: Zero marketing gives zero profit (Engine row 3 is a $0 test) | C91: =IF(ABS(Engine!R3)<0.01,"OK","FAIL")
B92: Daily contribution = existing-local effect + added locals x per-local contribution | C92: =IF(D53=0,IF(ABS(E56-(C74+C75*E43))<0.01,"OK","FAIL"),"n/a")
B93: Net profit at the break-even draw is zero (Engine row 4) | C93: =IF(AND(ISNUMBER(C76),Awareness>0,C81="No"),IF(ABS(Engine!R4)<0.01,"OK","FAIL"),"n/a")
B94: Extra devices needed in campaign? | C94: =IF(D53=0,"No (under capacity)","YES: "&D53&" block(s)")

Sheet Sensitivity
B2: Sensitivity Tables: Net Profit Over the Campaign
B3: Each table varies two levers; everything else comes from the Model tab. Axis values are editable. Green = profit, red = loss.
B5: 1. Marketing spend vs. gift shop spend per new local
B6: Marketing ($) \ Gift shop $ / new local | C6: 0 | D6: 1 | E6: 2.5 | F6: 5 | G6: 7.5 | H6: 10 | I6: 15
B7: 0 | C7: =Engine!R5 | D7: =Engine!R6 | E7: =Engine!R7 | F7: =Engine!R8 | G7: =Engine!R9 | H7: =Engine!R10 | I7: =Engine!R11
B8: 2500 | C8: =Engine!R12 | D8: =Engine!R13 | E8: =Engine!R14 | F8: =Engine!R15 | G8: =Engine!R16 | H8: =Engine!R17 | I8: =Engine!R18
B9: 5000 | C9: =Engine!R19 | D9: =Engine!R20 | E9: =Engine!R21 | F9: =Engine!R22 | G9: =Engine!R23 | H9: =Engine!R24 | I9: =Engine!R25
B10: 10000 | C10: =Engine!R26 | D10: =Engine!R27 | E10: =Engine!R28 | F10: =Engine!R29 | G10: =Engine!R30 | H10: =Engine!R31 | I10: =Engine!R32
B11: 15000 | C11: =Engine!R33 | D11: =Engine!R34 | E11: =Engine!R35 | F11: =Engine!R36 | G11: =Engine!R37 | H11: =Engine!R38 | I11: =Engine!R39
B12: 20000 | C12: =Engine!R40 | D12: =Engine!R41 | E12: =Engine!R42 | F12: =Engine!R43 | G12: =Engine!R44 | H12: =Engine!R45 | I12: =Engine!R46
B15: 2. Campaign-average payment vs. local take-up
B16: Avg payment ($) \ Take-up (% of locals) | C16: 0.1 | D16: 0.2 | E16: 0.3 | F16: 0.4 | G16: 0.5
B17: 0 | C17: =Engine!R47 | D17: =Engine!R48 | E17: =Engine!R49 | F17: =Engine!R50 | G17: =Engine!R51
B18: 1 | C18: =Engine!R52 | D18: =Engine!R53 | E18: =Engine!R54 | F18: =Engine!R55 | G18: =Engine!R56
B19: 2 | C19: =Engine!R57 | D19: =Engine!R58 | E19: =Engine!R59 | F19: =Engine!R60 | G19: =Engine!R61
B20: 3 | C20: =Engine!R62 | D20: =Engine!R63 | E20: =Engine!R64 | F20: =Engine!R65 | G20: =Engine!R66
B21: 4 | C21: =Engine!R67 | D21: =Engine!R68 | E21: =Engine!R69 | F21: =Engine!R70 | G21: =Engine!R71
B22: 5 | C22: =Engine!R72 | D22: =Engine!R73 | E22: =Engine!R74 | F22: =Engine!R75 | G22: =Engine!R76
B23: 6 | C23: =Engine!R77 | D23: =Engine!R78 | E23: =Engine!R79 | F23: =Engine!R80 | G23: =Engine!R81
B24: 7 | C24: =Engine!R82 | D24: =Engine!R83 | E24: =Engine!R84 | F24: =Engine!R85 | G24: =Engine!R86
B27: 3. Marketing spend vs. local traffic ceiling (7.5% = no draw)
B28: Marketing ($) \ Locals % of visitors (ceiling) | C28: 0.075 | D28: 0.09 | E28: 0.1 | F28: 0.125 | G28: 0.15 | H28: 0.2
B29: 0 | C29: =Engine!R87 | D29: =Engine!R88 | E29: =Engine!R89 | F29: =Engine!R90 | G29: =Engine!R91 | H29: =Engine!R92
B30: 2500 | C30: =Engine!R93 | D30: =Engine!R94 | E30: =Engine!R95 | F30: =Engine!R96 | G30: =Engine!R97 | H30: =Engine!R98
B31: 5000 | C31: =Engine!R99 | D31: =Engine!R100 | E31: =Engine!R101 | F31: =Engine!R102 | G31: =Engine!R103 | H31: =Engine!R104
B32: 10000 | C32: =Engine!R105 | D32: =Engine!R106 | E32: =Engine!R107 | F32: =Engine!R108 | G32: =Engine!R109 | H32: =Engine!R110
B33: 15000 | C33: =Engine!R111 | D33: =Engine!R112 | E33: =Engine!R113 | F33: =Engine!R114 | G33: =Engine!R115 | H33: =Engine!R116
B34: 20000 | C34: =Engine!R117 | D34: =Engine!R118 | E34: =Engine!R119 | F34: =Engine!R120 | G34: =Engine!R121 | H34: =Engine!R122
B37: 4. Local traffic ceiling vs. gift shop spend (base marketing)
B38: Locals % ceiling \ Gift shop $ / new local | C38: 0 | D38: 1 | E38: 2.5 | F38: 5 | G38: 7.5 | H38: 10 | I38: 15
B39: 0.075 | C39: =Engine!R123 | D39: =Engine!R124 | E39: =Engine!R125 | F39: =Engine!R126 | G39: =Engine!R127 | H39: =Engine!R128 | I39: =Engine!R129
B40: 0.09 | C40: =Engine!R130 | D40: =Engine!R131 | E40: =Engine!R132 | F40: =Engine!R133 | G40: =Engine!R134 | H40: =Engine!R135 | I40: =Engine!R136
B41: 0.1 | C41: =Engine!R137 | D41: =Engine!R138 | E41: =Engine!R139 | F41: =Engine!R140 | G41: =Engine!R141 | H41: =Engine!R142 | I41: =Engine!R143
B42: 0.125 | C42: =Engine!R144 | D42: =Engine!R145 | E42: =Engine!R146 | F42: =Engine!R147 | G42: =Engine!R148 | H42: =Engine!R149 | I42: =Engine!R150
B43: 0.15 | C43: =Engine!R151 | D43: =Engine!R152 | E43: =Engine!R153 | F43: =Engine!R154 | G43: =Engine!R155 | H43: =Engine!R156 | I43: =Engine!R157
B44: 0.2 | C44: =Engine!R158 | D44: =Engine!R159 | E44: =Engine!R160 | F44: =Engine!R161 | G44: =Engine!R162 | H44: =Engine!R163 | I44: =Engine!R164
B47: 5. Take-up and payment move together (base marketing)
B48: Scenario | C48: Payment ratio | D48: Take-up | E48: Avg payment ($) | F48: Net profit ($) | G48: Net profit, no gift shop ($)
B49: Payment-led: few take it, they pay well | C49: 0.8 | D49: 0.1 | E49: =PWYW_Suggested_Price*C49*Fade_Multiplier | F49: =Engine!R165 | G49: =Engine!R165-Engine!P165*Campaign_Days
B50: Balanced (near the base case) | C50: 0.6 | D50: 0.2 | E50: =PWYW_Suggested_Price*C50*Fade_Multiplier | F50: =Engine!R166 | G50: =Engine!R166-Engine!P166*Campaign_Days
B51: Volume-led: more take it, pay less | C51: 0.3 | D51: 0.4 | E51: =PWYW_Suggested_Price*C51*Fade_Multiplier | F51: =Engine!R167 | G51: =Engine!R167-Engine!P167*Campaign_Days
B52: Giveaway: nearly everyone, almost nothing | C52: 0.1 | D52: 0.5 | E52: =PWYW_Suggested_Price*C52*Fade_Multiplier | F52: =Engine!R168 | G52: =Engine!R168-Engine!P168*Campaign_Days
B53: Scenario pairs are PLACEHOLDERS that illustrate the trade-off between payment and take-up, not estimates.
B54: Tables 6-7 solve for the draw PWYW needs, so no assumption about how many locals marketing attracts is required. Compare each cell with the rise in local visitors you think a campaign of that size could achieve.
B55: 6. BREAK-EVEN added locals per day (marketing spend vs. gift shop spend)
B56: Marketing ($) \ Gift shop $ / local | C56: =C$6 | D56: =D$6 | E56: =E$6 | F56: =F$6 | G56: =G$6 | H56: =H$6 | I56: =I$6
B57: =$B$7 | C57: =IF((Local_AudioTour_Rate_PWYW*(Fee_Keep*Average_PWYW-Headset_Cost)+C$56)<=0,"n/a",($B57/Campaign_Days-Locals_Base*(1-EXP(-$B57/Marketing_Saturation_Spend))*(Fee_Keep*(Local_AudioTour_Rate_PWYW*Average_PWYW-Local_AudioTour_Rate_Init*AudioTour_Price)-Headset_Cost*(Local_AudioTour_Rate_PWYW-Local_AudioTour_Rate_Init)+Local_AudioTour_Rate_PWYW*GiftShop_Spillover))/(Local_AudioTour_Rate_PWYW*(Fee_Keep*Average_PWYW-Headset_Cost)+C$56)) | D57: =IF((Local_AudioTour_Rate_PWYW*(Fee_Keep*Average_PWYW-Headset_Cost)+D$56)<=0,"n/a",($B57/Campaign_Days-Locals_Base*(1-EXP(-$B57/Marketing_Saturation_Spend))*(Fee_Keep*(Local_AudioTour_Rate_PWYW*Average_PWYW-Local_AudioTour_Rate_Init*AudioTour_Price)-Headset_Cost*(Local_AudioTour_Rate_PWYW-Local_AudioTour_Rate_Init)+Local_AudioTour_Rate_PWYW*GiftShop_Spillover))/(Local_AudioTour_Rate_PWYW*(Fee_Keep*Average_PWYW-Headset_Cost)+D$56)) | E57: =IF((Local_AudioTour_Rate_PWYW*(Fee_Keep*Average_PWYW-Headset_Cost)+E$56)<=0,"n/a",($B57/Campaign_Days-Locals_Base*(1-EXP(-$B57/Marketing_Saturation_Spend))*(Fee_Keep*(Local_AudioTour_Rate_PWYW*Average_PWYW-Local_AudioTour_Rate_Init*AudioTour_Price)-Headset_Cost*(Local_AudioTour_Rate_PWYW-Local_AudioTour_Rate_Init)+Local_AudioTour_Rate_PWYW*GiftShop_Spillover))/(Local_AudioTour_Rate_PWYW*(Fee_Keep*Average_PWYW-Headset_Cost)+E$56)) | F57: =IF((Local_AudioTour_Rate_PWYW*(Fee_Keep*Average_PWYW-Headset_Cost)+F$56)<=0,"n/a",($B57/Campaign_Days-Locals_Base*(1-EXP(-$B57/Marketing_Saturation_Spend))*(Fee_Keep*(Local_AudioTour_Rate_PWYW*Average_PWYW-Local_AudioTour_Rate_Init*AudioTour_Price)-Headset_Cost*(Local_AudioTour_Rate_PWYW-Local_AudioTour_Rate_Init)+Local_AudioTour_Rate_PWYW*GiftShop_Spillover))/(Local_AudioTour_Rate_PWYW*(Fee_Keep*Average_PWYW-Headset_Cost)+F$56)) | G57: =IF((Local_AudioTour_Rate_PWYW*(Fee_Keep*Average_PWYW-Headset_Cost)+G$56)<=0,"n/a",($B57/Campaign_Days-Locals_Base*(1-EXP(-$B57/Marketing_Saturation_Spend))*(Fee_Keep*(Local_AudioTour_Rate_PWYW*Average_PWYW-Local_AudioTour_Rate_Init*AudioTour_Price)-Headset_Cost*(Local_AudioTour_Rate_PWYW-Local_AudioTour_Rate_Init)+Local_AudioTour_Rate_PWYW*GiftShop_Spillover))/(Local_AudioTour_Rate_PWYW*(Fee_Keep*Average_PWYW-Headset_Cost)+G$56)) | H57: =IF((Local_AudioTour_Rate_PWYW*(Fee_Keep*Average_PWYW-Headset_Cost)+H$56)<=0,"n/a",($B57/Campaign_Days-Locals_Base*(1-EXP(-$B57/Marketing_Saturation_Spend))*(Fee_Keep*(Local_AudioTour_Rate_PWYW*Average_PWYW-Local_AudioTour_Rate_Init*AudioTour_Price)-Headset_Cost*(Local_AudioTour_Rate_PWYW-Local_AudioTour_Rate_Init)+Local_AudioTour_Rate_PWYW*GiftShop_Spillover))/(Local_AudioTour_Rate_PWYW*(Fee_Keep*Average_PWYW-Headset_Cost)+H$56)) | I57: =IF((Local_AudioTour_Rate_PWYW*(Fee_Keep*Average_PWYW-Headset_Cost)+I$56)<=0,"n/a",($B57/Campaign_Days-Locals_Base*(1-EXP(-$B57/Marketing_Saturation_Spend))*(Fee_Keep*(Local_AudioTour_Rate_PWYW*Average_PWYW-Local_AudioTour_Rate_Init*AudioTour_Price)-Headset_Cost*(Local_AudioTour_Rate_PWYW-Local_AudioTour_Rate_Init)+Local_AudioTour_Rate_PWYW*GiftShop_Spillover))/(Local_AudioTour_Rate_PWYW*(Fee_Keep*Average_PWYW-Headset_Cost)+I$56))
B58: =$B$8 | C58: =IF((Local_AudioTour_Rate_PWYW*(Fee_Keep*Average_PWYW-Headset_Cost)+C$56)<=0,"n/a",($B58/Campaign_Days-Locals_Base*(1-EXP(-$B58/Marketing_Saturation_Spend))*(Fee_Keep*(Local_AudioTour_Rate_PWYW*Average_PWYW-Local_AudioTour_Rate_Init*AudioTour_Price)-Headset_Cost*(Local_AudioTour_Rate_PWYW-Local_AudioTour_Rate_Init)+Local_AudioTour_Rate_PWYW*GiftShop_Spillover))/(Local_AudioTour_Rate_PWYW*(Fee_Keep*Average_PWYW-Headset_Cost)+C$56)) | D58: =IF((Local_AudioTour_Rate_PWYW*(Fee_Keep*Average_PWYW-Headset_Cost)+D$56)<=0,"n/a",($B58/Campaign_Days-Locals_Base*(1-EXP(-$B58/Marketing_Saturation_Spend))*(Fee_Keep*(Local_AudioTour_Rate_PWYW*Average_PWYW-Local_AudioTour_Rate_Init*AudioTour_Price)-Headset_Cost*(Local_AudioTour_Rate_PWYW-Local_AudioTour_Rate_Init)+Local_AudioTour_Rate_PWYW*GiftShop_Spillover))/(Local_AudioTour_Rate_PWYW*(Fee_Keep*Average_PWYW-Headset_Cost)+D$56)) | E58: =IF((Local_AudioTour_Rate_PWYW*(Fee_Keep*Average_PWYW-Headset_Cost)+E$56)<=0,"n/a",($B58/Campaign_Days-Locals_Base*(1-EXP(-$B58/Marketing_Saturation_Spend))*(Fee_Keep*(Local_AudioTour_Rate_PWYW*Average_PWYW-Local_AudioTour_Rate_Init*AudioTour_Price)-Headset_Cost*(Local_AudioTour_Rate_PWYW-Local_AudioTour_Rate_Init)+Local_AudioTour_Rate_PWYW*GiftShop_Spillover))/(Local_AudioTour_Rate_PWYW*(Fee_Keep*Average_PWYW-Headset_Cost)+E$56)) | F58: =IF((Local_AudioTour_Rate_PWYW*(Fee_Keep*Average_PWYW-Headset_Cost)+F$56)<=0,"n/a",($B58/Campaign_Days-Locals_Base*(1-EXP(-$B58/Marketing_Saturation_Spend))*(Fee_Keep*(Local_AudioTour_Rate_PWYW*Average_PWYW-Local_AudioTour_Rate_Init*AudioTour_Price)-Headset_Cost*(Local_AudioTour_Rate_PWYW-Local_AudioTour_Rate_Init)+Local_AudioTour_Rate_PWYW*GiftShop_Spillover))/(Local_AudioTour_Rate_PWYW*(Fee_Keep*Average_PWYW-Headset_Cost)+F$56)) | G58: =IF((Local_AudioTour_Rate_PWYW*(Fee_Keep*Average_PWYW-Headset_Cost)+G$56)<=0,"n/a",($B58/Campaign_Days-Locals_Base*(1-EXP(-$B58/Marketing_Saturation_Spend))*(Fee_Keep*(Local_AudioTour_Rate_PWYW*Average_PWYW-Local_AudioTour_Rate_Init*AudioTour_Price)-Headset_Cost*(Local_AudioTour_Rate_PWYW-Local_AudioTour_Rate_Init)+Local_AudioTour_Rate_PWYW*GiftShop_Spillover))/(Local_AudioTour_Rate_PWYW*(Fee_Keep*Average_PWYW-Headset_Cost)+G$56)) | H58: =IF((Local_AudioTour_Rate_PWYW*(Fee_Keep*Average_PWYW-Headset_Cost)+H$56)<=0,"n/a",($B58/Campaign_Days-Locals_Base*(1-EXP(-$B58/Marketing_Saturation_Spend))*(Fee_Keep*(Local_AudioTour_Rate_PWYW*Average_PWYW-Local_AudioTour_Rate_Init*AudioTour_Price)-Headset_Cost*(Local_AudioTour_Rate_PWYW-Local_AudioTour_Rate_Init)+Local_AudioTour_Rate_PWYW*GiftShop_Spillover))/(Local_AudioTour_Rate_PWYW*(Fee_Keep*Average_PWYW-Headset_Cost)+H$56)) | I58: =IF((Local_AudioTour_Rate_PWYW*(Fee_Keep*Average_PWYW-Headset_Cost)+I$56)<=0,"n/a",($B58/Campaign_Days-Locals_Base*(1-EXP(-$B58/Marketing_Saturation_Spend))*(Fee_Keep*(Local_AudioTour_Rate_PWYW*Average_PWYW-Local_AudioTour_Rate_Init*AudioTour_Price)-Headset_Cost*(Local_AudioTour_Rate_PWYW-Local_AudioTour_Rate_Init)+Local_AudioTour_Rate_PWYW*GiftShop_Spillover))/(Local_AudioTour_Rate_PWYW*(Fee_Keep*Average_PWYW-Headset_Cost)+I$56))
B59: =$B$9 | C59: =IF((Local_AudioTour_Rate_PWYW*(Fee_Keep*Average_PWYW-Headset_Cost)+C$56)<=0,"n/a",($B59/Campaign_Days-Locals_Base*(1-EXP(-$B59/Marketing_Saturation_Spend))*(Fee_Keep*(Local_AudioTour_Rate_PWYW*Average_PWYW-Local_AudioTour_Rate_Init*AudioTour_Price)-Headset_Cost*(Local_AudioTour_Rate_PWYW-Local_AudioTour_Rate_Init)+Local_AudioTour_Rate_PWYW*GiftShop_Spillover))/(Local_AudioTour_Rate_PWYW*(Fee_Keep*Average_PWYW-Headset_Cost)+C$56)) | D59: =IF((Local_AudioTour_Rate_PWYW*(Fee_Keep*Average_PWYW-Headset_Cost)+D$56)<=0,"n/a",($B59/Campaign_Days-Locals_Base*(1-EXP(-$B59/Marketing_Saturation_Spend))*(Fee_Keep*(Local_AudioTour_Rate_PWYW*Average_PWYW-Local_AudioTour_Rate_Init*AudioTour_Price)-Headset_Cost*(Local_AudioTour_Rate_PWYW-Local_AudioTour_Rate_Init)+Local_AudioTour_Rate_PWYW*GiftShop_Spillover))/(Local_AudioTour_Rate_PWYW*(Fee_Keep*Average_PWYW-Headset_Cost)+D$56)) | E59: =IF((Local_AudioTour_Rate_PWYW*(Fee_Keep*Average_PWYW-Headset_Cost)+E$56)<=0,"n/a",($B59/Campaign_Days-Locals_Base*(1-EXP(-$B59/Marketing_Saturation_Spend))*(Fee_Keep*(Local_AudioTour_Rate_PWYW*Average_PWYW-Local_AudioTour_Rate_Init*AudioTour_Price)-Headset_Cost*(Local_AudioTour_Rate_PWYW-Local_AudioTour_Rate_Init)+Local_AudioTour_Rate_PWYW*GiftShop_Spillover))/(Local_AudioTour_Rate_PWYW*(Fee_Keep*Average_PWYW-Headset_Cost)+E$56)) | F59: =IF((Local_AudioTour_Rate_PWYW*(Fee_Keep*Average_PWYW-Headset_Cost)+F$56)<=0,"n/a",($B59/Campaign_Days-Locals_Base*(1-EXP(-$B59/Marketing_Saturation_Spend))*(Fee_Keep*(Local_AudioTour_Rate_PWYW*Average_PWYW-Local_AudioTour_Rate_Init*AudioTour_Price)-Headset_Cost*(Local_AudioTour_Rate_PWYW-Local_AudioTour_Rate_Init)+Local_AudioTour_Rate_PWYW*GiftShop_Spillover))/(Local_AudioTour_Rate_PWYW*(Fee_Keep*Average_PWYW-Headset_Cost)+F$56)) | G59: =IF((Local_AudioTour_Rate_PWYW*(Fee_Keep*Average_PWYW-Headset_Cost)+G$56)<=0,"n/a",($B59/Campaign_Days-Locals_Base*(1-EXP(-$B59/Marketing_Saturation_Spend))*(Fee_Keep*(Local_AudioTour_Rate_PWYW*Average_PWYW-Local_AudioTour_Rate_Init*AudioTour_Price)-Headset_Cost*(Local_AudioTour_Rate_PWYW-Local_AudioTour_Rate_Init)+Local_AudioTour_Rate_PWYW*GiftShop_Spillover))/(Local_AudioTour_Rate_PWYW*(Fee_Keep*Average_PWYW-Headset_Cost)+G$56)) | H59: =IF((Local_AudioTour_Rate_PWYW*(Fee_Keep*Average_PWYW-Headset_Cost)+H$56)<=0,"n/a",($B59/Campaign_Days-Locals_Base*(1-EXP(-$B59/Marketing_Saturation_Spend))*(Fee_Keep*(Local_AudioTour_Rate_PWYW*Average_PWYW-Local_AudioTour_Rate_Init*AudioTour_Price)-Headset_Cost*(Local_AudioTour_Rate_PWYW-Local_AudioTour_Rate_Init)+Local_AudioTour_Rate_PWYW*GiftShop_Spillover))/(Local_AudioTour_Rate_PWYW*(Fee_Keep*Average_PWYW-Headset_Cost)+H$56)) | I59: =IF((Local_AudioTour_Rate_PWYW*(Fee_Keep*Average_PWYW-Headset_Cost)+I$56)<=0,"n/a",($B59/Campaign_Days-Locals_Base*(1-EXP(-$B59/Marketing_Saturation_Spend))*(Fee_Keep*(Local_AudioTour_Rate_PWYW*Average_PWYW-Local_AudioTour_Rate_Init*AudioTour_Price)-Headset_Cost*(Local_AudioTour_Rate_PWYW-Local_AudioTour_Rate_Init)+Local_AudioTour_Rate_PWYW*GiftShop_Spillover))/(Local_AudioTour_Rate_PWYW*(Fee_Keep*Average_PWYW-Headset_Cost)+I$56))
B60: =$B$10 | C60: =IF((Local_AudioTour_Rate_PWYW*(Fee_Keep*Average_PWYW-Headset_Cost)+C$56)<=0,"n/a",($B60/Campaign_Days-Locals_Base*(1-EXP(-$B60/Marketing_Saturation_Spend))*(Fee_Keep*(Local_AudioTour_Rate_PWYW*Average_PWYW-Local_AudioTour_Rate_Init*AudioTour_Price)-Headset_Cost*(Local_AudioTour_Rate_PWYW-Local_AudioTour_Rate_Init)+Local_AudioTour_Rate_PWYW*GiftShop_Spillover))/(Local_AudioTour_Rate_PWYW*(Fee_Keep*Average_PWYW-Headset_Cost)+C$56)) | D60: =IF((Local_AudioTour_Rate_PWYW*(Fee_Keep*Average_PWYW-Headset_Cost)+D$56)<=0,"n/a",($B60/Campaign_Days-Locals_Base*(1-EXP(-$B60/Marketing_Saturation_Spend))*(Fee_Keep*(Local_AudioTour_Rate_PWYW*Average_PWYW-Local_AudioTour_Rate_Init*AudioTour_Price)-Headset_Cost*(Local_AudioTour_Rate_PWYW-Local_AudioTour_Rate_Init)+Local_AudioTour_Rate_PWYW*GiftShop_Spillover))/(Local_AudioTour_Rate_PWYW*(Fee_Keep*Average_PWYW-Headset_Cost)+D$56)) | E60: =IF((Local_AudioTour_Rate_PWYW*(Fee_Keep*Average_PWYW-Headset_Cost)+E$56)<=0,"n/a",($B60/Campaign_Days-Locals_Base*(1-EXP(-$B60/Marketing_Saturation_Spend))*(Fee_Keep*(Local_AudioTour_Rate_PWYW*Average_PWYW-Local_AudioTour_Rate_Init*AudioTour_Price)-Headset_Cost*(Local_AudioTour_Rate_PWYW-Local_AudioTour_Rate_Init)+Local_AudioTour_Rate_PWYW*GiftShop_Spillover))/(Local_AudioTour_Rate_PWYW*(Fee_Keep*Average_PWYW-Headset_Cost)+E$56)) | F60: =IF((Local_AudioTour_Rate_PWYW*(Fee_Keep*Average_PWYW-Headset_Cost)+F$56)<=0,"n/a",($B60/Campaign_Days-Locals_Base*(1-EXP(-$B60/Marketing_Saturation_Spend))*(Fee_Keep*(Local_AudioTour_Rate_PWYW*Average_PWYW-Local_AudioTour_Rate_Init*AudioTour_Price)-Headset_Cost*(Local_AudioTour_Rate_PWYW-Local_AudioTour_Rate_Init)+Local_AudioTour_Rate_PWYW*GiftShop_Spillover))/(Local_AudioTour_Rate_PWYW*(Fee_Keep*Average_PWYW-Headset_Cost)+F$56)) | G60: =IF((Local_AudioTour_Rate_PWYW*(Fee_Keep*Average_PWYW-Headset_Cost)+G$56)<=0,"n/a",($B60/Campaign_Days-Locals_Base*(1-EXP(-$B60/Marketing_Saturation_Spend))*(Fee_Keep*(Local_AudioTour_Rate_PWYW*Average_PWYW-Local_AudioTour_Rate_Init*AudioTour_Price)-Headset_Cost*(Local_AudioTour_Rate_PWYW-Local_AudioTour_Rate_Init)+Local_AudioTour_Rate_PWYW*GiftShop_Spillover))/(Local_AudioTour_Rate_PWYW*(Fee_Keep*Average_PWYW-Headset_Cost)+G$56)) | H60: =IF((Local_AudioTour_Rate_PWYW*(Fee_Keep*Average_PWYW-Headset_Cost)+H$56)<=0,"n/a",($B60/Campaign_Days-Locals_Base*(1-EXP(-$B60/Marketing_Saturation_Spend))*(Fee_Keep*(Local_AudioTour_Rate_PWYW*Average_PWYW-Local_AudioTour_Rate_Init*AudioTour_Price)-Headset_Cost*(Local_AudioTour_Rate_PWYW-Local_AudioTour_Rate_Init)+Local_AudioTour_Rate_PWYW*GiftShop_Spillover))/(Local_AudioTour_Rate_PWYW*(Fee_Keep*Average_PWYW-Headset_Cost)+H$56)) | I60: =IF((Local_AudioTour_Rate_PWYW*(Fee_Keep*Average_PWYW-Headset_Cost)+I$56)<=0,"n/a",($B60/Campaign_Days-Locals_Base*(1-EXP(-$B60/Marketing_Saturation_Spend))*(Fee_Keep*(Local_AudioTour_Rate_PWYW*Average_PWYW-Local_AudioTour_Rate_Init*AudioTour_Price)-Headset_Cost*(Local_AudioTour_Rate_PWYW-Local_AudioTour_Rate_Init)+Local_AudioTour_Rate_PWYW*GiftShop_Spillover))/(Local_AudioTour_Rate_PWYW*(Fee_Keep*Average_PWYW-Headset_Cost)+I$56))
B61: =$B$11 | C61: =IF((Local_AudioTour_Rate_PWYW*(Fee_Keep*Average_PWYW-Headset_Cost)+C$56)<=0,"n/a",($B61/Campaign_Days-Locals_Base*(1-EXP(-$B61/Marketing_Saturation_Spend))*(Fee_Keep*(Local_AudioTour_Rate_PWYW*Average_PWYW-Local_AudioTour_Rate_Init*AudioTour_Price)-Headset_Cost*(Local_AudioTour_Rate_PWYW-Local_AudioTour_Rate_Init)+Local_AudioTour_Rate_PWYW*GiftShop_Spillover))/(Local_AudioTour_Rate_PWYW*(Fee_Keep*Average_PWYW-Headset_Cost)+C$56)) | D61: =IF((Local_AudioTour_Rate_PWYW*(Fee_Keep*Average_PWYW-Headset_Cost)+D$56)<=0,"n/a",($B61/Campaign_Days-Locals_Base*(1-EXP(-$B61/Marketing_Saturation_Spend))*(Fee_Keep*(Local_AudioTour_Rate_PWYW*Average_PWYW-Local_AudioTour_Rate_Init*AudioTour_Price)-Headset_Cost*(Local_AudioTour_Rate_PWYW-Local_AudioTour_Rate_Init)+Local_AudioTour_Rate_PWYW*GiftShop_Spillover))/(Local_AudioTour_Rate_PWYW*(Fee_Keep*Average_PWYW-Headset_Cost)+D$56)) | E61: =IF((Local_AudioTour_Rate_PWYW*(Fee_Keep*Average_PWYW-Headset_Cost)+E$56)<=0,"n/a",($B61/Campaign_Days-Locals_Base*(1-EXP(-$B61/Marketing_Saturation_Spend))*(Fee_Keep*(Local_AudioTour_Rate_PWYW*Average_PWYW-Local_AudioTour_Rate_Init*AudioTour_Price)-Headset_Cost*(Local_AudioTour_Rate_PWYW-Local_AudioTour_Rate_Init)+Local_AudioTour_Rate_PWYW*GiftShop_Spillover))/(Local_AudioTour_Rate_PWYW*(Fee_Keep*Average_PWYW-Headset_Cost)+E$56)) | F61: =IF((Local_AudioTour_Rate_PWYW*(Fee_Keep*Average_PWYW-Headset_Cost)+F$56)<=0,"n/a",($B61/Campaign_Days-Locals_Base*(1-EXP(-$B61/Marketing_Saturation_Spend))*(Fee_Keep*(Local_AudioTour_Rate_PWYW*Average_PWYW-Local_AudioTour_Rate_Init*AudioTour_Price)-Headset_Cost*(Local_AudioTour_Rate_PWYW-Local_AudioTour_Rate_Init)+Local_AudioTour_Rate_PWYW*GiftShop_Spillover))/(Local_AudioTour_Rate_PWYW*(Fee_Keep*Average_PWYW-Headset_Cost)+F$56)) | G61: =IF((Local_AudioTour_Rate_PWYW*(Fee_Keep*Average_PWYW-Headset_Cost)+G$56)<=0,"n/a",($B61/Campaign_Days-Locals_Base*(1-EXP(-$B61/Marketing_Saturation_Spend))*(Fee_Keep*(Local_AudioTour_Rate_PWYW*Average_PWYW-Local_AudioTour_Rate_Init*AudioTour_Price)-Headset_Cost*(Local_AudioTour_Rate_PWYW-Local_AudioTour_Rate_Init)+Local_AudioTour_Rate_PWYW*GiftShop_Spillover))/(Local_AudioTour_Rate_PWYW*(Fee_Keep*Average_PWYW-Headset_Cost)+G$56)) | H61: =IF((Local_AudioTour_Rate_PWYW*(Fee_Keep*Average_PWYW-Headset_Cost)+H$56)<=0,"n/a",($B61/Campaign_Days-Locals_Base*(1-EXP(-$B61/Marketing_Saturation_Spend))*(Fee_Keep*(Local_AudioTour_Rate_PWYW*Average_PWYW-Local_AudioTour_Rate_Init*AudioTour_Price)-Headset_Cost*(Local_AudioTour_Rate_PWYW-Local_AudioTour_Rate_Init)+Local_AudioTour_Rate_PWYW*GiftShop_Spillover))/(Local_AudioTour_Rate_PWYW*(Fee_Keep*Average_PWYW-Headset_Cost)+H$56)) | I61: =IF((Local_AudioTour_Rate_PWYW*(Fee_Keep*Average_PWYW-Headset_Cost)+I$56)<=0,"n/a",($B61/Campaign_Days-Locals_Base*(1-EXP(-$B61/Marketing_Saturation_Spend))*(Fee_Keep*(Local_AudioTour_Rate_PWYW*Average_PWYW-Local_AudioTour_Rate_Init*AudioTour_Price)-Headset_Cost*(Local_AudioTour_Rate_PWYW-Local_AudioTour_Rate_Init)+Local_AudioTour_Rate_PWYW*GiftShop_Spillover))/(Local_AudioTour_Rate_PWYW*(Fee_Keep*Average_PWYW-Headset_Cost)+I$56))
B62: =$B$12 | C62: =IF((Local_AudioTour_Rate_PWYW*(Fee_Keep*Average_PWYW-Headset_Cost)+C$56)<=0,"n/a",($B62/Campaign_Days-Locals_Base*(1-EXP(-$B62/Marketing_Saturation_Spend))*(Fee_Keep*(Local_AudioTour_Rate_PWYW*Average_PWYW-Local_AudioTour_Rate_Init*AudioTour_Price)-Headset_Cost*(Local_AudioTour_Rate_PWYW-Local_AudioTour_Rate_Init)+Local_AudioTour_Rate_PWYW*GiftShop_Spillover))/(Local_AudioTour_Rate_PWYW*(Fee_Keep*Average_PWYW-Headset_Cost)+C$56)) | D62: =IF((Local_AudioTour_Rate_PWYW*(Fee_Keep*Average_PWYW-Headset_Cost)+D$56)<=0,"n/a",($B62/Campaign_Days-Locals_Base*(1-EXP(-$B62/Marketing_Saturation_Spend))*(Fee_Keep*(Local_AudioTour_Rate_PWYW*Average_PWYW-Local_AudioTour_Rate_Init*AudioTour_Price)-Headset_Cost*(Local_AudioTour_Rate_PWYW-Local_AudioTour_Rate_Init)+Local_AudioTour_Rate_PWYW*GiftShop_Spillover))/(Local_AudioTour_Rate_PWYW*(Fee_Keep*Average_PWYW-Headset_Cost)+D$56)) | E62: =IF((Local_AudioTour_Rate_PWYW*(Fee_Keep*Average_PWYW-Headset_Cost)+E$56)<=0,"n/a",($B62/Campaign_Days-Locals_Base*(1-EXP(-$B62/Marketing_Saturation_Spend))*(Fee_Keep*(Local_AudioTour_Rate_PWYW*Average_PWYW-Local_AudioTour_Rate_Init*AudioTour_Price)-Headset_Cost*(Local_AudioTour_Rate_PWYW-Local_AudioTour_Rate_Init)+Local_AudioTour_Rate_PWYW*GiftShop_Spillover))/(Local_AudioTour_Rate_PWYW*(Fee_Keep*Average_PWYW-Headset_Cost)+E$56)) | F62: =IF((Local_AudioTour_Rate_PWYW*(Fee_Keep*Average_PWYW-Headset_Cost)+F$56)<=0,"n/a",($B62/Campaign_Days-Locals_Base*(1-EXP(-$B62/Marketing_Saturation_Spend))*(Fee_Keep*(Local_AudioTour_Rate_PWYW*Average_PWYW-Local_AudioTour_Rate_Init*AudioTour_Price)-Headset_Cost*(Local_AudioTour_Rate_PWYW-Local_AudioTour_Rate_Init)+Local_AudioTour_Rate_PWYW*GiftShop_Spillover))/(Local_AudioTour_Rate_PWYW*(Fee_Keep*Average_PWYW-Headset_Cost)+F$56)) | G62: =IF((Local_AudioTour_Rate_PWYW*(Fee_Keep*Average_PWYW-Headset_Cost)+G$56)<=0,"n/a",($B62/Campaign_Days-Locals_Base*(1-EXP(-$B62/Marketing_Saturation_Spend))*(Fee_Keep*(Local_AudioTour_Rate_PWYW*Average_PWYW-Local_AudioTour_Rate_Init*AudioTour_Price)-Headset_Cost*(Local_AudioTour_Rate_PWYW-Local_AudioTour_Rate_Init)+Local_AudioTour_Rate_PWYW*GiftShop_Spillover))/(Local_AudioTour_Rate_PWYW*(Fee_Keep*Average_PWYW-Headset_Cost)+G$56)) | H62: =IF((Local_AudioTour_Rate_PWYW*(Fee_Keep*Average_PWYW-Headset_Cost)+H$56)<=0,"n/a",($B62/Campaign_Days-Locals_Base*(1-EXP(-$B62/Marketing_Saturation_Spend))*(Fee_Keep*(Local_AudioTour_Rate_PWYW*Average_PWYW-Local_AudioTour_Rate_Init*AudioTour_Price)-Headset_Cost*(Local_AudioTour_Rate_PWYW-Local_AudioTour_Rate_Init)+Local_AudioTour_Rate_PWYW*GiftShop_Spillover))/(Local_AudioTour_Rate_PWYW*(Fee_Keep*Average_PWYW-Headset_Cost)+H$56)) | I62: =IF((Local_AudioTour_Rate_PWYW*(Fee_Keep*Average_PWYW-Headset_Cost)+I$56)<=0,"n/a",($B62/Campaign_Days-Locals_Base*(1-EXP(-$B62/Marketing_Saturation_Spend))*(Fee_Keep*(Local_AudioTour_Rate_PWYW*Average_PWYW-Local_AudioTour_Rate_Init*AudioTour_Price)-Headset_Cost*(Local_AudioTour_Rate_PWYW-Local_AudioTour_Rate_Init)+Local_AudioTour_Rate_PWYW*GiftShop_Spillover))/(Local_AudioTour_Rate_PWYW*(Fee_Keep*Average_PWYW-Headset_Cost)+I$56))
B65: 7. BREAK-EVEN as % rise in today's local visitors
B66: Marketing ($) \ Gift shop $ / local | C66: =C$6 | D66: =D$6 | E66: =E$6 | F66: =F$6 | G66: =G$6 | H66: =H$6 | I66: =I$6
B67: =$B$7 | C67: =IF(ISNUMBER(IF((Local_AudioTour_Rate_PWYW*(Fee_Keep*Average_PWYW-Headset_Cost)+C$66)<=0,"n/a",($B67/Campaign_Days-Locals_Base*(1-EXP(-$B67/Marketing_Saturation_Spend))*(Fee_Keep*(Local_AudioTour_Rate_PWYW*Average_PWYW-Local_AudioTour_Rate_Init*AudioTour_Price)-Headset_Cost*(Local_AudioTour_Rate_PWYW-Local_AudioTour_Rate_Init)+Local_AudioTour_Rate_PWYW*GiftShop_Spillover))/(Local_AudioTour_Rate_PWYW*(Fee_Keep*Average_PWYW-Headset_Cost)+C$66))),IF((Local_AudioTour_Rate_PWYW*(Fee_Keep*Average_PWYW-Headset_Cost)+C$66)<=0,"n/a",($B67/Campaign_Days-Locals_Base*(1-EXP(-$B67/Marketing_Saturation_Spend))*(Fee_Keep*(Local_AudioTour_Rate_PWYW*Average_PWYW-Local_AudioTour_Rate_Init*AudioTour_Price)-Headset_Cost*(Local_AudioTour_Rate_PWYW-Local_AudioTour_Rate_Init)+Local_AudioTour_Rate_PWYW*GiftShop_Spillover))/(Local_AudioTour_Rate_PWYW*(Fee_Keep*Average_PWYW-Headset_Cost)+C$66))/Locals_Base,"n/a") | D67: =IF(ISNUMBER(IF((Local_AudioTour_Rate_PWYW*(Fee_Keep*Average_PWYW-Headset_Cost)+D$66)<=0,"n/a",($B67/Campaign_Days-Locals_Base*(1-EXP(-$B67/Marketing_Saturation_Spend))*(Fee_Keep*(Local_AudioTour_Rate_PWYW*Average_PWYW-Local_AudioTour_Rate_Init*AudioTour_Price)-Headset_Cost*(Local_AudioTour_Rate_PWYW-Local_AudioTour_Rate_Init)+Local_AudioTour_Rate_PWYW*GiftShop_Spillover))/(Local_AudioTour_Rate_PWYW*(Fee_Keep*Average_PWYW-Headset_Cost)+D$66))),IF((Local_AudioTour_Rate_PWYW*(Fee_Keep*Average_PWYW-Headset_Cost)+D$66)<=0,"n/a",($B67/Campaign_Days-Locals_Base*(1-EXP(-$B67/Marketing_Saturation_Spend))*(Fee_Keep*(Local_AudioTour_Rate_PWYW*Average_PWYW-Local_AudioTour_Rate_Init*AudioTour_Price)-Headset_Cost*(Local_AudioTour_Rate_PWYW-Local_AudioTour_Rate_Init)+Local_AudioTour_Rate_PWYW*GiftShop_Spillover))/(Local_AudioTour_Rate_PWYW*(Fee_Keep*Average_PWYW-Headset_Cost)+D$66))/Locals_Base,"n/a") | E67: =IF(ISNUMBER(IF((Local_AudioTour_Rate_PWYW*(Fee_Keep*Average_PWYW-Headset_Cost)+E$66)<=0,"n/a",($B67/Campaign_Days-Locals_Base*(1-EXP(-$B67/Marketing_Saturation_Spend))*(Fee_Keep*(Local_AudioTour_Rate_PWYW*Average_PWYW-Local_AudioTour_Rate_Init*AudioTour_Price)-Headset_Cost*(Local_AudioTour_Rate_PWYW-Local_AudioTour_Rate_Init)+Local_AudioTour_Rate_PWYW*GiftShop_Spillover))/(Local_AudioTour_Rate_PWYW*(Fee_Keep*Average_PWYW-Headset_Cost)+E$66))),IF((Local_AudioTour_Rate_PWYW*(Fee_Keep*Average_PWYW-Headset_Cost)+E$66)<=0,"n/a",($B67/Campaign_Days-Locals_Base*(1-EXP(-$B67/Marketing_Saturation_Spend))*(Fee_Keep*(Local_AudioTour_Rate_PWYW*Average_PWYW-Local_AudioTour_Rate_Init*AudioTour_Price)-Headset_Cost*(Local_AudioTour_Rate_PWYW-Local_AudioTour_Rate_Init)+Local_AudioTour_Rate_PWYW*GiftShop_Spillover))/(Local_AudioTour_Rate_PWYW*(Fee_Keep*Average_PWYW-Headset_Cost)+E$66))/Locals_Base,"n/a") | F67: =IF(ISNUMBER(IF((Local_AudioTour_Rate_PWYW*(Fee_Keep*Average_PWYW-Headset_Cost)+F$66)<=0,"n/a",($B67/Campaign_Days-Locals_Base*(1-EXP(-$B67/Marketing_Saturation_Spend))*(Fee_Keep*(Local_AudioTour_Rate_PWYW*Average_PWYW-Local_AudioTour_Rate_Init*AudioTour_Price)-Headset_Cost*(Local_AudioTour_Rate_PWYW-Local_AudioTour_Rate_Init)+Local_AudioTour_Rate_PWYW*GiftShop_Spillover))/(Local_AudioTour_Rate_PWYW*(Fee_Keep*Average_PWYW-Headset_Cost)+F$66))),IF((Local_AudioTour_Rate_PWYW*(Fee_Keep*Average_PWYW-Headset_Cost)+F$66)<=0,"n/a",($B67/Campaign_Days-Locals_Base*(1-EXP(-$B67/Marketing_Saturation_Spend))*(Fee_Keep*(Local_AudioTour_Rate_PWYW*Average_PWYW-Local_AudioTour_Rate_Init*AudioTour_Price)-Headset_Cost*(Local_AudioTour_Rate_PWYW-Local_AudioTour_Rate_Init)+Local_AudioTour_Rate_PWYW*GiftShop_Spillover))/(Local_AudioTour_Rate_PWYW*(Fee_Keep*Average_PWYW-Headset_Cost)+F$66))/Locals_Base,"n/a") | G67: =IF(ISNUMBER(IF((Local_AudioTour_Rate_PWYW*(Fee_Keep*Average_PWYW-Headset_Cost)+G$66)<=0,"n/a",($B67/Campaign_Days-Locals_Base*(1-EXP(-$B67/Marketing_Saturation_Spend))*(Fee_Keep*(Local_AudioTour_Rate_PWYW*Average_PWYW-Local_AudioTour_Rate_Init*AudioTour_Price)-Headset_Cost*(Local_AudioTour_Rate_PWYW-Local_AudioTour_Rate_Init)+Local_AudioTour_Rate_PWYW*GiftShop_Spillover))/(Local_AudioTour_Rate_PWYW*(Fee_Keep*Average_PWYW-Headset_Cost)+G$66))),IF((Local_AudioTour_Rate_PWYW*(Fee_Keep*Average_PWYW-Headset_Cost)+G$66)<=0,"n/a",($B67/Campaign_Days-Locals_Base*(1-EXP(-$B67/Marketing_Saturation_Spend))*(Fee_Keep*(Local_AudioTour_Rate_PWYW*Average_PWYW-Local_AudioTour_Rate_Init*AudioTour_Price)-Headset_Cost*(Local_AudioTour_Rate_PWYW-Local_AudioTour_Rate_Init)+Local_AudioTour_Rate_PWYW*GiftShop_Spillover))/(Local_AudioTour_Rate_PWYW*(Fee_Keep*Average_PWYW-Headset_Cost)+G$66))/Locals_Base,"n/a") | H67: =IF(ISNUMBER(IF((Local_AudioTour_Rate_PWYW*(Fee_Keep*Average_PWYW-Headset_Cost)+H$66)<=0,"n/a",($B67/Campaign_Days-Locals_Base*(1-EXP(-$B67/Marketing_Saturation_Spend))*(Fee_Keep*(Local_AudioTour_Rate_PWYW*Average_PWYW-Local_AudioTour_Rate_Init*AudioTour_Price)-Headset_Cost*(Local_AudioTour_Rate_PWYW-Local_AudioTour_Rate_Init)+Local_AudioTour_Rate_PWYW*GiftShop_Spillover))/(Local_AudioTour_Rate_PWYW*(Fee_Keep*Average_PWYW-Headset_Cost)+H$66))),IF((Local_AudioTour_Rate_PWYW*(Fee_Keep*Average_PWYW-Headset_Cost)+H$66)<=0,"n/a",($B67/Campaign_Days-Locals_Base*(1-EXP(-$B67/Marketing_Saturation_Spend))*(Fee_Keep*(Local_AudioTour_Rate_PWYW*Average_PWYW-Local_AudioTour_Rate_Init*AudioTour_Price)-Headset_Cost*(Local_AudioTour_Rate_PWYW-Local_AudioTour_Rate_Init)+Local_AudioTour_Rate_PWYW*GiftShop_Spillover))/(Local_AudioTour_Rate_PWYW*(Fee_Keep*Average_PWYW-Headset_Cost)+H$66))/Locals_Base,"n/a") | I67: =IF(ISNUMBER(IF((Local_AudioTour_Rate_PWYW*(Fee_Keep*Average_PWYW-Headset_Cost)+I$66)<=0,"n/a",($B67/Campaign_Days-Locals_Base*(1-EXP(-$B67/Marketing_Saturation_Spend))*(Fee_Keep*(Local_AudioTour_Rate_PWYW*Average_PWYW-Local_AudioTour_Rate_Init*AudioTour_Price)-Headset_Cost*(Local_AudioTour_Rate_PWYW-Local_AudioTour_Rate_Init)+Local_AudioTour_Rate_PWYW*GiftShop_Spillover))/(Local_AudioTour_Rate_PWYW*(Fee_Keep*Average_PWYW-Headset_Cost)+I$66))),IF((Local_AudioTour_Rate_PWYW*(Fee_Keep*Average_PWYW-Headset_Cost)+I$66)<=0,"n/a",($B67/Campaign_Days-Locals_Base*(1-EXP(-$B67/Marketing_Saturation_Spend))*(Fee_Keep*(Local_AudioTour_Rate_PWYW*Average_PWYW-Local_AudioTour_Rate_Init*AudioTour_Price)-Headset_Cost*(Local_AudioTour_Rate_PWYW-Local_AudioTour_Rate_Init)+Local_AudioTour_Rate_PWYW*GiftShop_Spillover))/(Local_AudioTour_Rate_PWYW*(Fee_Keep*Average_PWYW-Headset_Cost)+I$66))/Locals_Base,"n/a")
B68: =$B$8 | C68: =IF(ISNUMBER(IF((Local_AudioTour_Rate_PWYW*(Fee_Keep*Average_PWYW-Headset_Cost)+C$66)<=0,"n/a",($B68/Campaign_Days-Locals_Base*(1-EXP(-$B68/Marketing_Saturation_Spend))*(Fee_Keep*(Local_AudioTour_Rate_PWYW*Average_PWYW-Local_AudioTour_Rate_Init*AudioTour_Price)-Headset_Cost*(Local_AudioTour_Rate_PWYW-Local_AudioTour_Rate_Init)+Local_AudioTour_Rate_PWYW*GiftShop_Spillover))/(Local_AudioTour_Rate_PWYW*(Fee_Keep*Average_PWYW-Headset_Cost)+C$66))),IF((Local_AudioTour_Rate_PWYW*(Fee_Keep*Average_PWYW-Headset_Cost)+C$66)<=0,"n/a",($B68/Campaign_Days-Locals_Base*(1-EXP(-$B68/Marketing_Saturation_Spend))*(Fee_Keep*(Local_AudioTour_Rate_PWYW*Average_PWYW-Local_AudioTour_Rate_Init*AudioTour_Price)-Headset_Cost*(Local_AudioTour_Rate_PWYW-Local_AudioTour_Rate_Init)+Local_AudioTour_Rate_PWYW*GiftShop_Spillover))/(Local_AudioTour_Rate_PWYW*(Fee_Keep*Average_PWYW-Headset_Cost)+C$66))/Locals_Base,"n/a") | D68: =IF(ISNUMBER(IF((Local_AudioTour_Rate_PWYW*(Fee_Keep*Average_PWYW-Headset_Cost)+D$66)<=0,"n/a",($B68/Campaign_Days-Locals_Base*(1-EXP(-$B68/Marketing_Saturation_Spend))*(Fee_Keep*(Local_AudioTour_Rate_PWYW*Average_PWYW-Local_AudioTour_Rate_Init*AudioTour_Price)-Headset_Cost*(Local_AudioTour_Rate_PWYW-Local_AudioTour_Rate_Init)+Local_AudioTour_Rate_PWYW*GiftShop_Spillover))/(Local_AudioTour_Rate_PWYW*(Fee_Keep*Average_PWYW-Headset_Cost)+D$66))),IF((Local_AudioTour_Rate_PWYW*(Fee_Keep*Average_PWYW-Headset_Cost)+D$66)<=0,"n/a",($B68/Campaign_Days-Locals_Base*(1-EXP(-$B68/Marketing_Saturation_Spend))*(Fee_Keep*(Local_AudioTour_Rate_PWYW*Average_PWYW-Local_AudioTour_Rate_Init*AudioTour_Price)-Headset_Cost*(Local_AudioTour_Rate_PWYW-Local_AudioTour_Rate_Init)+Local_AudioTour_Rate_PWYW*GiftShop_Spillover))/(Local_AudioTour_Rate_PWYW*(Fee_Keep*Average_PWYW-Headset_Cost)+D$66))/Locals_Base,"n/a") | E68: =IF(ISNUMBER(IF((Local_AudioTour_Rate_PWYW*(Fee_Keep*Average_PWYW-Headset_Cost)+E$66)<=0,"n/a",($B68/Campaign_Days-Locals_Base*(1-EXP(-$B68/Marketing_Saturation_Spend))*(Fee_Keep*(Local_AudioTour_Rate_PWYW*Average_PWYW-Local_AudioTour_Rate_Init*AudioTour_Price)-Headset_Cost*(Local_AudioTour_Rate_PWYW-Local_AudioTour_Rate_Init)+Local_AudioTour_Rate_PWYW*GiftShop_Spillover))/(Local_AudioTour_Rate_PWYW*(Fee_Keep*Average_PWYW-Headset_Cost)+E$66))),IF((Local_AudioTour_Rate_PWYW*(Fee_Keep*Average_PWYW-Headset_Cost)+E$66)<=0,"n/a",($B68/Campaign_Days-Locals_Base*(1-EXP(-$B68/Marketing_Saturation_Spend))*(Fee_Keep*(Local_AudioTour_Rate_PWYW*Average_PWYW-Local_AudioTour_Rate_Init*AudioTour_Price)-Headset_Cost*(Local_AudioTour_Rate_PWYW-Local_AudioTour_Rate_Init)+Local_AudioTour_Rate_PWYW*GiftShop_Spillover))/(Local_AudioTour_Rate_PWYW*(Fee_Keep*Average_PWYW-Headset_Cost)+E$66))/Locals_Base,"n/a") | F68: =IF(ISNUMBER(IF((Local_AudioTour_Rate_PWYW*(Fee_Keep*Average_PWYW-Headset_Cost)+F$66)<=0,"n/a",($B68/Campaign_Days-Locals_Base*(1-EXP(-$B68/Marketing_Saturation_Spend))*(Fee_Keep*(Local_AudioTour_Rate_PWYW*Average_PWYW-Local_AudioTour_Rate_Init*AudioTour_Price)-Headset_Cost*(Local_AudioTour_Rate_PWYW-Local_AudioTour_Rate_Init)+Local_AudioTour_Rate_PWYW*GiftShop_Spillover))/(Local_AudioTour_Rate_PWYW*(Fee_Keep*Average_PWYW-Headset_Cost)+F$66))),IF((Local_AudioTour_Rate_PWYW*(Fee_Keep*Average_PWYW-Headset_Cost)+F$66)<=0,"n/a",($B68/Campaign_Days-Locals_Base*(1-EXP(-$B68/Marketing_Saturation_Spend))*(Fee_Keep*(Local_AudioTour_Rate_PWYW*Average_PWYW-Local_AudioTour_Rate_Init*AudioTour_Price)-Headset_Cost*(Local_AudioTour_Rate_PWYW-Local_AudioTour_Rate_Init)+Local_AudioTour_Rate_PWYW*GiftShop_Spillover))/(Local_AudioTour_Rate_PWYW*(Fee_Keep*Average_PWYW-Headset_Cost)+F$66))/Locals_Base,"n/a") | G68: =IF(ISNUMBER(IF((Local_AudioTour_Rate_PWYW*(Fee_Keep*Average_PWYW-Headset_Cost)+G$66)<=0,"n/a",($B68/Campaign_Days-Locals_Base*(1-EXP(-$B68/Marketing_Saturation_Spend))*(Fee_Keep*(Local_AudioTour_Rate_PWYW*Average_PWYW-Local_AudioTour_Rate_Init*AudioTour_Price)-Headset_Cost*(Local_AudioTour_Rate_PWYW-Local_AudioTour_Rate_Init)+Local_AudioTour_Rate_PWYW*GiftShop_Spillover))/(Local_AudioTour_Rate_PWYW*(Fee_Keep*Average_PWYW-Headset_Cost)+G$66))),IF((Local_AudioTour_Rate_PWYW*(Fee_Keep*Average_PWYW-Headset_Cost)+G$66)<=0,"n/a",($B68/Campaign_Days-Locals_Base*(1-EXP(-$B68/Marketing_Saturation_Spend))*(Fee_Keep*(Local_AudioTour_Rate_PWYW*Average_PWYW-Local_AudioTour_Rate_Init*AudioTour_Price)-Headset_Cost*(Local_AudioTour_Rate_PWYW-Local_AudioTour_Rate_Init)+Local_AudioTour_Rate_PWYW*GiftShop_Spillover))/(Local_AudioTour_Rate_PWYW*(Fee_Keep*Average_PWYW-Headset_Cost)+G$66))/Locals_Base,"n/a") | H68: =IF(ISNUMBER(IF((Local_AudioTour_Rate_PWYW*(Fee_Keep*Average_PWYW-Headset_Cost)+H$66)<=0,"n/a",($B68/Campaign_Days-Locals_Base*(1-EXP(-$B68/Marketing_Saturation_Spend))*(Fee_Keep*(Local_AudioTour_Rate_PWYW*Average_PWYW-Local_AudioTour_Rate_Init*AudioTour_Price)-Headset_Cost*(Local_AudioTour_Rate_PWYW-Local_AudioTour_Rate_Init)+Local_AudioTour_Rate_PWYW*GiftShop_Spillover))/(Local_AudioTour_Rate_PWYW*(Fee_Keep*Average_PWYW-Headset_Cost)+H$66))),IF((Local_AudioTour_Rate_PWYW*(Fee_Keep*Average_PWYW-Headset_Cost)+H$66)<=0,"n/a",($B68/Campaign_Days-Locals_Base*(1-EXP(-$B68/Marketing_Saturation_Spend))*(Fee_Keep*(Local_AudioTour_Rate_PWYW*Average_PWYW-Local_AudioTour_Rate_Init*AudioTour_Price)-Headset_Cost*(Local_AudioTour_Rate_PWYW-Local_AudioTour_Rate_Init)+Local_AudioTour_Rate_PWYW*GiftShop_Spillover))/(Local_AudioTour_Rate_PWYW*(Fee_Keep*Average_PWYW-Headset_Cost)+H$66))/Locals_Base,"n/a") | I68: =IF(ISNUMBER(IF((Local_AudioTour_Rate_PWYW*(Fee_Keep*Average_PWYW-Headset_Cost)+I$66)<=0,"n/a",($B68/Campaign_Days-Locals_Base*(1-EXP(-$B68/Marketing_Saturation_Spend))*(Fee_Keep*(Local_AudioTour_Rate_PWYW*Average_PWYW-Local_AudioTour_Rate_Init*AudioTour_Price)-Headset_Cost*(Local_AudioTour_Rate_PWYW-Local_AudioTour_Rate_Init)+Local_AudioTour_Rate_PWYW*GiftShop_Spillover))/(Local_AudioTour_Rate_PWYW*(Fee_Keep*Average_PWYW-Headset_Cost)+I$66))),IF((Local_AudioTour_Rate_PWYW*(Fee_Keep*Average_PWYW-Headset_Cost)+I$66)<=0,"n/a",($B68/Campaign_Days-Locals_Base*(1-EXP(-$B68/Marketing_Saturation_Spend))*(Fee_Keep*(Local_AudioTour_Rate_PWYW*Average_PWYW-Local_AudioTour_Rate_Init*AudioTour_Price)-Headset_Cost*(Local_AudioTour_Rate_PWYW-Local_AudioTour_Rate_Init)+Local_AudioTour_Rate_PWYW*GiftShop_Spillover))/(Local_AudioTour_Rate_PWYW*(Fee_Keep*Average_PWYW-Headset_Cost)+I$66))/Locals_Base,"n/a")
B69: =$B$9 | C69: =IF(ISNUMBER(IF((Local_AudioTour_Rate_PWYW*(Fee_Keep*Average_PWYW-Headset_Cost)+C$66)<=0,"n/a",($B69/Campaign_Days-Locals_Base*(1-EXP(-$B69/Marketing_Saturation_Spend))*(Fee_Keep*(Local_AudioTour_Rate_PWYW*Average_PWYW-Local_AudioTour_Rate_Init*AudioTour_Price)-Headset_Cost*(Local_AudioTour_Rate_PWYW-Local_AudioTour_Rate_Init)+Local_AudioTour_Rate_PWYW*GiftShop_Spillover))/(Local_AudioTour_Rate_PWYW*(Fee_Keep*Average_PWYW-Headset_Cost)+C$66))),IF((Local_AudioTour_Rate_PWYW*(Fee_Keep*Average_PWYW-Headset_Cost)+C$66)<=0,"n/a",($B69/Campaign_Days-Locals_Base*(1-EXP(-$B69/Marketing_Saturation_Spend))*(Fee_Keep*(Local_AudioTour_Rate_PWYW*Average_PWYW-Local_AudioTour_Rate_Init*AudioTour_Price)-Headset_Cost*(Local_AudioTour_Rate_PWYW-Local_AudioTour_Rate_Init)+Local_AudioTour_Rate_PWYW*GiftShop_Spillover))/(Local_AudioTour_Rate_PWYW*(Fee_Keep*Average_PWYW-Headset_Cost)+C$66))/Locals_Base,"n/a") | D69: =IF(ISNUMBER(IF((Local_AudioTour_Rate_PWYW*(Fee_Keep*Average_PWYW-Headset_Cost)+D$66)<=0,"n/a",($B69/Campaign_Days-Locals_Base*(1-EXP(-$B69/Marketing_Saturation_Spend))*(Fee_Keep*(Local_AudioTour_Rate_PWYW*Average_PWYW-Local_AudioTour_Rate_Init*AudioTour_Price)-Headset_Cost*(Local_AudioTour_Rate_PWYW-Local_AudioTour_Rate_Init)+Local_AudioTour_Rate_PWYW*GiftShop_Spillover))/(Local_AudioTour_Rate_PWYW*(Fee_Keep*Average_PWYW-Headset_Cost)+D$66))),IF((Local_AudioTour_Rate_PWYW*(Fee_Keep*Average_PWYW-Headset_Cost)+D$66)<=0,"n/a",($B69/Campaign_Days-Locals_Base*(1-EXP(-$B69/Marketing_Saturation_Spend))*(Fee_Keep*(Local_AudioTour_Rate_PWYW*Average_PWYW-Local_AudioTour_Rate_Init*AudioTour_Price)-Headset_Cost*(Local_AudioTour_Rate_PWYW-Local_AudioTour_Rate_Init)+Local_AudioTour_Rate_PWYW*GiftShop_Spillover))/(Local_AudioTour_Rate_PWYW*(Fee_Keep*Average_PWYW-Headset_Cost)+D$66))/Locals_Base,"n/a") | E69: =IF(ISNUMBER(IF((Local_AudioTour_Rate_PWYW*(Fee_Keep*Average_PWYW-Headset_Cost)+E$66)<=0,"n/a",($B69/Campaign_Days-Locals_Base*(1-EXP(-$B69/Marketing_Saturation_Spend))*(Fee_Keep*(Local_AudioTour_Rate_PWYW*Average_PWYW-Local_AudioTour_Rate_Init*AudioTour_Price)-Headset_Cost*(Local_AudioTour_Rate_PWYW-Local_AudioTour_Rate_Init)+Local_AudioTour_Rate_PWYW*GiftShop_Spillover))/(Local_AudioTour_Rate_PWYW*(Fee_Keep*Average_PWYW-Headset_Cost)+E$66))),IF((Local_AudioTour_Rate_PWYW*(Fee_Keep*Average_PWYW-Headset_Cost)+E$66)<=0,"n/a",($B69/Campaign_Days-Locals_Base*(1-EXP(-$B69/Marketing_Saturation_Spend))*(Fee_Keep*(Local_AudioTour_Rate_PWYW*Average_PWYW-Local_AudioTour_Rate_Init*AudioTour_Price)-Headset_Cost*(Local_AudioTour_Rate_PWYW-Local_AudioTour_Rate_Init)+Local_AudioTour_Rate_PWYW*GiftShop_Spillover))/(Local_AudioTour_Rate_PWYW*(Fee_Keep*Average_PWYW-Headset_Cost)+E$66))/Locals_Base,"n/a") | F69: =IF(ISNUMBER(IF((Local_AudioTour_Rate_PWYW*(Fee_Keep*Average_PWYW-Headset_Cost)+F$66)<=0,"n/a",($B69/Campaign_Days-Locals_Base*(1-EXP(-$B69/Marketing_Saturation_Spend))*(Fee_Keep*(Local_AudioTour_Rate_PWYW*Average_PWYW-Local_AudioTour_Rate_Init*AudioTour_Price)-Headset_Cost*(Local_AudioTour_Rate_PWYW-Local_AudioTour_Rate_Init)+Local_AudioTour_Rate_PWYW*GiftShop_Spillover))/(Local_AudioTour_Rate_PWYW*(Fee_Keep*Average_PWYW-Headset_Cost)+F$66))),IF((Local_AudioTour_Rate_PWYW*(Fee_Keep*Average_PWYW-Headset_Cost)+F$66)<=0,"n/a",($B69/Campaign_Days-Locals_Base*(1-EXP(-$B69/Marketing_Saturation_Spend))*(Fee_Keep*(Local_AudioTour_Rate_PWYW*Average_PWYW-Local_AudioTour_Rate_Init*AudioTour_Price)-Headset_Cost*(Local_AudioTour_Rate_PWYW-Local_AudioTour_Rate_Init)+Local_AudioTour_Rate_PWYW*GiftShop_Spillover))/(Local_AudioTour_Rate_PWYW*(Fee_Keep*Average_PWYW-Headset_Cost)+F$66))/Locals_Base,"n/a") | G69: =IF(ISNUMBER(IF((Local_AudioTour_Rate_PWYW*(Fee_Keep*Average_PWYW-Headset_Cost)+G$66)<=0,"n/a",($B69/Campaign_Days-Locals_Base*(1-EXP(-$B69/Marketing_Saturation_Spend))*(Fee_Keep*(Local_AudioTour_Rate_PWYW*Average_PWYW-Local_AudioTour_Rate_Init*AudioTour_Price)-Headset_Cost*(Local_AudioTour_Rate_PWYW-Local_AudioTour_Rate_Init)+Local_AudioTour_Rate_PWYW*GiftShop_Spillover))/(Local_AudioTour_Rate_PWYW*(Fee_Keep*Average_PWYW-Headset_Cost)+G$66))),IF((Local_AudioTour_Rate_PWYW*(Fee_Keep*Average_PWYW-Headset_Cost)+G$66)<=0,"n/a",($B69/Campaign_Days-Locals_Base*(1-EXP(-$B69/Marketing_Saturation_Spend))*(Fee_Keep*(Local_AudioTour_Rate_PWYW*Average_PWYW-Local_AudioTour_Rate_Init*AudioTour_Price)-Headset_Cost*(Local_AudioTour_Rate_PWYW-Local_AudioTour_Rate_Init)+Local_AudioTour_Rate_PWYW*GiftShop_Spillover))/(Local_AudioTour_Rate_PWYW*(Fee_Keep*Average_PWYW-Headset_Cost)+G$66))/Locals_Base,"n/a") | H69: =IF(ISNUMBER(IF((Local_AudioTour_Rate_PWYW*(Fee_Keep*Average_PWYW-Headset_Cost)+H$66)<=0,"n/a",($B69/Campaign_Days-Locals_Base*(1-EXP(-$B69/Marketing_Saturation_Spend))*(Fee_Keep*(Local_AudioTour_Rate_PWYW*Average_PWYW-Local_AudioTour_Rate_Init*AudioTour_Price)-Headset_Cost*(Local_AudioTour_Rate_PWYW-Local_AudioTour_Rate_Init)+Local_AudioTour_Rate_PWYW*GiftShop_Spillover))/(Local_AudioTour_Rate_PWYW*(Fee_Keep*Average_PWYW-Headset_Cost)+H$66))),IF((Local_AudioTour_Rate_PWYW*(Fee_Keep*Average_PWYW-Headset_Cost)+H$66)<=0,"n/a",($B69/Campaign_Days-Locals_Base*(1-EXP(-$B69/Marketing_Saturation_Spend))*(Fee_Keep*(Local_AudioTour_Rate_PWYW*Average_PWYW-Local_AudioTour_Rate_Init*AudioTour_Price)-Headset_Cost*(Local_AudioTour_Rate_PWYW-Local_AudioTour_Rate_Init)+Local_AudioTour_Rate_PWYW*GiftShop_Spillover))/(Local_AudioTour_Rate_PWYW*(Fee_Keep*Average_PWYW-Headset_Cost)+H$66))/Locals_Base,"n/a") | I69: =IF(ISNUMBER(IF((Local_AudioTour_Rate_PWYW*(Fee_Keep*Average_PWYW-Headset_Cost)+I$66)<=0,"n/a",($B69/Campaign_Days-Locals_Base*(1-EXP(-$B69/Marketing_Saturation_Spend))*(Fee_Keep*(Local_AudioTour_Rate_PWYW*Average_PWYW-Local_AudioTour_Rate_Init*AudioTour_Price)-Headset_Cost*(Local_AudioTour_Rate_PWYW-Local_AudioTour_Rate_Init)+Local_AudioTour_Rate_PWYW*GiftShop_Spillover))/(Local_AudioTour_Rate_PWYW*(Fee_Keep*Average_PWYW-Headset_Cost)+I$66))),IF((Local_AudioTour_Rate_PWYW*(Fee_Keep*Average_PWYW-Headset_Cost)+I$66)<=0,"n/a",($B69/Campaign_Days-Locals_Base*(1-EXP(-$B69/Marketing_Saturation_Spend))*(Fee_Keep*(Local_AudioTour_Rate_PWYW*Average_PWYW-Local_AudioTour_Rate_Init*AudioTour_Price)-Headset_Cost*(Local_AudioTour_Rate_PWYW-Local_AudioTour_Rate_Init)+Local_AudioTour_Rate_PWYW*GiftShop_Spillover))/(Local_AudioTour_Rate_PWYW*(Fee_Keep*Average_PWYW-Headset_Cost)+I$66))/Locals_Base,"n/a")
B70: =$B$10 | C70: =IF(ISNUMBER(IF((Local_AudioTour_Rate_PWYW*(Fee_Keep*Average_PWYW-Headset_Cost)+C$66)<=0,"n/a",($B70/Campaign_Days-Locals_Base*(1-EXP(-$B70/Marketing_Saturation_Spend))*(Fee_Keep*(Local_AudioTour_Rate_PWYW*Average_PWYW-Local_AudioTour_Rate_Init*AudioTour_Price)-Headset_Cost*(Local_AudioTour_Rate_PWYW-Local_AudioTour_Rate_Init)+Local_AudioTour_Rate_PWYW*GiftShop_Spillover))/(Local_AudioTour_Rate_PWYW*(Fee_Keep*Average_PWYW-Headset_Cost)+C$66))),IF((Local_AudioTour_Rate_PWYW*(Fee_Keep*Average_PWYW-Headset_Cost)+C$66)<=0,"n/a",($B70/Campaign_Days-Locals_Base*(1-EXP(-$B70/Marketing_Saturation_Spend))*(Fee_Keep*(Local_AudioTour_Rate_PWYW*Average_PWYW-Local_AudioTour_Rate_Init*AudioTour_Price)-Headset_Cost*(Local_AudioTour_Rate_PWYW-Local_AudioTour_Rate_Init)+Local_AudioTour_Rate_PWYW*GiftShop_Spillover))/(Local_AudioTour_Rate_PWYW*(Fee_Keep*Average_PWYW-Headset_Cost)+C$66))/Locals_Base,"n/a") | D70: =IF(ISNUMBER(IF((Local_AudioTour_Rate_PWYW*(Fee_Keep*Average_PWYW-Headset_Cost)+D$66)<=0,"n/a",($B70/Campaign_Days-Locals_Base*(1-EXP(-$B70/Marketing_Saturation_Spend))*(Fee_Keep*(Local_AudioTour_Rate_PWYW*Average_PWYW-Local_AudioTour_Rate_Init*AudioTour_Price)-Headset_Cost*(Local_AudioTour_Rate_PWYW-Local_AudioTour_Rate_Init)+Local_AudioTour_Rate_PWYW*GiftShop_Spillover))/(Local_AudioTour_Rate_PWYW*(Fee_Keep*Average_PWYW-Headset_Cost)+D$66))),IF((Local_AudioTour_Rate_PWYW*(Fee_Keep*Average_PWYW-Headset_Cost)+D$66)<=0,"n/a",($B70/Campaign_Days-Locals_Base*(1-EXP(-$B70/Marketing_Saturation_Spend))*(Fee_Keep*(Local_AudioTour_Rate_PWYW*Average_PWYW-Local_AudioTour_Rate_Init*AudioTour_Price)-Headset_Cost*(Local_AudioTour_Rate_PWYW-Local_AudioTour_Rate_Init)+Local_AudioTour_Rate_PWYW*GiftShop_Spillover))/(Local_AudioTour_Rate_PWYW*(Fee_Keep*Average_PWYW-Headset_Cost)+D$66))/Locals_Base,"n/a") | E70: =IF(ISNUMBER(IF((Local_AudioTour_Rate_PWYW*(Fee_Keep*Average_PWYW-Headset_Cost)+E$66)<=0,"n/a",($B70/Campaign_Days-Locals_Base*(1-EXP(-$B70/Marketing_Saturation_Spend))*(Fee_Keep*(Local_AudioTour_Rate_PWYW*Average_PWYW-Local_AudioTour_Rate_Init*AudioTour_Price)-Headset_Cost*(Local_AudioTour_Rate_PWYW-Local_AudioTour_Rate_Init)+Local_AudioTour_Rate_PWYW*GiftShop_Spillover))/(Local_AudioTour_Rate_PWYW*(Fee_Keep*Average_PWYW-Headset_Cost)+E$66))),IF((Local_AudioTour_Rate_PWYW*(Fee_Keep*Average_PWYW-Headset_Cost)+E$66)<=0,"n/a",($B70/Campaign_Days-Locals_Base*(1-EXP(-$B70/Marketing_Saturation_Spend))*(Fee_Keep*(Local_AudioTour_Rate_PWYW*Average_PWYW-Local_AudioTour_Rate_Init*AudioTour_Price)-Headset_Cost*(Local_AudioTour_Rate_PWYW-Local_AudioTour_Rate_Init)+Local_AudioTour_Rate_PWYW*GiftShop_Spillover))/(Local_AudioTour_Rate_PWYW*(Fee_Keep*Average_PWYW-Headset_Cost)+E$66))/Locals_Base,"n/a") | F70: =IF(ISNUMBER(IF((Local_AudioTour_Rate_PWYW*(Fee_Keep*Average_PWYW-Headset_Cost)+F$66)<=0,"n/a",($B70/Campaign_Days-Locals_Base*(1-EXP(-$B70/Marketing_Saturation_Spend))*(Fee_Keep*(Local_AudioTour_Rate_PWYW*Average_PWYW-Local_AudioTour_Rate_Init*AudioTour_Price)-Headset_Cost*(Local_AudioTour_Rate_PWYW-Local_AudioTour_Rate_Init)+Local_AudioTour_Rate_PWYW*GiftShop_Spillover))/(Local_AudioTour_Rate_PWYW*(Fee_Keep*Average_PWYW-Headset_Cost)+F$66))),IF((Local_AudioTour_Rate_PWYW*(Fee_Keep*Average_PWYW-Headset_Cost)+F$66)<=0,"n/a",($B70/Campaign_Days-Locals_Base*(1-EXP(-$B70/Marketing_Saturation_Spend))*(Fee_Keep*(Local_AudioTour_Rate_PWYW*Average_PWYW-Local_AudioTour_Rate_Init*AudioTour_Price)-Headset_Cost*(Local_AudioTour_Rate_PWYW-Local_AudioTour_Rate_Init)+Local_AudioTour_Rate_PWYW*GiftShop_Spillover))/(Local_AudioTour_Rate_PWYW*(Fee_Keep*Average_PWYW-Headset_Cost)+F$66))/Locals_Base,"n/a") | G70: =IF(ISNUMBER(IF((Local_AudioTour_Rate_PWYW*(Fee_Keep*Average_PWYW-Headset_Cost)+G$66)<=0,"n/a",($B70/Campaign_Days-Locals_Base*(1-EXP(-$B70/Marketing_Saturation_Spend))*(Fee_Keep*(Local_AudioTour_Rate_PWYW*Average_PWYW-Local_AudioTour_Rate_Init*AudioTour_Price)-Headset_Cost*(Local_AudioTour_Rate_PWYW-Local_AudioTour_Rate_Init)+Local_AudioTour_Rate_PWYW*GiftShop_Spillover))/(Local_AudioTour_Rate_PWYW*(Fee_Keep*Average_PWYW-Headset_Cost)+G$66))),IF((Local_AudioTour_Rate_PWYW*(Fee_Keep*Average_PWYW-Headset_Cost)+G$66)<=0,"n/a",($B70/Campaign_Days-Locals_Base*(1-EXP(-$B70/Marketing_Saturation_Spend))*(Fee_Keep*(Local_AudioTour_Rate_PWYW*Average_PWYW-Local_AudioTour_Rate_Init*AudioTour_Price)-Headset_Cost*(Local_AudioTour_Rate_PWYW-Local_AudioTour_Rate_Init)+Local_AudioTour_Rate_PWYW*GiftShop_Spillover))/(Local_AudioTour_Rate_PWYW*(Fee_Keep*Average_PWYW-Headset_Cost)+G$66))/Locals_Base,"n/a") | H70: =IF(ISNUMBER(IF((Local_AudioTour_Rate_PWYW*(Fee_Keep*Average_PWYW-Headset_Cost)+H$66)<=0,"n/a",($B70/Campaign_Days-Locals_Base*(1-EXP(-$B70/Marketing_Saturation_Spend))*(Fee_Keep*(Local_AudioTour_Rate_PWYW*Average_PWYW-Local_AudioTour_Rate_Init*AudioTour_Price)-Headset_Cost*(Local_AudioTour_Rate_PWYW-Local_AudioTour_Rate_Init)+Local_AudioTour_Rate_PWYW*GiftShop_Spillover))/(Local_AudioTour_Rate_PWYW*(Fee_Keep*Average_PWYW-Headset_Cost)+H$66))),IF((Local_AudioTour_Rate_PWYW*(Fee_Keep*Average_PWYW-Headset_Cost)+H$66)<=0,"n/a",($B70/Campaign_Days-Locals_Base*(1-EXP(-$B70/Marketing_Saturation_Spend))*(Fee_Keep*(Local_AudioTour_Rate_PWYW*Average_PWYW-Local_AudioTour_Rate_Init*AudioTour_Price)-Headset_Cost*(Local_AudioTour_Rate_PWYW-Local_AudioTour_Rate_Init)+Local_AudioTour_Rate_PWYW*GiftShop_Spillover))/(Local_AudioTour_Rate_PWYW*(Fee_Keep*Average_PWYW-Headset_Cost)+H$66))/Locals_Base,"n/a") | I70: =IF(ISNUMBER(IF((Local_AudioTour_Rate_PWYW*(Fee_Keep*Average_PWYW-Headset_Cost)+I$66)<=0,"n/a",($B70/Campaign_Days-Locals_Base*(1-EXP(-$B70/Marketing_Saturation_Spend))*(Fee_Keep*(Local_AudioTour_Rate_PWYW*Average_PWYW-Local_AudioTour_Rate_Init*AudioTour_Price)-Headset_Cost*(Local_AudioTour_Rate_PWYW-Local_AudioTour_Rate_Init)+Local_AudioTour_Rate_PWYW*GiftShop_Spillover))/(Local_AudioTour_Rate_PWYW*(Fee_Keep*Average_PWYW-Headset_Cost)+I$66))),IF((Local_AudioTour_Rate_PWYW*(Fee_Keep*Average_PWYW-Headset_Cost)+I$66)<=0,"n/a",($B70/Campaign_Days-Locals_Base*(1-EXP(-$B70/Marketing_Saturation_Spend))*(Fee_Keep*(Local_AudioTour_Rate_PWYW*Average_PWYW-Local_AudioTour_Rate_Init*AudioTour_Price)-Headset_Cost*(Local_AudioTour_Rate_PWYW-Local_AudioTour_Rate_Init)+Local_AudioTour_Rate_PWYW*GiftShop_Spillover))/(Local_AudioTour_Rate_PWYW*(Fee_Keep*Average_PWYW-Headset_Cost)+I$66))/Locals_Base,"n/a")
B71: =$B$11 | C71: =IF(ISNUMBER(IF((Local_AudioTour_Rate_PWYW*(Fee_Keep*Average_PWYW-Headset_Cost)+C$66)<=0,"n/a",($B71/Campaign_Days-Locals_Base*(1-EXP(-$B71/Marketing_Saturation_Spend))*(Fee_Keep*(Local_AudioTour_Rate_PWYW*Average_PWYW-Local_AudioTour_Rate_Init*AudioTour_Price)-Headset_Cost*(Local_AudioTour_Rate_PWYW-Local_AudioTour_Rate_Init)+Local_AudioTour_Rate_PWYW*GiftShop_Spillover))/(Local_AudioTour_Rate_PWYW*(Fee_Keep*Average_PWYW-Headset_Cost)+C$66))),IF((Local_AudioTour_Rate_PWYW*(Fee_Keep*Average_PWYW-Headset_Cost)+C$66)<=0,"n/a",($B71/Campaign_Days-Locals_Base*(1-EXP(-$B71/Marketing_Saturation_Spend))*(Fee_Keep*(Local_AudioTour_Rate_PWYW*Average_PWYW-Local_AudioTour_Rate_Init*AudioTour_Price)-Headset_Cost*(Local_AudioTour_Rate_PWYW-Local_AudioTour_Rate_Init)+Local_AudioTour_Rate_PWYW*GiftShop_Spillover))/(Local_AudioTour_Rate_PWYW*(Fee_Keep*Average_PWYW-Headset_Cost)+C$66))/Locals_Base,"n/a") | D71: =IF(ISNUMBER(IF((Local_AudioTour_Rate_PWYW*(Fee_Keep*Average_PWYW-Headset_Cost)+D$66)<=0,"n/a",($B71/Campaign_Days-Locals_Base*(1-EXP(-$B71/Marketing_Saturation_Spend))*(Fee_Keep*(Local_AudioTour_Rate_PWYW*Average_PWYW-Local_AudioTour_Rate_Init*AudioTour_Price)-Headset_Cost*(Local_AudioTour_Rate_PWYW-Local_AudioTour_Rate_Init)+Local_AudioTour_Rate_PWYW*GiftShop_Spillover))/(Local_AudioTour_Rate_PWYW*(Fee_Keep*Average_PWYW-Headset_Cost)+D$66))),IF((Local_AudioTour_Rate_PWYW*(Fee_Keep*Average_PWYW-Headset_Cost)+D$66)<=0,"n/a",($B71/Campaign_Days-Locals_Base*(1-EXP(-$B71/Marketing_Saturation_Spend))*(Fee_Keep*(Local_AudioTour_Rate_PWYW*Average_PWYW-Local_AudioTour_Rate_Init*AudioTour_Price)-Headset_Cost*(Local_AudioTour_Rate_PWYW-Local_AudioTour_Rate_Init)+Local_AudioTour_Rate_PWYW*GiftShop_Spillover))/(Local_AudioTour_Rate_PWYW*(Fee_Keep*Average_PWYW-Headset_Cost)+D$66))/Locals_Base,"n/a") | E71: =IF(ISNUMBER(IF((Local_AudioTour_Rate_PWYW*(Fee_Keep*Average_PWYW-Headset_Cost)+E$66)<=0,"n/a",($B71/Campaign_Days-Locals_Base*(1-EXP(-$B71/Marketing_Saturation_Spend))*(Fee_Keep*(Local_AudioTour_Rate_PWYW*Average_PWYW-Local_AudioTour_Rate_Init*AudioTour_Price)-Headset_Cost*(Local_AudioTour_Rate_PWYW-Local_AudioTour_Rate_Init)+Local_AudioTour_Rate_PWYW*GiftShop_Spillover))/(Local_AudioTour_Rate_PWYW*(Fee_Keep*Average_PWYW-Headset_Cost)+E$66))),IF((Local_AudioTour_Rate_PWYW*(Fee_Keep*Average_PWYW-Headset_Cost)+E$66)<=0,"n/a",($B71/Campaign_Days-Locals_Base*(1-EXP(-$B71/Marketing_Saturation_Spend))*(Fee_Keep*(Local_AudioTour_Rate_PWYW*Average_PWYW-Local_AudioTour_Rate_Init*AudioTour_Price)-Headset_Cost*(Local_AudioTour_Rate_PWYW-Local_AudioTour_Rate_Init)+Local_AudioTour_Rate_PWYW*GiftShop_Spillover))/(Local_AudioTour_Rate_PWYW*(Fee_Keep*Average_PWYW-Headset_Cost)+E$66))/Locals_Base,"n/a") | F71: =IF(ISNUMBER(IF((Local_AudioTour_Rate_PWYW*(Fee_Keep*Average_PWYW-Headset_Cost)+F$66)<=0,"n/a",($B71/Campaign_Days-Locals_Base*(1-EXP(-$B71/Marketing_Saturation_Spend))*(Fee_Keep*(Local_AudioTour_Rate_PWYW*Average_PWYW-Local_AudioTour_Rate_Init*AudioTour_Price)-Headset_Cost*(Local_AudioTour_Rate_PWYW-Local_AudioTour_Rate_Init)+Local_AudioTour_Rate_PWYW*GiftShop_Spillover))/(Local_AudioTour_Rate_PWYW*(Fee_Keep*Average_PWYW-Headset_Cost)+F$66))),IF((Local_AudioTour_Rate_PWYW*(Fee_Keep*Average_PWYW-Headset_Cost)+F$66)<=0,"n/a",($B71/Campaign_Days-Locals_Base*(1-EXP(-$B71/Marketing_Saturation_Spend))*(Fee_Keep*(Local_AudioTour_Rate_PWYW*Average_PWYW-Local_AudioTour_Rate_Init*AudioTour_Price)-Headset_Cost*(Local_AudioTour_Rate_PWYW-Local_AudioTour_Rate_Init)+Local_AudioTour_Rate_PWYW*GiftShop_Spillover))/(Local_AudioTour_Rate_PWYW*(Fee_Keep*Average_PWYW-Headset_Cost)+F$66))/Locals_Base,"n/a") | G71: =IF(ISNUMBER(IF((Local_AudioTour_Rate_PWYW*(Fee_Keep*Average_PWYW-Headset_Cost)+G$66)<=0,"n/a",($B71/Campaign_Days-Locals_Base*(1-EXP(-$B71/Marketing_Saturation_Spend))*(Fee_Keep*(Local_AudioTour_Rate_PWYW*Average_PWYW-Local_AudioTour_Rate_Init*AudioTour_Price)-Headset_Cost*(Local_AudioTour_Rate_PWYW-Local_AudioTour_Rate_Init)+Local_AudioTour_Rate_PWYW*GiftShop_Spillover))/(Local_AudioTour_Rate_PWYW*(Fee_Keep*Average_PWYW-Headset_Cost)+G$66))),IF((Local_AudioTour_Rate_PWYW*(Fee_Keep*Average_PWYW-Headset_Cost)+G$66)<=0,"n/a",($B71/Campaign_Days-Locals_Base*(1-EXP(-$B71/Marketing_Saturation_Spend))*(Fee_Keep*(Local_AudioTour_Rate_PWYW*Average_PWYW-Local_AudioTour_Rate_Init*AudioTour_Price)-Headset_Cost*(Local_AudioTour_Rate_PWYW-Local_AudioTour_Rate_Init)+Local_AudioTour_Rate_PWYW*GiftShop_Spillover))/(Local_AudioTour_Rate_PWYW*(Fee_Keep*Average_PWYW-Headset_Cost)+G$66))/Locals_Base,"n/a") | H71: =IF(ISNUMBER(IF((Local_AudioTour_Rate_PWYW*(Fee_Keep*Average_PWYW-Headset_Cost)+H$66)<=0,"n/a",($B71/Campaign_Days-Locals_Base*(1-EXP(-$B71/Marketing_Saturation_Spend))*(Fee_Keep*(Local_AudioTour_Rate_PWYW*Average_PWYW-Local_AudioTour_Rate_Init*AudioTour_Price)-Headset_Cost*(Local_AudioTour_Rate_PWYW-Local_AudioTour_Rate_Init)+Local_AudioTour_Rate_PWYW*GiftShop_Spillover))/(Local_AudioTour_Rate_PWYW*(Fee_Keep*Average_PWYW-Headset_Cost)+H$66))),IF((Local_AudioTour_Rate_PWYW*(Fee_Keep*Average_PWYW-Headset_Cost)+H$66)<=0,"n/a",($B71/Campaign_Days-Locals_Base*(1-EXP(-$B71/Marketing_Saturation_Spend))*(Fee_Keep*(Local_AudioTour_Rate_PWYW*Average_PWYW-Local_AudioTour_Rate_Init*AudioTour_Price)-Headset_Cost*(Local_AudioTour_Rate_PWYW-Local_AudioTour_Rate_Init)+Local_AudioTour_Rate_PWYW*GiftShop_Spillover))/(Local_AudioTour_Rate_PWYW*(Fee_Keep*Average_PWYW-Headset_Cost)+H$66))/Locals_Base,"n/a") | I71: =IF(ISNUMBER(IF((Local_AudioTour_Rate_PWYW*(Fee_Keep*Average_PWYW-Headset_Cost)+I$66)<=0,"n/a",($B71/Campaign_Days-Locals_Base*(1-EXP(-$B71/Marketing_Saturation_Spend))*(Fee_Keep*(Local_AudioTour_Rate_PWYW*Average_PWYW-Local_AudioTour_Rate_Init*AudioTour_Price)-Headset_Cost*(Local_AudioTour_Rate_PWYW-Local_AudioTour_Rate_Init)+Local_AudioTour_Rate_PWYW*GiftShop_Spillover))/(Local_AudioTour_Rate_PWYW*(Fee_Keep*Average_PWYW-Headset_Cost)+I$66))),IF((Local_AudioTour_Rate_PWYW*(Fee_Keep*Average_PWYW-Headset_Cost)+I$66)<=0,"n/a",($B71/Campaign_Days-Locals_Base*(1-EXP(-$B71/Marketing_Saturation_Spend))*(Fee_Keep*(Local_AudioTour_Rate_PWYW*Average_PWYW-Local_AudioTour_Rate_Init*AudioTour_Price)-Headset_Cost*(Local_AudioTour_Rate_PWYW-Local_AudioTour_Rate_Init)+Local_AudioTour_Rate_PWYW*GiftShop_Spillover))/(Local_AudioTour_Rate_PWYW*(Fee_Keep*Average_PWYW-Headset_Cost)+I$66))/Locals_Base,"n/a")
B72: =$B$12 | C72: =IF(ISNUMBER(IF((Local_AudioTour_Rate_PWYW*(Fee_Keep*Average_PWYW-Headset_Cost)+C$66)<=0,"n/a",($B72/Campaign_Days-Locals_Base*(1-EXP(-$B72/Marketing_Saturation_Spend))*(Fee_Keep*(Local_AudioTour_Rate_PWYW*Average_PWYW-Local_AudioTour_Rate_Init*AudioTour_Price)-Headset_Cost*(Local_AudioTour_Rate_PWYW-Local_AudioTour_Rate_Init)+Local_AudioTour_Rate_PWYW*GiftShop_Spillover))/(Local_AudioTour_Rate_PWYW*(Fee_Keep*Average_PWYW-Headset_Cost)+C$66))),IF((Local_AudioTour_Rate_PWYW*(Fee_Keep*Average_PWYW-Headset_Cost)+C$66)<=0,"n/a",($B72/Campaign_Days-Locals_Base*(1-EXP(-$B72/Marketing_Saturation_Spend))*(Fee_Keep*(Local_AudioTour_Rate_PWYW*Average_PWYW-Local_AudioTour_Rate_Init*AudioTour_Price)-Headset_Cost*(Local_AudioTour_Rate_PWYW-Local_AudioTour_Rate_Init)+Local_AudioTour_Rate_PWYW*GiftShop_Spillover))/(Local_AudioTour_Rate_PWYW*(Fee_Keep*Average_PWYW-Headset_Cost)+C$66))/Locals_Base,"n/a") | D72: =IF(ISNUMBER(IF((Local_AudioTour_Rate_PWYW*(Fee_Keep*Average_PWYW-Headset_Cost)+D$66)<=0,"n/a",($B72/Campaign_Days-Locals_Base*(1-EXP(-$B72/Marketing_Saturation_Spend))*(Fee_Keep*(Local_AudioTour_Rate_PWYW*Average_PWYW-Local_AudioTour_Rate_Init*AudioTour_Price)-Headset_Cost*(Local_AudioTour_Rate_PWYW-Local_AudioTour_Rate_Init)+Local_AudioTour_Rate_PWYW*GiftShop_Spillover))/(Local_AudioTour_Rate_PWYW*(Fee_Keep*Average_PWYW-Headset_Cost)+D$66))),IF((Local_AudioTour_Rate_PWYW*(Fee_Keep*Average_PWYW-Headset_Cost)+D$66)<=0,"n/a",($B72/Campaign_Days-Locals_Base*(1-EXP(-$B72/Marketing_Saturation_Spend))*(Fee_Keep*(Local_AudioTour_Rate_PWYW*Average_PWYW-Local_AudioTour_Rate_Init*AudioTour_Price)-Headset_Cost*(Local_AudioTour_Rate_PWYW-Local_AudioTour_Rate_Init)+Local_AudioTour_Rate_PWYW*GiftShop_Spillover))/(Local_AudioTour_Rate_PWYW*(Fee_Keep*Average_PWYW-Headset_Cost)+D$66))/Locals_Base,"n/a") | E72: =IF(ISNUMBER(IF((Local_AudioTour_Rate_PWYW*(Fee_Keep*Average_PWYW-Headset_Cost)+E$66)<=0,"n/a",($B72/Campaign_Days-Locals_Base*(1-EXP(-$B72/Marketing_Saturation_Spend))*(Fee_Keep*(Local_AudioTour_Rate_PWYW*Average_PWYW-Local_AudioTour_Rate_Init*AudioTour_Price)-Headset_Cost*(Local_AudioTour_Rate_PWYW-Local_AudioTour_Rate_Init)+Local_AudioTour_Rate_PWYW*GiftShop_Spillover))/(Local_AudioTour_Rate_PWYW*(Fee_Keep*Average_PWYW-Headset_Cost)+E$66))),IF((Local_AudioTour_Rate_PWYW*(Fee_Keep*Average_PWYW-Headset_Cost)+E$66)<=0,"n/a",($B72/Campaign_Days-Locals_Base*(1-EXP(-$B72/Marketing_Saturation_Spend))*(Fee_Keep*(Local_AudioTour_Rate_PWYW*Average_PWYW-Local_AudioTour_Rate_Init*AudioTour_Price)-Headset_Cost*(Local_AudioTour_Rate_PWYW-Local_AudioTour_Rate_Init)+Local_AudioTour_Rate_PWYW*GiftShop_Spillover))/(Local_AudioTour_Rate_PWYW*(Fee_Keep*Average_PWYW-Headset_Cost)+E$66))/Locals_Base,"n/a") | F72: =IF(ISNUMBER(IF((Local_AudioTour_Rate_PWYW*(Fee_Keep*Average_PWYW-Headset_Cost)+F$66)<=0,"n/a",($B72/Campaign_Days-Locals_Base*(1-EXP(-$B72/Marketing_Saturation_Spend))*(Fee_Keep*(Local_AudioTour_Rate_PWYW*Average_PWYW-Local_AudioTour_Rate_Init*AudioTour_Price)-Headset_Cost*(Local_AudioTour_Rate_PWYW-Local_AudioTour_Rate_Init)+Local_AudioTour_Rate_PWYW*GiftShop_Spillover))/(Local_AudioTour_Rate_PWYW*(Fee_Keep*Average_PWYW-Headset_Cost)+F$66))),IF((Local_AudioTour_Rate_PWYW*(Fee_Keep*Average_PWYW-Headset_Cost)+F$66)<=0,"n/a",($B72/Campaign_Days-Locals_Base*(1-EXP(-$B72/Marketing_Saturation_Spend))*(Fee_Keep*(Local_AudioTour_Rate_PWYW*Average_PWYW-Local_AudioTour_Rate_Init*AudioTour_Price)-Headset_Cost*(Local_AudioTour_Rate_PWYW-Local_AudioTour_Rate_Init)+Local_AudioTour_Rate_PWYW*GiftShop_Spillover))/(Local_AudioTour_Rate_PWYW*(Fee_Keep*Average_PWYW-Headset_Cost)+F$66))/Locals_Base,"n/a") | G72: =IF(ISNUMBER(IF((Local_AudioTour_Rate_PWYW*(Fee_Keep*Average_PWYW-Headset_Cost)+G$66)<=0,"n/a",($B72/Campaign_Days-Locals_Base*(1-EXP(-$B72/Marketing_Saturation_Spend))*(Fee_Keep*(Local_AudioTour_Rate_PWYW*Average_PWYW-Local_AudioTour_Rate_Init*AudioTour_Price)-Headset_Cost*(Local_AudioTour_Rate_PWYW-Local_AudioTour_Rate_Init)+Local_AudioTour_Rate_PWYW*GiftShop_Spillover))/(Local_AudioTour_Rate_PWYW*(Fee_Keep*Average_PWYW-Headset_Cost)+G$66))),IF((Local_AudioTour_Rate_PWYW*(Fee_Keep*Average_PWYW-Headset_Cost)+G$66)<=0,"n/a",($B72/Campaign_Days-Locals_Base*(1-EXP(-$B72/Marketing_Saturation_Spend))*(Fee_Keep*(Local_AudioTour_Rate_PWYW*Average_PWYW-Local_AudioTour_Rate_Init*AudioTour_Price)-Headset_Cost*(Local_AudioTour_Rate_PWYW-Local_AudioTour_Rate_Init)+Local_AudioTour_Rate_PWYW*GiftShop_Spillover))/(Local_AudioTour_Rate_PWYW*(Fee_Keep*Average_PWYW-Headset_Cost)+G$66))/Locals_Base,"n/a") | H72: =IF(ISNUMBER(IF((Local_AudioTour_Rate_PWYW*(Fee_Keep*Average_PWYW-Headset_Cost)+H$66)<=0,"n/a",($B72/Campaign_Days-Locals_Base*(1-EXP(-$B72/Marketing_Saturation_Spend))*(Fee_Keep*(Local_AudioTour_Rate_PWYW*Average_PWYW-Local_AudioTour_Rate_Init*AudioTour_Price)-Headset_Cost*(Local_AudioTour_Rate_PWYW-Local_AudioTour_Rate_Init)+Local_AudioTour_Rate_PWYW*GiftShop_Spillover))/(Local_AudioTour_Rate_PWYW*(Fee_Keep*Average_PWYW-Headset_Cost)+H$66))),IF((Local_AudioTour_Rate_PWYW*(Fee_Keep*Average_PWYW-Headset_Cost)+H$66)<=0,"n/a",($B72/Campaign_Days-Locals_Base*(1-EXP(-$B72/Marketing_Saturation_Spend))*(Fee_Keep*(Local_AudioTour_Rate_PWYW*Average_PWYW-Local_AudioTour_Rate_Init*AudioTour_Price)-Headset_Cost*(Local_AudioTour_Rate_PWYW-Local_AudioTour_Rate_Init)+Local_AudioTour_Rate_PWYW*GiftShop_Spillover))/(Local_AudioTour_Rate_PWYW*(Fee_Keep*Average_PWYW-Headset_Cost)+H$66))/Locals_Base,"n/a") | I72: =IF(ISNUMBER(IF((Local_AudioTour_Rate_PWYW*(Fee_Keep*Average_PWYW-Headset_Cost)+I$66)<=0,"n/a",($B72/Campaign_Days-Locals_Base*(1-EXP(-$B72/Marketing_Saturation_Spend))*(Fee_Keep*(Local_AudioTour_Rate_PWYW*Average_PWYW-Local_AudioTour_Rate_Init*AudioTour_Price)-Headset_Cost*(Local_AudioTour_Rate_PWYW-Local_AudioTour_Rate_Init)+Local_AudioTour_Rate_PWYW*GiftShop_Spillover))/(Local_AudioTour_Rate_PWYW*(Fee_Keep*Average_PWYW-Headset_Cost)+I$66))),IF((Local_AudioTour_Rate_PWYW*(Fee_Keep*Average_PWYW-Headset_Cost)+I$66)<=0,"n/a",($B72/Campaign_Days-Locals_Base*(1-EXP(-$B72/Marketing_Saturation_Spend))*(Fee_Keep*(Local_AudioTour_Rate_PWYW*Average_PWYW-Local_AudioTour_Rate_Init*AudioTour_Price)-Headset_Cost*(Local_AudioTour_Rate_PWYW-Local_AudioTour_Rate_Init)+Local_AudioTour_Rate_PWYW*GiftShop_Spillover))/(Local_AudioTour_Rate_PWYW*(Fee_Keep*Average_PWYW-Headset_Cost)+I$66))/Locals_Base,"n/a")

Sheet Engine
A1: Scenario | B1: Marketing | C1: Ceiling | D1: GiftShop | E1: Avg PWYW | F1: Take-up | G1: Final share | H1: Local visitors | I1: Added locals | J1: Local audio users | K1: Total audio users | L1: Device blocks | M1: Device $/day | N1: Audio rev chg | O1: Headset chg | P1: Gift shop chg | Q1: Daily contribution | R1: Net profit | T1: One row per sensitivity scenario. Lever columns B-F come from the Sensitivity axes or the Model inputs.
A2: Base case | B2: =Marketing_Spend | C2: =Locals_Share_Ceiling | D2: =GiftShop_Net_Spend_Local | E2: =Average_PWYW | F2: =Local_AudioTour_Rate_PWYW | G2: =Percentage_Locals_Init+(C2-Percentage_Locals_Init)*(1-EXP(-B2/Marketing_Saturation_Spend)) | H2: =Tourists_Base*G2/(1-G2) | I2: =H2-Locals_Base | J2: =Locals_Base*(1-(1-EXP(-B2/Marketing_Saturation_Spend)))*Local_AudioTour_Rate_Init+(H2-Locals_Base*(1-(1-EXP(-B2/Marketing_Saturation_Spend))))*F2 | K2: =AudioTourist_Base+J2 | L2: =MAX(0,ROUNDUP((K2-Device_Capacity)/Device_Block_Size,0)) | M2: =L2*Device_Block_Cost/Device_Amort_Days | N2: =Fee_Keep*(Locals_Base*(1-(1-EXP(-B2/Marketing_Saturation_Spend)))*Local_AudioTour_Rate_Init*AudioTour_Price+(H2-Locals_Base*(1-(1-EXP(-B2/Marketing_Saturation_Spend))))*F2*E2-AudioLocal_Base*AudioTour_Price) | O2: =(K2-Total_Daily_AudioTour)*Headset_Cost | P2: =I2*D2+Locals_Base*(1-EXP(-B2/Marketing_Saturation_Spend))*F2*GiftShop_Spillover | Q2: =N2-O2-M2+P2 | R2: =Q2*Campaign_Days-B2
A3: Zero-marketing test | B3: =0 | C3: =Locals_Share_Ceiling | D3: =GiftShop_Net_Spend_Local | E3: =Average_PWYW | F3: =Local_AudioTour_Rate_PWYW | G3: =Percentage_Locals_Init+(C3-Percentage_Locals_Init)*(1-EXP(-B3/Marketing_Saturation_Spend)) | H3: =Tourists_Base*G3/(1-G3) | I3: =H3-Locals_Base | J3: =Locals_Base*(1-(1-EXP(-B3/Marketing_Saturation_Spend)))*Local_AudioTour_Rate_Init+(H3-Locals_Base*(1-(1-EXP(-B3/Marketing_Saturation_Spend))))*F3 | K3: =AudioTourist_Base+J3 | L3: =MAX(0,ROUNDUP((K3-Device_Capacity)/Device_Block_Size,0)) | M3: =L3*Device_Block_Cost/Device_Amort_Days | N3: =Fee_Keep*(Locals_Base*(1-(1-EXP(-B3/Marketing_Saturation_Spend)))*Local_AudioTour_Rate_Init*AudioTour_Price+(H3-Locals_Base*(1-(1-EXP(-B3/Marketing_Saturation_Spend))))*F3*E3-AudioLocal_Base*AudioTour_Price) | O3: =(K3-Total_Daily_AudioTour)*Headset_Cost | P3: =I3*D3+Locals_Base*(1-EXP(-B3/Marketing_Saturation_Spend))*F3*GiftShop_Spillover | Q3: =N3-O3-M3+P3 | R3: =Q3*Campaign_Days-B3
A4: Break-even draw test | B4: =Marketing_Spend | C4: =IF(AND(ISNUMBER(Model!$C$76),Awareness>0),Percentage_Locals_Init+((Locals_Base+Model!$C$76)/(Tourists_Base+Locals_Base+Model!$C$76)-Percentage_Locals_Init)/Awareness,Locals_Share_Ceiling) | D4: =GiftShop_Net_Spend_Local | E4: =Average_PWYW | F4: =Local_AudioTour_Rate_PWYW | G4: =Percentage_Locals_Init+(C4-Percentage_Locals_Init)*(1-EXP(-B4/Marketing_Saturation_Spend)) | H4: =Tourists_Base*G4/(1-G4) | I4: =H4-Locals_Base | J4: =Locals_Base*(1-(1-EXP(-B4/Marketing_Saturation_Spend)))*Local_AudioTour_Rate_Init+(H4-Locals_Base*(1-(1-EXP(-B4/Marketing_Saturation_Spend))))*F4 | K4: =AudioTourist_Base+J4 | L4: =MAX(0,ROUNDUP((K4-Device_Capacity)/Device_Block_Size,0)) | M4: =L4*Device_Block_Cost/Device_Amort_Days | N4: =Fee_Keep*(Locals_Base*(1-(1-EXP(-B4/Marketing_Saturation_Spend)))*Local_AudioTour_Rate_Init*AudioTour_Price+(H4-Locals_Base*(1-(1-EXP(-B4/Marketing_Saturation_Spend))))*F4*E4-AudioLocal_Base*AudioTour_Price) | O4: =(K4-Total_Daily_AudioTour)*Headset_Cost | P4: =I4*D4+Locals_Base*(1-EXP(-B4/Marketing_Saturation_Spend))*F4*GiftShop_Spillover | Q4: =N4-O4-M4+P4 | R4: =Q4*Campaign_Days-B4
A5: 1. r1 c1 | B5: =Sensitivity!$B$7 | C5: =Locals_Share_Ceiling | D5: =Sensitivity!C$6 | E5: =Average_PWYW | F5: =Local_AudioTour_Rate_PWYW | G5: =Percentage_Locals_Init+(C5-Percentage_Locals_Init)*(1-EXP(-B5/Marketing_Saturation_Spend)) | H5: =Tourists_Base*G5/(1-G5) | I5: =H5-Locals_Base | J5: =Locals_Base*(1-(1-EXP(-B5/Marketing_Saturation_Spend)))*Local_AudioTour_Rate_Init+(H5-Locals_Base*(1-(1-EXP(-B5/Marketing_Saturation_Spend))))*F5 | K5: =AudioTourist_Base+J5 | L5: =MAX(0,ROUNDUP((K5-Device_Capacity)/Device_Block_Size,0)) | M5: =L5*Device_Block_Cost/Device_Amort_Days | N5: =Fee_Keep*(Locals_Base*(1-(1-EXP(-B5/Marketing_Saturation_Spend)))*Local_AudioTour_Rate_Init*AudioTour_Price+(H5-Locals_Base*(1-(1-EXP(-B5/Marketing_Saturation_Spend))))*F5*E5-AudioLocal_Base*AudioTour_Price) | O5: =(K5-Total_Daily_AudioTour)*Headset_Cost | P5: =I5*D5+Locals_Base*(1-EXP(-B5/Marketing_Saturation_Spend))*F5*GiftShop_Spillover | Q5: =N5-O5-M5+P5 | R5: =Q5*Campaign_Days-B5
A6: 1. r1 c2 | B6: =Sensitivity!$B$7 | C6: =Locals_Share_Ceiling | D6: =Sensitivity!D$6 | E6: =Average_PWYW | F6: =Local_AudioTour_Rate_PWYW | G6: =Percentage_Locals_Init+(C6-Percentage_Locals_Init)*(1-EXP(-B6/Marketing_Saturation_Spend)) | H6: =Tourists_Base*G6/(1-G6) | I6: =H6-Locals_Base | J6: =Locals_Base*(1-(1-EXP(-B6/Marketing_Saturation_Spend)))*Local_AudioTour_Rate_Init+(H6-Locals_Base*(1-(1-EXP(-B6/Marketing_Saturation_Spend))))*F6 | K6: =AudioTourist_Base+J6 | L6: =MAX(0,ROUNDUP((K6-Device_Capacity)/Device_Block_Size,0)) | M6: =L6*Device_Block_Cost/Device_Amort_Days | N6: =Fee_Keep*(Locals_Base*(1-(1-EXP(-B6/Marketing_Saturation_Spend)))*Local_AudioTour_Rate_Init*AudioTour_Price+(H6-Locals_Base*(1-(1-EXP(-B6/Marketing_Saturation_Spend))))*F6*E6-AudioLocal_Base*AudioTour_Price) | O6: =(K6-Total_Daily_AudioTour)*Headset_Cost | P6: =I6*D6+Locals_Base*(1-EXP(-B6/Marketing_Saturation_Spend))*F6*GiftShop_Spillover | Q6: =N6-O6-M6+P6 | R6: =Q6*Campaign_Days-B6
A7: 1. r1 c3 | B7: =Sensitivity!$B$7 | C7: =Locals_Share_Ceiling | D7: =Sensitivity!E$6 | E7: =Average_PWYW | F7: =Local_AudioTour_Rate_PWYW | G7: =Percentage_Locals_Init+(C7-Percentage_Locals_Init)*(1-EXP(-B7/Marketing_Saturation_Spend)) | H7: =Tourists_Base*G7/(1-G7) | I7: =H7-Locals_Base | J7: =Locals_Base*(1-(1-EXP(-B7/Marketing_Saturation_Spend)))*Local_AudioTour_Rate_Init+(H7-Locals_Base*(1-(1-EXP(-B7/Marketing_Saturation_Spend))))*F7 | K7: =AudioTourist_Base+J7 | L7: =MAX(0,ROUNDUP((K7-Device_Capacity)/Device_Block_Size,0)) | M7: =L7*Device_Block_Cost/Device_Amort_Days | N7: =Fee_Keep*(Locals_Base*(1-(1-EXP(-B7/Marketing_Saturation_Spend)))*Local_AudioTour_Rate_Init*AudioTour_Price+(H7-Locals_Base*(1-(1-EXP(-B7/Marketing_Saturation_Spend))))*F7*E7-AudioLocal_Base*AudioTour_Price) | O7: =(K7-Total_Daily_AudioTour)*Headset_Cost | P7: =I7*D7+Locals_Base*(1-EXP(-B7/Marketing_Saturation_Spend))*F7*GiftShop_Spillover | Q7: =N7-O7-M7+P7 | R7: =Q7*Campaign_Days-B7
A8: 1. r1 c4 | B8: =Sensitivity!$B$7 | C8: =Locals_Share_Ceiling | D8: =Sensitivity!F$6 | E8: =Average_PWYW | F8: =Local_AudioTour_Rate_PWYW | G8: =Percentage_Locals_Init+(C8-Percentage_Locals_Init)*(1-EXP(-B8/Marketing_Saturation_Spend)) | H8: =Tourists_Base*G8/(1-G8) | I8: =H8-Locals_Base | J8: =Locals_Base*(1-(1-EXP(-B8/Marketing_Saturation_Spend)))*Local_AudioTour_Rate_Init+(H8-Locals_Base*(1-(1-EXP(-B8/Marketing_Saturation_Spend))))*F8 | K8: =AudioTourist_Base+J8 | L8: =MAX(0,ROUNDUP((K8-Device_Capacity)/Device_Block_Size,0)) | M8: =L8*Device_Block_Cost/Device_Amort_Days | N8: =Fee_Keep*(Locals_Base*(1-(1-EXP(-B8/Marketing_Saturation_Spend)))*Local_AudioTour_Rate_Init*AudioTour_Price+(H8-Locals_Base*(1-(1-EXP(-B8/Marketing_Saturation_Spend))))*F8*E8-AudioLocal_Base*AudioTour_Price) | O8: =(K8-Total_Daily_AudioTour)*Headset_Cost | P8: =I8*D8+Locals_Base*(1-EXP(-B8/Marketing_Saturation_Spend))*F8*GiftShop_Spillover | Q8: =N8-O8-M8+P8 | R8: =Q8*Campaign_Days-B8
A9: 1. r1 c5 | B9: =Sensitivity!$B$7 | C9: =Locals_Share_Ceiling | D9: =Sensitivity!G$6 | E9: =Average_PWYW | F9: =Local_AudioTour_Rate_PWYW | G9: =Percentage_Locals_Init+(C9-Percentage_Locals_Init)*(1-EXP(-B9/Marketing_Saturation_Spend)) | H9: =Tourists_Base*G9/(1-G9) | I9: =H9-Locals_Base | J9: =Locals_Base*(1-(1-EXP(-B9/Marketing_Saturation_Spend)))*Local_AudioTour_Rate_Init+(H9-Locals_Base*(1-(1-EXP(-B9/Marketing_Saturation_Spend))))*F9 | K9: =AudioTourist_Base+J9 | L9: =MAX(0,ROUNDUP((K9-Device_Capacity)/Device_Block_Size,0)) | M9: =L9*Device_Block_Cost/Device_Amort_Days | N9: =Fee_Keep*(Locals_Base*(1-(1-EXP(-B9/Marketing_Saturation_Spend)))*Local_AudioTour_Rate_Init*AudioTour_Price+(H9-Locals_Base*(1-(1-EXP(-B9/Marketing_Saturation_Spend))))*F9*E9-AudioLocal_Base*AudioTour_Price) | O9: =(K9-Total_Daily_AudioTour)*Headset_Cost | P9: =I9*D9+Locals_Base*(1-EXP(-B9/Marketing_Saturation_Spend))*F9*GiftShop_Spillover | Q9: =N9-O9-M9+P9 | R9: =Q9*Campaign_Days-B9
A10: 1. r1 c6 | B10: =Sensitivity!$B$7 | C10: =Locals_Share_Ceiling | D10: =Sensitivity!H$6 | E10: =Average_PWYW | F10: =Local_AudioTour_Rate_PWYW | G10: =Percentage_Locals_Init+(C10-Percentage_Locals_Init)*(1-EXP(-B10/Marketing_Saturation_Spend)) | H10: =Tourists_Base*G10/(1-G10) | I10: =H10-Locals_Base | J10: =Locals_Base*(1-(1-EXP(-B10/Marketing_Saturation_Spend)))*Local_AudioTour_Rate_Init+(H10-Locals_Base*(1-(1-EXP(-B10/Marketing_Saturation_Spend))))*F10 | K10: =AudioTourist_Base+J10 | L10: =MAX(0,ROUNDUP((K10-Device_Capacity)/Device_Block_Size,0)) | M10: =L10*Device_Block_Cost/Device_Amort_Days | N10: =Fee_Keep*(Locals_Base*(1-(1-EXP(-B10/Marketing_Saturation_Spend)))*Local_AudioTour_Rate_Init*AudioTour_Price+(H10-Locals_Base*(1-(1-EXP(-B10/Marketing_Saturation_Spend))))*F10*E10-AudioLocal_Base*AudioTour_Price) | O10: =(K10-Total_Daily_AudioTour)*Headset_Cost | P10: =I10*D10+Locals_Base*(1-EXP(-B10/Marketing_Saturation_Spend))*F10*GiftShop_Spillover | Q10: =N10-O10-M10+P10 | R10: =Q10*Campaign_Days-B10
A11: 1. r1 c7 | B11: =Sensitivity!$B$7 | C11: =Locals_Share_Ceiling | D11: =Sensitivity!I$6 | E11: =Average_PWYW | F11: =Local_AudioTour_Rate_PWYW | G11: =Percentage_Locals_Init+(C11-Percentage_Locals_Init)*(1-EXP(-B11/Marketing_Saturation_Spend)) | H11: =Tourists_Base*G11/(1-G11) | I11: =H11-Locals_Base | J11: =Locals_Base*(1-(1-EXP(-B11/Marketing_Saturation_Spend)))*Local_AudioTour_Rate_Init+(H11-Locals_Base*(1-(1-EXP(-B11/Marketing_Saturation_Spend))))*F11 | K11: =AudioTourist_Base+J11 | L11: =MAX(0,ROUNDUP((K11-Device_Capacity)/Device_Block_Size,0)) | M11: =L11*Device_Block_Cost/Device_Amort_Days | N11: =Fee_Keep*(Locals_Base*(1-(1-EXP(-B11/Marketing_Saturation_Spend)))*Local_AudioTour_Rate_Init*AudioTour_Price+(H11-Locals_Base*(1-(1-EXP(-B11/Marketing_Saturation_Spend))))*F11*E11-AudioLocal_Base*AudioTour_Price) | O11: =(K11-Total_Daily_AudioTour)*Headset_Cost | P11: =I11*D11+Locals_Base*(1-EXP(-B11/Marketing_Saturation_Spend))*F11*GiftShop_Spillover | Q11: =N11-O11-M11+P11 | R11: =Q11*Campaign_Days-B11
A12: 1. r2 c1 | B12: =Sensitivity!$B$8 | C12: =Locals_Share_Ceiling | D12: =Sensitivity!C$6 | E12: =Average_PWYW | F12: =Local_AudioTour_Rate_PWYW | G12: =Percentage_Locals_Init+(C12-Percentage_Locals_Init)*(1-EXP(-B12/Marketing_Saturation_Spend)) | H12: =Tourists_Base*G12/(1-G12) | I12: =H12-Locals_Base | J12: =Locals_Base*(1-(1-EXP(-B12/Marketing_Saturation_Spend)))*Local_AudioTour_Rate_Init+(H12-Locals_Base*(1-(1-EXP(-B12/Marketing_Saturation_Spend))))*F12 | K12: =AudioTourist_Base+J12 | L12: =MAX(0,ROUNDUP((K12-Device_Capacity)/Device_Block_Size,0)) | M12: =L12*Device_Block_Cost/Device_Amort_Days | N12: =Fee_Keep*(Locals_Base*(1-(1-EXP(-B12/Marketing_Saturation_Spend)))*Local_AudioTour_Rate_Init*AudioTour_Price+(H12-Locals_Base*(1-(1-EXP(-B12/Marketing_Saturation_Spend))))*F12*E12-AudioLocal_Base*AudioTour_Price) | O12: =(K12-Total_Daily_AudioTour)*Headset_Cost | P12: =I12*D12+Locals_Base*(1-EXP(-B12/Marketing_Saturation_Spend))*F12*GiftShop_Spillover | Q12: =N12-O12-M12+P12 | R12: =Q12*Campaign_Days-B12
A13: 1. r2 c2 | B13: =Sensitivity!$B$8 | C13: =Locals_Share_Ceiling | D13: =Sensitivity!D$6 | E13: =Average_PWYW | F13: =Local_AudioTour_Rate_PWYW | G13: =Percentage_Locals_Init+(C13-Percentage_Locals_Init)*(1-EXP(-B13/Marketing_Saturation_Spend)) | H13: =Tourists_Base*G13/(1-G13) | I13: =H13-Locals_Base | J13: =Locals_Base*(1-(1-EXP(-B13/Marketing_Saturation_Spend)))*Local_AudioTour_Rate_Init+(H13-Locals_Base*(1-(1-EXP(-B13/Marketing_Saturation_Spend))))*F13 | K13: =AudioTourist_Base+J13 | L13: =MAX(0,ROUNDUP((K13-Device_Capacity)/Device_Block_Size,0)) | M13: =L13*Device_Block_Cost/Device_Amort_Days | N13: =Fee_Keep*(Locals_Base*(1-(1-EXP(-B13/Marketing_Saturation_Spend)))*Local_AudioTour_Rate_Init*AudioTour_Price+(H13-Locals_Base*(1-(1-EXP(-B13/Marketing_Saturation_Spend))))*F13*E13-AudioLocal_Base*AudioTour_Price) | O13: =(K13-Total_Daily_AudioTour)*Headset_Cost | P13: =I13*D13+Locals_Base*(1-EXP(-B13/Marketing_Saturation_Spend))*F13*GiftShop_Spillover | Q13: =N13-O13-M13+P13 | R13: =Q13*Campaign_Days-B13
A14: 1. r2 c3 | B14: =Sensitivity!$B$8 | C14: =Locals_Share_Ceiling | D14: =Sensitivity!E$6 | E14: =Average_PWYW | F14: =Local_AudioTour_Rate_PWYW | G14: =Percentage_Locals_Init+(C14-Percentage_Locals_Init)*(1-EXP(-B14/Marketing_Saturation_Spend)) | H14: =Tourists_Base*G14/(1-G14) | I14: =H14-Locals_Base | J14: =Locals_Base*(1-(1-EXP(-B14/Marketing_Saturation_Spend)))*Local_AudioTour_Rate_Init+(H14-Locals_Base*(1-(1-EXP(-B14/Marketing_Saturation_Spend))))*F14 | K14: =AudioTourist_Base+J14 | L14: =MAX(0,ROUNDUP((K14-Device_Capacity)/Device_Block_Size,0)) | M14: =L14*Device_Block_Cost/Device_Amort_Days | N14: =Fee_Keep*(Locals_Base*(1-(1-EXP(-B14/Marketing_Saturation_Spend)))*Local_AudioTour_Rate_Init*AudioTour_Price+(H14-Locals_Base*(1-(1-EXP(-B14/Marketing_Saturation_Spend))))*F14*E14-AudioLocal_Base*AudioTour_Price) | O14: =(K14-Total_Daily_AudioTour)*Headset_Cost | P14: =I14*D14+Locals_Base*(1-EXP(-B14/Marketing_Saturation_Spend))*F14*GiftShop_Spillover | Q14: =N14-O14-M14+P14 | R14: =Q14*Campaign_Days-B14
A15: 1. r2 c4 | B15: =Sensitivity!$B$8 | C15: =Locals_Share_Ceiling | D15: =Sensitivity!F$6 | E15: =Average_PWYW | F15: =Local_AudioTour_Rate_PWYW | G15: =Percentage_Locals_Init+(C15-Percentage_Locals_Init)*(1-EXP(-B15/Marketing_Saturation_Spend)) | H15: =Tourists_Base*G15/(1-G15) | I15: =H15-Locals_Base | J15: =Locals_Base*(1-(1-EXP(-B15/Marketing_Saturation_Spend)))*Local_AudioTour_Rate_Init+(H15-Locals_Base*(1-(1-EXP(-B15/Marketing_Saturation_Spend))))*F15 | K15: =AudioTourist_Base+J15 | L15: =MAX(0,ROUNDUP((K15-Device_Capacity)/Device_Block_Size,0)) | M15: =L15*Device_Block_Cost/Device_Amort_Days | N15: =Fee_Keep*(Locals_Base*(1-(1-EXP(-B15/Marketing_Saturation_Spend)))*Local_AudioTour_Rate_Init*AudioTour_Price+(H15-Locals_Base*(1-(1-EXP(-B15/Marketing_Saturation_Spend))))*F15*E15-AudioLocal_Base*AudioTour_Price) | O15: =(K15-Total_Daily_AudioTour)*Headset_Cost | P15: =I15*D15+Locals_Base*(1-EXP(-B15/Marketing_Saturation_Spend))*F15*GiftShop_Spillover | Q15: =N15-O15-M15+P15 | R15: =Q15*Campaign_Days-B15
A16: 1. r2 c5 | B16: =Sensitivity!$B$8 | C16: =Locals_Share_Ceiling | D16: =Sensitivity!G$6 | E16: =Average_PWYW | F16: =Local_AudioTour_Rate_PWYW | G16: =Percentage_Locals_Init+(C16-Percentage_Locals_Init)*(1-EXP(-B16/Marketing_Saturation_Spend)) | H16: =Tourists_Base*G16/(1-G16) | I16: =H16-Locals_Base | J16: =Locals_Base*(1-(1-EXP(-B16/Marketing_Saturation_Spend)))*Local_AudioTour_Rate_Init+(H16-Locals_Base*(1-(1-EXP(-B16/Marketing_Saturation_Spend))))*F16 | K16: =AudioTourist_Base+J16 | L16: =MAX(0,ROUNDUP((K16-Device_Capacity)/Device_Block_Size,0)) | M16: =L16*Device_Block_Cost/Device_Amort_Days | N16: =Fee_Keep*(Locals_Base*(1-(1-EXP(-B16/Marketing_Saturation_Spend)))*Local_AudioTour_Rate_Init*AudioTour_Price+(H16-Locals_Base*(1-(1-EXP(-B16/Marketing_Saturation_Spend))))*F16*E16-AudioLocal_Base*AudioTour_Price) | O16: =(K16-Total_Daily_AudioTour)*Headset_Cost | P16: =I16*D16+Locals_Base*(1-EXP(-B16/Marketing_Saturation_Spend))*F16*GiftShop_Spillover | Q16: =N16-O16-M16+P16 | R16: =Q16*Campaign_Days-B16
A17: 1. r2 c6 | B17: =Sensitivity!$B$8 | C17: =Locals_Share_Ceiling | D17: =Sensitivity!H$6 | E17: =Average_PWYW | F17: =Local_AudioTour_Rate_PWYW | G17: =Percentage_Locals_Init+(C17-Percentage_Locals_Init)*(1-EXP(-B17/Marketing_Saturation_Spend)) | H17: =Tourists_Base*G17/(1-G17) | I17: =H17-Locals_Base | J17: =Locals_Base*(1-(1-EXP(-B17/Marketing_Saturation_Spend)))*Local_AudioTour_Rate_Init+(H17-Locals_Base*(1-(1-EXP(-B17/Marketing_Saturation_Spend))))*F17 | K17: =AudioTourist_Base+J17 | L17: =MAX(0,ROUNDUP((K17-Device_Capacity)/Device_Block_Size,0)) | M17: =L17*Device_Block_Cost/Device_Amort_Days | N17: =Fee_Keep*(Locals_Base*(1-(1-EXP(-B17/Marketing_Saturation_Spend)))*Local_AudioTour_Rate_Init*AudioTour_Price+(H17-Locals_Base*(1-(1-EXP(-B17/Marketing_Saturation_Spend))))*F17*E17-AudioLocal_Base*AudioTour_Price) | O17: =(K17-Total_Daily_AudioTour)*Headset_Cost | P17: =I17*D17+Locals_Base*(1-EXP(-B17/Marketing_Saturation_Spend))*F17*GiftShop_Spillover | Q17: =N17-O17-M17+P17 | R17: =Q17*Campaign_Days-B17
A18: 1. r2 c7 | B18: =Sensitivity!$B$8 | C18: =Locals_Share_Ceiling | D18: =Sensitivity!I$6 | E18: =Average_PWYW | F18: =Local_AudioTour_Rate_PWYW | G18: =Percentage_Locals_Init+(C18-Percentage_Locals_Init)*(1-EXP(-B18/Marketing_Saturation_Spend)) | H18: =Tourists_Base*G18/(1-G18) | I18: =H18-Locals_Base | J18: =Locals_Base*(1-(1-EXP(-B18/Marketing_Saturation_Spend)))*Local_AudioTour_Rate_Init+(H18-Locals_Base*(1-(1-EXP(-B18/Marketing_Saturation_Spend))))*F18 | K18: =AudioTourist_Base+J18 | L18: =MAX(0,ROUNDUP((K18-Device_Capacity)/Device_Block_Size,0)) | M18: =L18*Device_Block_Cost/Device_Amort_Days | N18: =Fee_Keep*(Locals_Base*(1-(1-EXP(-B18/Marketing_Saturation_Spend)))*Local_AudioTour_Rate_Init*AudioTour_Price+(H18-Locals_Base*(1-(1-EXP(-B18/Marketing_Saturation_Spend))))*F18*E18-AudioLocal_Base*AudioTour_Price) | O18: =(K18-Total_Daily_AudioTour)*Headset_Cost | P18: =I18*D18+Locals_Base*(1-EXP(-B18/Marketing_Saturation_Spend))*F18*GiftShop_Spillover | Q18: =N18-O18-M18+P18 | R18: =Q18*Campaign_Days-B18
A19: 1. r3 c1 | B19: =Sensitivity!$B$9 | C19: =Locals_Share_Ceiling | D19: =Sensitivity!C$6 | E19: =Average_PWYW | F19: =Local_AudioTour_Rate_PWYW | G19: =Percentage_Locals_Init+(C19-Percentage_Locals_Init)*(1-EXP(-B19/Marketing_Saturation_Spend)) | H19: =Tourists_Base*G19/(1-G19) | I19: =H19-Locals_Base | J19: =Locals_Base*(1-(1-EXP(-B19/Marketing_Saturation_Spend)))*Local_AudioTour_Rate_Init+(H19-Locals_Base*(1-(1-EXP(-B19/Marketing_Saturation_Spend))))*F19 | K19: =AudioTourist_Base+J19 | L19: =MAX(0,ROUNDUP((K19-Device_Capacity)/Device_Block_Size,0)) | M19: =L19*Device_Block_Cost/Device_Amort_Days | N19: =Fee_Keep*(Locals_Base*(1-(1-EXP(-B19/Marketing_Saturation_Spend)))*Local_AudioTour_Rate_Init*AudioTour_Price+(H19-Locals_Base*(1-(1-EXP(-B19/Marketing_Saturation_Spend))))*F19*E19-AudioLocal_Base*AudioTour_Price) | O19: =(K19-Total_Daily_AudioTour)*Headset_Cost | P19: =I19*D19+Locals_Base*(1-EXP(-B19/Marketing_Saturation_Spend))*F19*GiftShop_Spillover | Q19: =N19-O19-M19+P19 | R19: =Q19*Campaign_Days-B19
A20: 1. r3 c2 | B20: =Sensitivity!$B$9 | C20: =Locals_Share_Ceiling | D20: =Sensitivity!D$6 | E20: =Average_PWYW | F20: =Local_AudioTour_Rate_PWYW | G20: =Percentage_Locals_Init+(C20-Percentage_Locals_Init)*(1-EXP(-B20/Marketing_Saturation_Spend)) | H20: =Tourists_Base*G20/(1-G20) | I20: =H20-Locals_Base | J20: =Locals_Base*(1-(1-EXP(-B20/Marketing_Saturation_Spend)))*Local_AudioTour_Rate_Init+(H20-Locals_Base*(1-(1-EXP(-B20/Marketing_Saturation_Spend))))*F20 | K20: =AudioTourist_Base+J20 | L20: =MAX(0,ROUNDUP((K20-Device_Capacity)/Device_Block_Size,0)) | M20: =L20*Device_Block_Cost/Device_Amort_Days | N20: =Fee_Keep*(Locals_Base*(1-(1-EXP(-B20/Marketing_Saturation_Spend)))*Local_AudioTour_Rate_Init*AudioTour_Price+(H20-Locals_Base*(1-(1-EXP(-B20/Marketing_Saturation_Spend))))*F20*E20-AudioLocal_Base*AudioTour_Price) | O20: =(K20-Total_Daily_AudioTour)*Headset_Cost | P20: =I20*D20+Locals_Base*(1-EXP(-B20/Marketing_Saturation_Spend))*F20*GiftShop_Spillover | Q20: =N20-O20-M20+P20 | R20: =Q20*Campaign_Days-B20
A21: 1. r3 c3 | B21: =Sensitivity!$B$9 | C21: =Locals_Share_Ceiling | D21: =Sensitivity!E$6 | E21: =Average_PWYW | F21: =Local_AudioTour_Rate_PWYW | G21: =Percentage_Locals_Init+(C21-Percentage_Locals_Init)*(1-EXP(-B21/Marketing_Saturation_Spend)) | H21: =Tourists_Base*G21/(1-G21) | I21: =H21-Locals_Base | J21: =Locals_Base*(1-(1-EXP(-B21/Marketing_Saturation_Spend)))*Local_AudioTour_Rate_Init+(H21-Locals_Base*(1-(1-EXP(-B21/Marketing_Saturation_Spend))))*F21 | K21: =AudioTourist_Base+J21 | L21: =MAX(0,ROUNDUP((K21-Device_Capacity)/Device_Block_Size,0)) | M21: =L21*Device_Block_Cost/Device_Amort_Days | N21: =Fee_Keep*(Locals_Base*(1-(1-EXP(-B21/Marketing_Saturation_Spend)))*Local_AudioTour_Rate_Init*AudioTour_Price+(H21-Locals_Base*(1-(1-EXP(-B21/Marketing_Saturation_Spend))))*F21*E21-AudioLocal_Base*AudioTour_Price) | O21: =(K21-Total_Daily_AudioTour)*Headset_Cost | P21: =I21*D21+Locals_Base*(1-EXP(-B21/Marketing_Saturation_Spend))*F21*GiftShop_Spillover | Q21: =N21-O21-M21+P21 | R21: =Q21*Campaign_Days-B21
A22: 1. r3 c4 | B22: =Sensitivity!$B$9 | C22: =Locals_Share_Ceiling | D22: =Sensitivity!F$6 | E22: =Average_PWYW | F22: =Local_AudioTour_Rate_PWYW | G22: =Percentage_Locals_Init+(C22-Percentage_Locals_Init)*(1-EXP(-B22/Marketing_Saturation_Spend)) | H22: =Tourists_Base*G22/(1-G22) | I22: =H22-Locals_Base | J22: =Locals_Base*(1-(1-EXP(-B22/Marketing_Saturation_Spend)))*Local_AudioTour_Rate_Init+(H22-Locals_Base*(1-(1-EXP(-B22/Marketing_Saturation_Spend))))*F22 | K22: =AudioTourist_Base+J22 | L22: =MAX(0,ROUNDUP((K22-Device_Capacity)/Device_Block_Size,0)) | M22: =L22*Device_Block_Cost/Device_Amort_Days | N22: =Fee_Keep*(Locals_Base*(1-(1-EXP(-B22/Marketing_Saturation_Spend)))*Local_AudioTour_Rate_Init*AudioTour_Price+(H22-Locals_Base*(1-(1-EXP(-B22/Marketing_Saturation_Spend))))*F22*E22-AudioLocal_Base*AudioTour_Price) | O22: =(K22-Total_Daily_AudioTour)*Headset_Cost | P22: =I22*D22+Locals_Base*(1-EXP(-B22/Marketing_Saturation_Spend))*F22*GiftShop_Spillover | Q22: =N22-O22-M22+P22 | R22: =Q22*Campaign_Days-B22
A23: 1. r3 c5 | B23: =Sensitivity!$B$9 | C23: =Locals_Share_Ceiling | D23: =Sensitivity!G$6 | E23: =Average_PWYW | F23: =Local_AudioTour_Rate_PWYW | G23: =Percentage_Locals_Init+(C23-Percentage_Locals_Init)*(1-EXP(-B23/Marketing_Saturation_Spend)) | H23: =Tourists_Base*G23/(1-G23) | I23: =H23-Locals_Base | J23: =Locals_Base*(1-(1-EXP(-B23/Marketing_Saturation_Spend)))*Local_AudioTour_Rate_Init+(H23-Locals_Base*(1-(1-EXP(-B23/Marketing_Saturation_Spend))))*F23 | K23: =AudioTourist_Base+J23 | L23: =MAX(0,ROUNDUP((K23-Device_Capacity)/Device_Block_Size,0)) | M23: =L23*Device_Block_Cost/Device_Amort_Days | N23: =Fee_Keep*(Locals_Base*(1-(1-EXP(-B23/Marketing_Saturation_Spend)))*Local_AudioTour_Rate_Init*AudioTour_Price+(H23-Locals_Base*(1-(1-EXP(-B23/Marketing_Saturation_Spend))))*F23*E23-AudioLocal_Base*AudioTour_Price) | O23: =(K23-Total_Daily_AudioTour)*Headset_Cost | P23: =I23*D23+Locals_Base*(1-EXP(-B23/Marketing_Saturation_Spend))*F23*GiftShop_Spillover | Q23: =N23-O23-M23+P23 | R23: =Q23*Campaign_Days-B23
A24: 1. r3 c6 | B24: =Sensitivity!$B$9 | C24: =Locals_Share_Ceiling | D24: =Sensitivity!H$6 | E24: =Average_PWYW | F24: =Local_AudioTour_Rate_PWYW | G24: =Percentage_Locals_Init+(C24-Percentage_Locals_Init)*(1-EXP(-B24/Marketing_Saturation_Spend)) | H24: =Tourists_Base*G24/(1-G24) | I24: =H24-Locals_Base | J24: =Locals_Base*(1-(1-EXP(-B24/Marketing_Saturation_Spend)))*Local_AudioTour_Rate_Init+(H24-Locals_Base*(1-(1-EXP(-B24/Marketing_Saturation_Spend))))*F24 | K24: =AudioTourist_Base+J24 | L24: =MAX(0,ROUNDUP((K24-Device_Capacity)/Device_Block_Size,0)) | M24: =L24*Device_Block_Cost/Device_Amort_Days | N24: =Fee_Keep*(Locals_Base*(1-(1-EXP(-B24/Marketing_Saturation_Spend)))*Local_AudioTour_Rate_Init*AudioTour_Price+(H24-Locals_Base*(1-(1-EXP(-B24/Marketing_Saturation_Spend))))*F24*E24-AudioLocal_Base*AudioTour_Price) | O24: =(K24-Total_Daily_AudioTour)*Headset_Cost | P24: =I24*D24+Locals_Base*(1-EXP(-B24/Marketing_Saturation_Spend))*F24*GiftShop_Spillover | Q24: =N24-O24-M24+P24 | R24: =Q24*Campaign_Days-B24
A25: 1. r3 c7 | B25: =Sensitivity!$B$9 | C25: =Locals_Share_Ceiling | D25: =Sensitivity!I$6 | E25: =Average_PWYW | F25: =Local_AudioTour_Rate_PWYW | G25: =Percentage_Locals_Init+(C25-Percentage_Locals_Init)*(1-EXP(-B25/Marketing_Saturation_Spend)) | H25: =Tourists_Base*G25/(1-G25) | I25: =H25-Locals_Base | J25: =Locals_Base*(1-(1-EXP(-B25/Marketing_Saturation_Spend)))*Local_AudioTour_Rate_Init+(H25-Locals_Base*(1-(1-EXP(-B25/Marketing_Saturation_Spend))))*F25 | K25: =AudioTourist_Base+J25 | L25: =MAX(0,ROUNDUP((K25-Device_Capacity)/Device_Block_Size,0)) | M25: =L25*Device_Block_Cost/Device_Amort_Days | N25: =Fee_Keep*(Locals_Base*(1-(1-EXP(-B25/Marketing_Saturation_Spend)))*Local_AudioTour_Rate_Init*AudioTour_Price+(H25-Locals_Base*(1-(1-EXP(-B25/Marketing_Saturation_Spend))))*F25*E25-AudioLocal_Base*AudioTour_Price) | O25: =(K25-Total_Daily_AudioTour)*Headset_Cost | P25: =I25*D25+Locals_Base*(1-EXP(-B25/Marketing_Saturation_Spend))*F25*GiftShop_Spillover | Q25: =N25-O25-M25+P25 | R25: =Q25*Campaign_Days-B25
A26: 1. r4 c1 | B26: =Sensitivity!$B$10 | C26: =Locals_Share_Ceiling | D26: =Sensitivity!C$6 | E26: =Average_PWYW | F26: =Local_AudioTour_Rate_PWYW | G26: =Percentage_Locals_Init+(C26-Percentage_Locals_Init)*(1-EXP(-B26/Marketing_Saturation_Spend)) | H26: =Tourists_Base*G26/(1-G26) | I26: =H26-Locals_Base | J26: =Locals_Base*(1-(1-EXP(-B26/Marketing_Saturation_Spend)))*Local_AudioTour_Rate_Init+(H26-Locals_Base*(1-(1-EXP(-B26/Marketing_Saturation_Spend))))*F26 | K26: =AudioTourist_Base+J26 | L26: =MAX(0,ROUNDUP((K26-Device_Capacity)/Device_Block_Size,0)) | M26: =L26*Device_Block_Cost/Device_Amort_Days | N26: =Fee_Keep*(Locals_Base*(1-(1-EXP(-B26/Marketing_Saturation_Spend)))*Local_AudioTour_Rate_Init*AudioTour_Price+(H26-Locals_Base*(1-(1-EXP(-B26/Marketing_Saturation_Spend))))*F26*E26-AudioLocal_Base*AudioTour_Price) | O26: =(K26-Total_Daily_AudioTour)*Headset_Cost | P26: =I26*D26+Locals_Base*(1-EXP(-B26/Marketing_Saturation_Spend))*F26*GiftShop_Spillover | Q26: =N26-O26-M26+P26 | R26: =Q26*Campaign_Days-B26
A27: 1. r4 c2 | B27: =Sensitivity!$B$10 | C27: =Locals_Share_Ceiling | D27: =Sensitivity!D$6 | E27: =Average_PWYW | F27: =Local_AudioTour_Rate_PWYW | G27: =Percentage_Locals_Init+(C27-Percentage_Locals_Init)*(1-EXP(-B27/Marketing_Saturation_Spend)) | H27: =Tourists_Base*G27/(1-G27) | I27: =H27-Locals_Base | J27: =Locals_Base*(1-(1-EXP(-B27/Marketing_Saturation_Spend)))*Local_AudioTour_Rate_Init+(H27-Locals_Base*(1-(1-EXP(-B27/Marketing_Saturation_Spend))))*F27 | K27: =AudioTourist_Base+J27 | L27: =MAX(0,ROUNDUP((K27-Device_Capacity)/Device_Block_Size,0)) | M27: =L27*Device_Block_Cost/Device_Amort_Days | N27: =Fee_Keep*(Locals_Base*(1-(1-EXP(-B27/Marketing_Saturation_Spend)))*Local_AudioTour_Rate_Init*AudioTour_Price+(H27-Locals_Base*(1-(1-EXP(-B27/Marketing_Saturation_Spend))))*F27*E27-AudioLocal_Base*AudioTour_Price) | O27: =(K27-Total_Daily_AudioTour)*Headset_Cost | P27: =I27*D27+Locals_Base*(1-EXP(-B27/Marketing_Saturation_Spend))*F27*GiftShop_Spillover | Q27: =N27-O27-M27+P27 | R27: =Q27*Campaign_Days-B27
A28: 1. r4 c3 | B28: =Sensitivity!$B$10 | C28: =Locals_Share_Ceiling | D28: =Sensitivity!E$6 | E28: =Average_PWYW | F28: =Local_AudioTour_Rate_PWYW | G28: =Percentage_Locals_Init+(C28-Percentage_Locals_Init)*(1-EXP(-B28/Marketing_Saturation_Spend)) | H28: =Tourists_Base*G28/(1-G28) | I28: =H28-Locals_Base | J28: =Locals_Base*(1-(1-EXP(-B28/Marketing_Saturation_Spend)))*Local_AudioTour_Rate_Init+(H28-Locals_Base*(1-(1-EXP(-B28/Marketing_Saturation_Spend))))*F28 | K28: =AudioTourist_Base+J28 | L28: =MAX(0,ROUNDUP((K28-Device_Capacity)/Device_Block_Size,0)) | M28: =L28*Device_Block_Cost/Device_Amort_Days | N28: =Fee_Keep*(Locals_Base*(1-(1-EXP(-B28/Marketing_Saturation_Spend)))*Local_AudioTour_Rate_Init*AudioTour_Price+(H28-Locals_Base*(1-(1-EXP(-B28/Marketing_Saturation_Spend))))*F28*E28-AudioLocal_Base*AudioTour_Price) | O28: =(K28-Total_Daily_AudioTour)*Headset_Cost | P28: =I28*D28+Locals_Base*(1-EXP(-B28/Marketing_Saturation_Spend))*F28*GiftShop_Spillover | Q28: =N28-O28-M28+P28 | R28: =Q28*Campaign_Days-B28
A29: 1. r4 c4 | B29: =Sensitivity!$B$10 | C29: =Locals_Share_Ceiling | D29: =Sensitivity!F$6 | E29: =Average_PWYW | F29: =Local_AudioTour_Rate_PWYW | G29: =Percentage_Locals_Init+(C29-Percentage_Locals_Init)*(1-EXP(-B29/Marketing_Saturation_Spend)) | H29: =Tourists_Base*G29/(1-G29) | I29: =H29-Locals_Base | J29: =Locals_Base*(1-(1-EXP(-B29/Marketing_Saturation_Spend)))*Local_AudioTour_Rate_Init+(H29-Locals_Base*(1-(1-EXP(-B29/Marketing_Saturation_Spend))))*F29 | K29: =AudioTourist_Base+J29 | L29: =MAX(0,ROUNDUP((K29-Device_Capacity)/Device_Block_Size,0)) | M29: =L29*Device_Block_Cost/Device_Amort_Days | N29: =Fee_Keep*(Locals_Base*(1-(1-EXP(-B29/Marketing_Saturation_Spend)))*Local_AudioTour_Rate_Init*AudioTour_Price+(H29-Locals_Base*(1-(1-EXP(-B29/Marketing_Saturation_Spend))))*F29*E29-AudioLocal_Base*AudioTour_Price) | O29: =(K29-Total_Daily_AudioTour)*Headset_Cost | P29: =I29*D29+Locals_Base*(1-EXP(-B29/Marketing_Saturation_Spend))*F29*GiftShop_Spillover | Q29: =N29-O29-M29+P29 | R29: =Q29*Campaign_Days-B29
A30: 1. r4 c5 | B30: =Sensitivity!$B$10 | C30: =Locals_Share_Ceiling | D30: =Sensitivity!G$6 | E30: =Average_PWYW | F30: =Local_AudioTour_Rate_PWYW | G30: =Percentage_Locals_Init+(C30-Percentage_Locals_Init)*(1-EXP(-B30/Marketing_Saturation_Spend)) | H30: =Tourists_Base*G30/(1-G30) | I30: =H30-Locals_Base | J30: =Locals_Base*(1-(1-EXP(-B30/Marketing_Saturation_Spend)))*Local_AudioTour_Rate_Init+(H30-Locals_Base*(1-(1-EXP(-B30/Marketing_Saturation_Spend))))*F30 | K30: =AudioTourist_Base+J30 | L30: =MAX(0,ROUNDUP((K30-Device_Capacity)/Device_Block_Size,0)) | M30: =L30*Device_Block_Cost/Device_Amort_Days | N30: =Fee_Keep*(Locals_Base*(1-(1-EXP(-B30/Marketing_Saturation_Spend)))*Local_AudioTour_Rate_Init*AudioTour_Price+(H30-Locals_Base*(1-(1-EXP(-B30/Marketing_Saturation_Spend))))*F30*E30-AudioLocal_Base*AudioTour_Price) | O30: =(K30-Total_Daily_AudioTour)*Headset_Cost | P30: =I30*D30+Locals_Base*(1-EXP(-B30/Marketing_Saturation_Spend))*F30*GiftShop_Spillover | Q30: =N30-O30-M30+P30 | R30: =Q30*Campaign_Days-B30
A31: 1. r4 c6 | B31: =Sensitivity!$B$10 | C31: =Locals_Share_Ceiling | D31: =Sensitivity!H$6 | E31: =Average_PWYW | F31: =Local_AudioTour_Rate_PWYW | G31: =Percentage_Locals_Init+(C31-Percentage_Locals_Init)*(1-EXP(-B31/Marketing_Saturation_Spend)) | H31: =Tourists_Base*G31/(1-G31) | I31: =H31-Locals_Base | J31: =Locals_Base*(1-(1-EXP(-B31/Marketing_Saturation_Spend)))*Local_AudioTour_Rate_Init+(H31-Locals_Base*(1-(1-EXP(-B31/Marketing_Saturation_Spend))))*F31 | K31: =AudioTourist_Base+J31 | L31: =MAX(0,ROUNDUP((K31-Device_Capacity)/Device_Block_Size,0)) | M31: =L31*Device_Block_Cost/Device_Amort_Days | N31: =Fee_Keep*(Locals_Base*(1-(1-EXP(-B31/Marketing_Saturation_Spend)))*Local_AudioTour_Rate_Init*AudioTour_Price+(H31-Locals_Base*(1-(1-EXP(-B31/Marketing_Saturation_Spend))))*F31*E31-AudioLocal_Base*AudioTour_Price) | O31: =(K31-Total_Daily_AudioTour)*Headset_Cost | P31: =I31*D31+Locals_Base*(1-EXP(-B31/Marketing_Saturation_Spend))*F31*GiftShop_Spillover | Q31: =N31-O31-M31+P31 | R31: =Q31*Campaign_Days-B31
A32: 1. r4 c7 | B32: =Sensitivity!$B$10 | C32: =Locals_Share_Ceiling | D32: =Sensitivity!I$6 | E32: =Average_PWYW | F32: =Local_AudioTour_Rate_PWYW | G32: =Percentage_Locals_Init+(C32-Percentage_Locals_Init)*(1-EXP(-B32/Marketing_Saturation_Spend)) | H32: =Tourists_Base*G32/(1-G32) | I32: =H32-Locals_Base | J32: =Locals_Base*(1-(1-EXP(-B32/Marketing_Saturation_Spend)))*Local_AudioTour_Rate_Init+(H32-Locals_Base*(1-(1-EXP(-B32/Marketing_Saturation_Spend))))*F32 | K32: =AudioTourist_Base+J32 | L32: =MAX(0,ROUNDUP((K32-Device_Capacity)/Device_Block_Size,0)) | M32: =L32*Device_Block_Cost/Device_Amort_Days | N32: =Fee_Keep*(Locals_Base*(1-(1-EXP(-B32/Marketing_Saturation_Spend)))*Local_AudioTour_Rate_Init*AudioTour_Price+(H32-Locals_Base*(1-(1-EXP(-B32/Marketing_Saturation_Spend))))*F32*E32-AudioLocal_Base*AudioTour_Price) | O32: =(K32-Total_Daily_AudioTour)*Headset_Cost | P32: =I32*D32+Locals_Base*(1-EXP(-B32/Marketing_Saturation_Spend))*F32*GiftShop_Spillover | Q32: =N32-O32-M32+P32 | R32: =Q32*Campaign_Days-B32
A33: 1. r5 c1 | B33: =Sensitivity!$B$11 | C33: =Locals_Share_Ceiling | D33: =Sensitivity!C$6 | E33: =Average_PWYW | F33: =Local_AudioTour_Rate_PWYW | G33: =Percentage_Locals_Init+(C33-Percentage_Locals_Init)*(1-EXP(-B33/Marketing_Saturation_Spend)) | H33: =Tourists_Base*G33/(1-G33) | I33: =H33-Locals_Base | J33: =Locals_Base*(1-(1-EXP(-B33/Marketing_Saturation_Spend)))*Local_AudioTour_Rate_Init+(H33-Locals_Base*(1-(1-EXP(-B33/Marketing_Saturation_Spend))))*F33 | K33: =AudioTourist_Base+J33 | L33: =MAX(0,ROUNDUP((K33-Device_Capacity)/Device_Block_Size,0)) | M33: =L33*Device_Block_Cost/Device_Amort_Days | N33: =Fee_Keep*(Locals_Base*(1-(1-EXP(-B33/Marketing_Saturation_Spend)))*Local_AudioTour_Rate_Init*AudioTour_Price+(H33-Locals_Base*(1-(1-EXP(-B33/Marketing_Saturation_Spend))))*F33*E33-AudioLocal_Base*AudioTour_Price) | O33: =(K33-Total_Daily_AudioTour)*Headset_Cost | P33: =I33*D33+Locals_Base*(1-EXP(-B33/Marketing_Saturation_Spend))*F33*GiftShop_Spillover | Q33: =N33-O33-M33+P33 | R33: =Q33*Campaign_Days-B33
A34: 1. r5 c2 | B34: =Sensitivity!$B$11 | C34: =Locals_Share_Ceiling | D34: =Sensitivity!D$6 | E34: =Average_PWYW | F34: =Local_AudioTour_Rate_PWYW | G34: =Percentage_Locals_Init+(C34-Percentage_Locals_Init)*(1-EXP(-B34/Marketing_Saturation_Spend)) | H34: =Tourists_Base*G34/(1-G34) | I34: =H34-Locals_Base | J34: =Locals_Base*(1-(1-EXP(-B34/Marketing_Saturation_Spend)))*Local_AudioTour_Rate_Init+(H34-Locals_Base*(1-(1-EXP(-B34/Marketing_Saturation_Spend))))*F34 | K34: =AudioTourist_Base+J34 | L34: =MAX(0,ROUNDUP((K34-Device_Capacity)/Device_Block_Size,0)) | M34: =L34*Device_Block_Cost/Device_Amort_Days | N34: =Fee_Keep*(Locals_Base*(1-(1-EXP(-B34/Marketing_Saturation_Spend)))*Local_AudioTour_Rate_Init*AudioTour_Price+(H34-Locals_Base*(1-(1-EXP(-B34/Marketing_Saturation_Spend))))*F34*E34-AudioLocal_Base*AudioTour_Price) | O34: =(K34-Total_Daily_AudioTour)*Headset_Cost | P34: =I34*D34+Locals_Base*(1-EXP(-B34/Marketing_Saturation_Spend))*F34*GiftShop_Spillover | Q34: =N34-O34-M34+P34 | R34: =Q34*Campaign_Days-B34
A35: 1. r5 c3 | B35: =Sensitivity!$B$11 | C35: =Locals_Share_Ceiling | D35: =Sensitivity!E$6 | E35: =Average_PWYW | F35: =Local_AudioTour_Rate_PWYW | G35: =Percentage_Locals_Init+(C35-Percentage_Locals_Init)*(1-EXP(-B35/Marketing_Saturation_Spend)) | H35: =Tourists_Base*G35/(1-G35) | I35: =H35-Locals_Base | J35: =Locals_Base*(1-(1-EXP(-B35/Marketing_Saturation_Spend)))*Local_AudioTour_Rate_Init+(H35-Locals_Base*(1-(1-EXP(-B35/Marketing_Saturation_Spend))))*F35 | K35: =AudioTourist_Base+J35 | L35: =MAX(0,ROUNDUP((K35-Device_Capacity)/Device_Block_Size,0)) | M35: =L35*Device_Block_Cost/Device_Amort_Days | N35: =Fee_Keep*(Locals_Base*(1-(1-EXP(-B35/Marketing_Saturation_Spend)))*Local_AudioTour_Rate_Init*AudioTour_Price+(H35-Locals_Base*(1-(1-EXP(-B35/Marketing_Saturation_Spend))))*F35*E35-AudioLocal_Base*AudioTour_Price) | O35: =(K35-Total_Daily_AudioTour)*Headset_Cost | P35: =I35*D35+Locals_Base*(1-EXP(-B35/Marketing_Saturation_Spend))*F35*GiftShop_Spillover | Q35: =N35-O35-M35+P35 | R35: =Q35*Campaign_Days-B35
A36: 1. r5 c4 | B36: =Sensitivity!$B$11 | C36: =Locals_Share_Ceiling | D36: =Sensitivity!F$6 | E36: =Average_PWYW | F36: =Local_AudioTour_Rate_PWYW | G36: =Percentage_Locals_Init+(C36-Percentage_Locals_Init)*(1-EXP(-B36/Marketing_Saturation_Spend)) | H36: =Tourists_Base*G36/(1-G36) | I36: =H36-Locals_Base | J36: =Locals_Base*(1-(1-EXP(-B36/Marketing_Saturation_Spend)))*Local_AudioTour_Rate_Init+(H36-Locals_Base*(1-(1-EXP(-B36/Marketing_Saturation_Spend))))*F36 | K36: =AudioTourist_Base+J36 | L36: =MAX(0,ROUNDUP((K36-Device_Capacity)/Device_Block_Size,0)) | M36: =L36*Device_Block_Cost/Device_Amort_Days | N36: =Fee_Keep*(Locals_Base*(1-(1-EXP(-B36/Marketing_Saturation_Spend)))*Local_AudioTour_Rate_Init*AudioTour_Price+(H36-Locals_Base*(1-(1-EXP(-B36/Marketing_Saturation_Spend))))*F36*E36-AudioLocal_Base*AudioTour_Price) | O36: =(K36-Total_Daily_AudioTour)*Headset_Cost | P36: =I36*D36+Locals_Base*(1-EXP(-B36/Marketing_Saturation_Spend))*F36*GiftShop_Spillover | Q36: =N36-O36-M36+P36 | R36: =Q36*Campaign_Days-B36
A37: 1. r5 c5 | B37: =Sensitivity!$B$11 | C37: =Locals_Share_Ceiling | D37: =Sensitivity!G$6 | E37: =Average_PWYW | F37: =Local_AudioTour_Rate_PWYW | G37: =Percentage_Locals_Init+(C37-Percentage_Locals_Init)*(1-EXP(-B37/Marketing_Saturation_Spend)) | H37: =Tourists_Base*G37/(1-G37) | I37: =H37-Locals_Base | J37: =Locals_Base*(1-(1-EXP(-B37/Marketing_Saturation_Spend)))*Local_AudioTour_Rate_Init+(H37-Locals_Base*(1-(1-EXP(-B37/Marketing_Saturation_Spend))))*F37 | K37: =AudioTourist_Base+J37 | L37: =MAX(0,ROUNDUP((K37-Device_Capacity)/Device_Block_Size,0)) | M37: =L37*Device_Block_Cost/Device_Amort_Days | N37: =Fee_Keep*(Locals_Base*(1-(1-EXP(-B37/Marketing_Saturation_Spend)))*Local_AudioTour_Rate_Init*AudioTour_Price+(H37-Locals_Base*(1-(1-EXP(-B37/Marketing_Saturation_Spend))))*F37*E37-AudioLocal_Base*AudioTour_Price) | O37: =(K37-Total_Daily_AudioTour)*Headset_Cost | P37: =I37*D37+Locals_Base*(1-EXP(-B37/Marketing_Saturation_Spend))*F37*GiftShop_Spillover | Q37: =N37-O37-M37+P37 | R37: =Q37*Campaign_Days-B37
A38: 1. r5 c6 | B38: =Sensitivity!$B$11 | C38: =Locals_Share_Ceiling | D38: =Sensitivity!H$6 | E38: =Average_PWYW | F38: =Local_AudioTour_Rate_PWYW | G38: =Percentage_Locals_Init+(C38-Percentage_Locals_Init)*(1-EXP(-B38/Marketing_Saturation_Spend)) | H38: =Tourists_Base*G38/(1-G38) | I38: =H38-Locals_Base | J38: =Locals_Base*(1-(1-EXP(-B38/Marketing_Saturation_Spend)))*Local_AudioTour_Rate_Init+(H38-Locals_Base*(1-(1-EXP(-B38/Marketing_Saturation_Spend))))*F38 | K38: =AudioTourist_Base+J38 | L38: =MAX(0,ROUNDUP((K38-Device_Capacity)/Device_Block_Size,0)) | M38: =L38*Device_Block_Cost/Device_Amort_Days | N38: =Fee_Keep*(Locals_Base*(1-(1-EXP(-B38/Marketing_Saturation_Spend)))*Local_AudioTour_Rate_Init*AudioTour_Price+(H38-Locals_Base*(1-(1-EXP(-B38/Marketing_Saturation_Spend))))*F38*E38-AudioLocal_Base*AudioTour_Price) | O38: =(K38-Total_Daily_AudioTour)*Headset_Cost | P38: =I38*D38+Locals_Base*(1-EXP(-B38/Marketing_Saturation_Spend))*F38*GiftShop_Spillover | Q38: =N38-O38-M38+P38 | R38: =Q38*Campaign_Days-B38
A39: 1. r5 c7 | B39: =Sensitivity!$B$11 | C39: =Locals_Share_Ceiling | D39: =Sensitivity!I$6 | E39: =Average_PWYW | F39: =Local_AudioTour_Rate_PWYW | G39: =Percentage_Locals_Init+(C39-Percentage_Locals_Init)*(1-EXP(-B39/Marketing_Saturation_Spend)) | H39: =Tourists_Base*G39/(1-G39) | I39: =H39-Locals_Base | J39: =Locals_Base*(1-(1-EXP(-B39/Marketing_Saturation_Spend)))*Local_AudioTour_Rate_Init+(H39-Locals_Base*(1-(1-EXP(-B39/Marketing_Saturation_Spend))))*F39 | K39: =AudioTourist_Base+J39 | L39: =MAX(0,ROUNDUP((K39-Device_Capacity)/Device_Block_Size,0)) | M39: =L39*Device_Block_Cost/Device_Amort_Days | N39: =Fee_Keep*(Locals_Base*(1-(1-EXP(-B39/Marketing_Saturation_Spend)))*Local_AudioTour_Rate_Init*AudioTour_Price+(H39-Locals_Base*(1-(1-EXP(-B39/Marketing_Saturation_Spend))))*F39*E39-AudioLocal_Base*AudioTour_Price) | O39: =(K39-Total_Daily_AudioTour)*Headset_Cost | P39: =I39*D39+Locals_Base*(1-EXP(-B39/Marketing_Saturation_Spend))*F39*GiftShop_Spillover | Q39: =N39-O39-M39+P39 | R39: =Q39*Campaign_Days-B39
A40: 1. r6 c1 | B40: =Sensitivity!$B$12 | C40: =Locals_Share_Ceiling | D40: =Sensitivity!C$6 | E40: =Average_PWYW | F40: =Local_AudioTour_Rate_PWYW | G40: =Percentage_Locals_Init+(C40-Percentage_Locals_Init)*(1-EXP(-B40/Marketing_Saturation_Spend)) | H40: =Tourists_Base*G40/(1-G40) | I40: =H40-Locals_Base | J40: =Locals_Base*(1-(1-EXP(-B40/Marketing_Saturation_Spend)))*Local_AudioTour_Rate_Init+(H40-Locals_Base*(1-(1-EXP(-B40/Marketing_Saturation_Spend))))*F40 | K40: =AudioTourist_Base+J40 | L40: =MAX(0,ROUNDUP((K40-Device_Capacity)/Device_Block_Size,0)) | M40: =L40*Device_Block_Cost/Device_Amort_Days | N40: =Fee_Keep*(Locals_Base*(1-(1-EXP(-B40/Marketing_Saturation_Spend)))*Local_AudioTour_Rate_Init*AudioTour_Price+(H40-Locals_Base*(1-(1-EXP(-B40/Marketing_Saturation_Spend))))*F40*E40-AudioLocal_Base*AudioTour_Price) | O40: =(K40-Total_Daily_AudioTour)*Headset_Cost | P40: =I40*D40+Locals_Base*(1-EXP(-B40/Marketing_Saturation_Spend))*F40*GiftShop_Spillover | Q40: =N40-O40-M40+P40 | R40: =Q40*Campaign_Days-B40
A41: 1. r6 c2 | B41: =Sensitivity!$B$12 | C41: =Locals_Share_Ceiling | D41: =Sensitivity!D$6 | E41: =Average_PWYW | F41: =Local_AudioTour_Rate_PWYW | G41: =Percentage_Locals_Init+(C41-Percentage_Locals_Init)*(1-EXP(-B41/Marketing_Saturation_Spend)) | H41: =Tourists_Base*G41/(1-G41) | I41: =H41-Locals_Base | J41: =Locals_Base*(1-(1-EXP(-B41/Marketing_Saturation_Spend)))*Local_AudioTour_Rate_Init+(H41-Locals_Base*(1-(1-EXP(-B41/Marketing_Saturation_Spend))))*F41 | K41: =AudioTourist_Base+J41 | L41: =MAX(0,ROUNDUP((K41-Device_Capacity)/Device_Block_Size,0)) | M41: =L41*Device_Block_Cost/Device_Amort_Days | N41: =Fee_Keep*(Locals_Base*(1-(1-EXP(-B41/Marketing_Saturation_Spend)))*Local_AudioTour_Rate_Init*AudioTour_Price+(H41-Locals_Base*(1-(1-EXP(-B41/Marketing_Saturation_Spend))))*F41*E41-AudioLocal_Base*AudioTour_Price) | O41: =(K41-Total_Daily_AudioTour)*Headset_Cost | P41: =I41*D41+Locals_Base*(1-EXP(-B41/Marketing_Saturation_Spend))*F41*GiftShop_Spillover | Q41: =N41-O41-M41+P41 | R41: =Q41*Campaign_Days-B41
A42: 1. r6 c3 | B42: =Sensitivity!$B$12 | C42: =Locals_Share_Ceiling | D42: =Sensitivity!E$6 | E42: =Average_PWYW | F42: =Local_AudioTour_Rate_PWYW | G42: =Percentage_Locals_Init+(C42-Percentage_Locals_Init)*(1-EXP(-B42/Marketing_Saturation_Spend)) | H42: =Tourists_Base*G42/(1-G42) | I42: =H42-Locals_Base | J42: =Locals_Base*(1-(1-EXP(-B42/Marketing_Saturation_Spend)))*Local_AudioTour_Rate_Init+(H42-Locals_Base*(1-(1-EXP(-B42/Marketing_Saturation_Spend))))*F42 | K42: =AudioTourist_Base+J42 | L42: =MAX(0,ROUNDUP((K42-Device_Capacity)/Device_Block_Size,0)) | M42: =L42*Device_Block_Cost/Device_Amort_Days | N42: =Fee_Keep*(Locals_Base*(1-(1-EXP(-B42/Marketing_Saturation_Spend)))*Local_AudioTour_Rate_Init*AudioTour_Price+(H42-Locals_Base*(1-(1-EXP(-B42/Marketing_Saturation_Spend))))*F42*E42-AudioLocal_Base*AudioTour_Price) | O42: =(K42-Total_Daily_AudioTour)*Headset_Cost | P42: =I42*D42+Locals_Base*(1-EXP(-B42/Marketing_Saturation_Spend))*F42*GiftShop_Spillover | Q42: =N42-O42-M42+P42 | R42: =Q42*Campaign_Days-B42
A43: 1. r6 c4 | B43: =Sensitivity!$B$12 | C43: =Locals_Share_Ceiling | D43: =Sensitivity!F$6 | E43: =Average_PWYW | F43: =Local_AudioTour_Rate_PWYW | G43: =Percentage_Locals_Init+(C43-Percentage_Locals_Init)*(1-EXP(-B43/Marketing_Saturation_Spend)) | H43: =Tourists_Base*G43/(1-G43) | I43: =H43-Locals_Base | J43: =Locals_Base*(1-(1-EXP(-B43/Marketing_Saturation_Spend)))*Local_AudioTour_Rate_Init+(H43-Locals_Base*(1-(1-EXP(-B43/Marketing_Saturation_Spend))))*F43 | K43: =AudioTourist_Base+J43 | L43: =MAX(0,ROUNDUP((K43-Device_Capacity)/Device_Block_Size,0)) | M43: =L43*Device_Block_Cost/Device_Amort_Days | N43: =Fee_Keep*(Locals_Base*(1-(1-EXP(-B43/Marketing_Saturation_Spend)))*Local_AudioTour_Rate_Init*AudioTour_Price+(H43-Locals_Base*(1-(1-EXP(-B43/Marketing_Saturation_Spend))))*F43*E43-AudioLocal_Base*AudioTour_Price) | O43: =(K43-Total_Daily_AudioTour)*Headset_Cost | P43: =I43*D43+Locals_Base*(1-EXP(-B43/Marketing_Saturation_Spend))*F43*GiftShop_Spillover | Q43: =N43-O43-M43+P43 | R43: =Q43*Campaign_Days-B43
A44: 1. r6 c5 | B44: =Sensitivity!$B$12 | C44: =Locals_Share_Ceiling | D44: =Sensitivity!G$6 | E44: =Average_PWYW | F44: =Local_AudioTour_Rate_PWYW | G44: =Percentage_Locals_Init+(C44-Percentage_Locals_Init)*(1-EXP(-B44/Marketing_Saturation_Spend)) | H44: =Tourists_Base*G44/(1-G44) | I44: =H44-Locals_Base | J44: =Locals_Base*(1-(1-EXP(-B44/Marketing_Saturation_Spend)))*Local_AudioTour_Rate_Init+(H44-Locals_Base*(1-(1-EXP(-B44/Marketing_Saturation_Spend))))*F44 | K44: =AudioTourist_Base+J44 | L44: =MAX(0,ROUNDUP((K44-Device_Capacity)/Device_Block_Size,0)) | M44: =L44*Device_Block_Cost/Device_Amort_Days | N44: =Fee_Keep*(Locals_Base*(1-(1-EXP(-B44/Marketing_Saturation_Spend)))*Local_AudioTour_Rate_Init*AudioTour_Price+(H44-Locals_Base*(1-(1-EXP(-B44/Marketing_Saturation_Spend))))*F44*E44-AudioLocal_Base*AudioTour_Price) | O44: =(K44-Total_Daily_AudioTour)*Headset_Cost | P44: =I44*D44+Locals_Base*(1-EXP(-B44/Marketing_Saturation_Spend))*F44*GiftShop_Spillover | Q44: =N44-O44-M44+P44 | R44: =Q44*Campaign_Days-B44
A45: 1. r6 c6 | B45: =Sensitivity!$B$12 | C45: =Locals_Share_Ceiling | D45: =Sensitivity!H$6 | E45: =Average_PWYW | F45: =Local_AudioTour_Rate_PWYW | G45: =Percentage_Locals_Init+(C45-Percentage_Locals_Init)*(1-EXP(-B45/Marketing_Saturation_Spend)) | H45: =Tourists_Base*G45/(1-G45) | I45: =H45-Locals_Base | J45: =Locals_Base*(1-(1-EXP(-B45/Marketing_Saturation_Spend)))*Local_AudioTour_Rate_Init+(H45-Locals_Base*(1-(1-EXP(-B45/Marketing_Saturation_Spend))))*F45 | K45: =AudioTourist_Base+J45 | L45: =MAX(0,ROUNDUP((K45-Device_Capacity)/Device_Block_Size,0)) | M45: =L45*Device_Block_Cost/Device_Amort_Days | N45: =Fee_Keep*(Locals_Base*(1-(1-EXP(-B45/Marketing_Saturation_Spend)))*Local_AudioTour_Rate_Init*AudioTour_Price+(H45-Locals_Base*(1-(1-EXP(-B45/Marketing_Saturation_Spend))))*F45*E45-AudioLocal_Base*AudioTour_Price) | O45: =(K45-Total_Daily_AudioTour)*Headset_Cost | P45: =I45*D45+Locals_Base*(1-EXP(-B45/Marketing_Saturation_Spend))*F45*GiftShop_Spillover | Q45: =N45-O45-M45+P45 | R45: =Q45*Campaign_Days-B45
A46: 1. r6 c7 | B46: =Sensitivity!$B$12 | C46: =Locals_Share_Ceiling | D46: =Sensitivity!I$6 | E46: =Average_PWYW | F46: =Local_AudioTour_Rate_PWYW | G46: =Percentage_Locals_Init+(C46-Percentage_Locals_Init)*(1-EXP(-B46/Marketing_Saturation_Spend)) | H46: =Tourists_Base*G46/(1-G46) | I46: =H46-Locals_Base | J46: =Locals_Base*(1-(1-EXP(-B46/Marketing_Saturation_Spend)))*Local_AudioTour_Rate_Init+(H46-Locals_Base*(1-(1-EXP(-B46/Marketing_Saturation_Spend))))*F46 | K46: =AudioTourist_Base+J46 | L46: =MAX(0,ROUNDUP((K46-Device_Capacity)/Device_Block_Size,0)) | M46: =L46*Device_Block_Cost/Device_Amort_Days | N46: =Fee_Keep*(Locals_Base*(1-(1-EXP(-B46/Marketing_Saturation_Spend)))*Local_AudioTour_Rate_Init*AudioTour_Price+(H46-Locals_Base*(1-(1-EXP(-B46/Marketing_Saturation_Spend))))*F46*E46-AudioLocal_Base*AudioTour_Price) | O46: =(K46-Total_Daily_AudioTour)*Headset_Cost | P46: =I46*D46+Locals_Base*(1-EXP(-B46/Marketing_Saturation_Spend))*F46*GiftShop_Spillover | Q46: =N46-O46-M46+P46 | R46: =Q46*Campaign_Days-B46
A47: 2. r1 c1 | B47: =Marketing_Spend | C47: =Locals_Share_Ceiling | D47: =GiftShop_Net_Spend_Local | E47: =Sensitivity!$B$17 | F47: =Sensitivity!C$16 | G47: =Percentage_Locals_Init+(C47-Percentage_Locals_Init)*(1-EXP(-B47/Marketing_Saturation_Spend)) | H47: =Tourists_Base*G47/(1-G47) | I47: =H47-Locals_Base | J47: =Locals_Base*(1-(1-EXP(-B47/Marketing_Saturation_Spend)))*Local_AudioTour_Rate_Init+(H47-Locals_Base*(1-(1-EXP(-B47/Marketing_Saturation_Spend))))*F47 | K47: =AudioTourist_Base+J47 | L47: =MAX(0,ROUNDUP((K47-Device_Capacity)/Device_Block_Size,0)) | M47: =L47*Device_Block_Cost/Device_Amort_Days | N47: =Fee_Keep*(Locals_Base*(1-(1-EXP(-B47/Marketing_Saturation_Spend)))*Local_AudioTour_Rate_Init*AudioTour_Price+(H47-Locals_Base*(1-(1-EXP(-B47/Marketing_Saturation_Spend))))*F47*E47-AudioLocal_Base*AudioTour_Price) | O47: =(K47-Total_Daily_AudioTour)*Headset_Cost | P47: =I47*D47+Locals_Base*(1-EXP(-B47/Marketing_Saturation_Spend))*F47*GiftShop_Spillover | Q47: =N47-O47-M47+P47 | R47: =Q47*Campaign_Days-B47
A48: 2. r1 c2 | B48: =Marketing_Spend | C48: =Locals_Share_Ceiling | D48: =GiftShop_Net_Spend_Local | E48: =Sensitivity!$B$17 | F48: =Sensitivity!D$16 | G48: =Percentage_Locals_Init+(C48-Percentage_Locals_Init)*(1-EXP(-B48/Marketing_Saturation_Spend)) | H48: =Tourists_Base*G48/(1-G48) | I48: =H48-Locals_Base | J48: =Locals_Base*(1-(1-EXP(-B48/Marketing_Saturation_Spend)))*Local_AudioTour_Rate_Init+(H48-Locals_Base*(1-(1-EXP(-B48/Marketing_Saturation_Spend))))*F48 | K48: =AudioTourist_Base+J48 | L48: =MAX(0,ROUNDUP((K48-Device_Capacity)/Device_Block_Size,0)) | M48: =L48*Device_Block_Cost/Device_Amort_Days | N48: =Fee_Keep*(Locals_Base*(1-(1-EXP(-B48/Marketing_Saturation_Spend)))*Local_AudioTour_Rate_Init*AudioTour_Price+(H48-Locals_Base*(1-(1-EXP(-B48/Marketing_Saturation_Spend))))*F48*E48-AudioLocal_Base*AudioTour_Price) | O48: =(K48-Total_Daily_AudioTour)*Headset_Cost | P48: =I48*D48+Locals_Base*(1-EXP(-B48/Marketing_Saturation_Spend))*F48*GiftShop_Spillover | Q48: =N48-O48-M48+P48 | R48: =Q48*Campaign_Days-B48
A49: 2. r1 c3 | B49: =Marketing_Spend | C49: =Locals_Share_Ceiling | D49: =GiftShop_Net_Spend_Local | E49: =Sensitivity!$B$17 | F49: =Sensitivity!E$16 | G49: =Percentage_Locals_Init+(C49-Percentage_Locals_Init)*(1-EXP(-B49/Marketing_Saturation_Spend)) | H49: =Tourists_Base*G49/(1-G49) | I49: =H49-Locals_Base | J49: =Locals_Base*(1-(1-EXP(-B49/Marketing_Saturation_Spend)))*Local_AudioTour_Rate_Init+(H49-Locals_Base*(1-(1-EXP(-B49/Marketing_Saturation_Spend))))*F49 | K49: =AudioTourist_Base+J49 | L49: =MAX(0,ROUNDUP((K49-Device_Capacity)/Device_Block_Size,0)) | M49: =L49*Device_Block_Cost/Device_Amort_Days | N49: =Fee_Keep*(Locals_Base*(1-(1-EXP(-B49/Marketing_Saturation_Spend)))*Local_AudioTour_Rate_Init*AudioTour_Price+(H49-Locals_Base*(1-(1-EXP(-B49/Marketing_Saturation_Spend))))*F49*E49-AudioLocal_Base*AudioTour_Price) | O49: =(K49-Total_Daily_AudioTour)*Headset_Cost | P49: =I49*D49+Locals_Base*(1-EXP(-B49/Marketing_Saturation_Spend))*F49*GiftShop_Spillover | Q49: =N49-O49-M49+P49 | R49: =Q49*Campaign_Days-B49
A50: 2. r1 c4 | B50: =Marketing_Spend | C50: =Locals_Share_Ceiling | D50: =GiftShop_Net_Spend_Local | E50: =Sensitivity!$B$17 | F50: =Sensitivity!F$16 | G50: =Percentage_Locals_Init+(C50-Percentage_Locals_Init)*(1-EXP(-B50/Marketing_Saturation_Spend)) | H50: =Tourists_Base*G50/(1-G50) | I50: =H50-Locals_Base | J50: =Locals_Base*(1-(1-EXP(-B50/Marketing_Saturation_Spend)))*Local_AudioTour_Rate_Init+(H50-Locals_Base*(1-(1-EXP(-B50/Marketing_Saturation_Spend))))*F50 | K50: =AudioTourist_Base+J50 | L50: =MAX(0,ROUNDUP((K50-Device_Capacity)/Device_Block_Size,0)) | M50: =L50*Device_Block_Cost/Device_Amort_Days | N50: =Fee_Keep*(Locals_Base*(1-(1-EXP(-B50/Marketing_Saturation_Spend)))*Local_AudioTour_Rate_Init*AudioTour_Price+(H50-Locals_Base*(1-(1-EXP(-B50/Marketing_Saturation_Spend))))*F50*E50-AudioLocal_Base*AudioTour_Price) | O50: =(K50-Total_Daily_AudioTour)*Headset_Cost | P50: =I50*D50+Locals_Base*(1-EXP(-B50/Marketing_Saturation_Spend))*F50*GiftShop_Spillover | Q50: =N50-O50-M50+P50 | R50: =Q50*Campaign_Days-B50
A51: 2. r1 c5 | B51: =Marketing_Spend | C51: =Locals_Share_Ceiling | D51: =GiftShop_Net_Spend_Local | E51: =Sensitivity!$B$17 | F51: =Sensitivity!G$16 | G51: =Percentage_Locals_Init+(C51-Percentage_Locals_Init)*(1-EXP(-B51/Marketing_Saturation_Spend)) | H51: =Tourists_Base*G51/(1-G51) | I51: =H51-Locals_Base | J51: =Locals_Base*(1-(1-EXP(-B51/Marketing_Saturation_Spend)))*Local_AudioTour_Rate_Init+(H51-Locals_Base*(1-(1-EXP(-B51/Marketing_Saturation_Spend))))*F51 | K51: =AudioTourist_Base+J51 | L51: =MAX(0,ROUNDUP((K51-Device_Capacity)/Device_Block_Size,0)) | M51: =L51*Device_Block_Cost/Device_Amort_Days | N51: =Fee_Keep*(Locals_Base*(1-(1-EXP(-B51/Marketing_Saturation_Spend)))*Local_AudioTour_Rate_Init*AudioTour_Price+(H51-Locals_Base*(1-(1-EXP(-B51/Marketing_Saturation_Spend))))*F51*E51-AudioLocal_Base*AudioTour_Price) | O51: =(K51-Total_Daily_AudioTour)*Headset_Cost | P51: =I51*D51+Locals_Base*(1-EXP(-B51/Marketing_Saturation_Spend))*F51*GiftShop_Spillover | Q51: =N51-O51-M51+P51 | R51: =Q51*Campaign_Days-B51
A52: 2. r2 c1 | B52: =Marketing_Spend | C52: =Locals_Share_Ceiling | D52: =GiftShop_Net_Spend_Local | E52: =Sensitivity!$B$18 | F52: =Sensitivity!C$16 | G52: =Percentage_Locals_Init+(C52-Percentage_Locals_Init)*(1-EXP(-B52/Marketing_Saturation_Spend)) | H52: =Tourists_Base*G52/(1-G52) | I52: =H52-Locals_Base | J52: =Locals_Base*(1-(1-EXP(-B52/Marketing_Saturation_Spend)))*Local_AudioTour_Rate_Init+(H52-Locals_Base*(1-(1-EXP(-B52/Marketing_Saturation_Spend))))*F52 | K52: =AudioTourist_Base+J52 | L52: =MAX(0,ROUNDUP((K52-Device_Capacity)/Device_Block_Size,0)) | M52: =L52*Device_Block_Cost/Device_Amort_Days | N52: =Fee_Keep*(Locals_Base*(1-(1-EXP(-B52/Marketing_Saturation_Spend)))*Local_AudioTour_Rate_Init*AudioTour_Price+(H52-Locals_Base*(1-(1-EXP(-B52/Marketing_Saturation_Spend))))*F52*E52-AudioLocal_Base*AudioTour_Price) | O52: =(K52-Total_Daily_AudioTour)*Headset_Cost | P52: =I52*D52+Locals_Base*(1-EXP(-B52/Marketing_Saturation_Spend))*F52*GiftShop_Spillover | Q52: =N52-O52-M52+P52 | R52: =Q52*Campaign_Days-B52
A53: 2. r2 c2 | B53: =Marketing_Spend | C53: =Locals_Share_Ceiling | D53: =GiftShop_Net_Spend_Local | E53: =Sensitivity!$B$18 | F53: =Sensitivity!D$16 | G53: =Percentage_Locals_Init+(C53-Percentage_Locals_Init)*(1-EXP(-B53/Marketing_Saturation_Spend)) | H53: =Tourists_Base*G53/(1-G53) | I53: =H53-Locals_Base | J53: =Locals_Base*(1-(1-EXP(-B53/Marketing_Saturation_Spend)))*Local_AudioTour_Rate_Init+(H53-Locals_Base*(1-(1-EXP(-B53/Marketing_Saturation_Spend))))*F53 | K53: =AudioTourist_Base+J53 | L53: =MAX(0,ROUNDUP((K53-Device_Capacity)/Device_Block_Size,0)) | M53: =L53*Device_Block_Cost/Device_Amort_Days | N53: =Fee_Keep*(Locals_Base*(1-(1-EXP(-B53/Marketing_Saturation_Spend)))*Local_AudioTour_Rate_Init*AudioTour_Price+(H53-Locals_Base*(1-(1-EXP(-B53/Marketing_Saturation_Spend))))*F53*E53-AudioLocal_Base*AudioTour_Price) | O53: =(K53-Total_Daily_AudioTour)*Headset_Cost | P53: =I53*D53+Locals_Base*(1-EXP(-B53/Marketing_Saturation_Spend))*F53*GiftShop_Spillover | Q53: =N53-O53-M53+P53 | R53: =Q53*Campaign_Days-B53
A54: 2. r2 c3 | B54: =Marketing_Spend | C54: =Locals_Share_Ceiling | D54: =GiftShop_Net_Spend_Local | E54: =Sensitivity!$B$18 | F54: =Sensitivity!E$16 | G54: =Percentage_Locals_Init+(C54-Percentage_Locals_Init)*(1-EXP(-B54/Marketing_Saturation_Spend)) | H54: =Tourists_Base*G54/(1-G54) | I54: =H54-Locals_Base | J54: =Locals_Base*(1-(1-EXP(-B54/Marketing_Saturation_Spend)))*Local_AudioTour_Rate_Init+(H54-Locals_Base*(1-(1-EXP(-B54/Marketing_Saturation_Spend))))*F54 | K54: =AudioTourist_Base+J54 | L54: =MAX(0,ROUNDUP((K54-Device_Capacity)/Device_Block_Size,0)) | M54: =L54*Device_Block_Cost/Device_Amort_Days | N54: =Fee_Keep*(Locals_Base*(1-(1-EXP(-B54/Marketing_Saturation_Spend)))*Local_AudioTour_Rate_Init*AudioTour_Price+(H54-Locals_Base*(1-(1-EXP(-B54/Marketing_Saturation_Spend))))*F54*E54-AudioLocal_Base*AudioTour_Price) | O54: =(K54-Total_Daily_AudioTour)*Headset_Cost | P54: =I54*D54+Locals_Base*(1-EXP(-B54/Marketing_Saturation_Spend))*F54*GiftShop_Spillover | Q54: =N54-O54-M54+P54 | R54: =Q54*Campaign_Days-B54
A55: 2. r2 c4 | B55: =Marketing_Spend | C55: =Locals_Share_Ceiling | D55: =GiftShop_Net_Spend_Local | E55: =Sensitivity!$B$18 | F55: =Sensitivity!F$16 | G55: =Percentage_Locals_Init+(C55-Percentage_Locals_Init)*(1-EXP(-B55/Marketing_Saturation_Spend)) | H55: =Tourists_Base*G55/(1-G55) | I55: =H55-Locals_Base | J55: =Locals_Base*(1-(1-EXP(-B55/Marketing_Saturation_Spend)))*Local_AudioTour_Rate_Init+(H55-Locals_Base*(1-(1-EXP(-B55/Marketing_Saturation_Spend))))*F55 | K55: =AudioTourist_Base+J55 | L55: =MAX(0,ROUNDUP((K55-Device_Capacity)/Device_Block_Size,0)) | M55: =L55*Device_Block_Cost/Device_Amort_Days | N55: =Fee_Keep*(Locals_Base*(1-(1-EXP(-B55/Marketing_Saturation_Spend)))*Local_AudioTour_Rate_Init*AudioTour_Price+(H55-Locals_Base*(1-(1-EXP(-B55/Marketing_Saturation_Spend))))*F55*E55-AudioLocal_Base*AudioTour_Price) | O55: =(K55-Total_Daily_AudioTour)*Headset_Cost | P55: =I55*D55+Locals_Base*(1-EXP(-B55/Marketing_Saturation_Spend))*F55*GiftShop_Spillover | Q55: =N55-O55-M55+P55 | R55: =Q55*Campaign_Days-B55
A56: 2. r2 c5 | B56: =Marketing_Spend | C56: =Locals_Share_Ceiling | D56: =GiftShop_Net_Spend_Local | E56: =Sensitivity!$B$18 | F56: =Sensitivity!G$16 | G56: =Percentage_Locals_Init+(C56-Percentage_Locals_Init)*(1-EXP(-B56/Marketing_Saturation_Spend)) | H56: =Tourists_Base*G56/(1-G56) | I56: =H56-Locals_Base | J56: =Locals_Base*(1-(1-EXP(-B56/Marketing_Saturation_Spend)))*Local_AudioTour_Rate_Init+(H56-Locals_Base*(1-(1-EXP(-B56/Marketing_Saturation_Spend))))*F56 | K56: =AudioTourist_Base+J56 | L56: =MAX(0,ROUNDUP((K56-Device_Capacity)/Device_Block_Size,0)) | M56: =L56*Device_Block_Cost/Device_Amort_Days | N56: =Fee_Keep*(Locals_Base*(1-(1-EXP(-B56/Marketing_Saturation_Spend)))*Local_AudioTour_Rate_Init*AudioTour_Price+(H56-Locals_Base*(1-(1-EXP(-B56/Marketing_Saturation_Spend))))*F56*E56-AudioLocal_Base*AudioTour_Price) | O56: =(K56-Total_Daily_AudioTour)*Headset_Cost | P56: =I56*D56+Locals_Base*(1-EXP(-B56/Marketing_Saturation_Spend))*F56*GiftShop_Spillover | Q56: =N56-O56-M56+P56 | R56: =Q56*Campaign_Days-B56
A57: 2. r3 c1 | B57: =Marketing_Spend | C57: =Locals_Share_Ceiling | D57: =GiftShop_Net_Spend_Local | E57: =Sensitivity!$B$19 | F57: =Sensitivity!C$16 | G57: =Percentage_Locals_Init+(C57-Percentage_Locals_Init)*(1-EXP(-B57/Marketing_Saturation_Spend)) | H57: =Tourists_Base*G57/(1-G57) | I57: =H57-Locals_Base | J57: =Locals_Base*(1-(1-EXP(-B57/Marketing_Saturation_Spend)))*Local_AudioTour_Rate_Init+(H57-Locals_Base*(1-(1-EXP(-B57/Marketing_Saturation_Spend))))*F57 | K57: =AudioTourist_Base+J57 | L57: =MAX(0,ROUNDUP((K57-Device_Capacity)/Device_Block_Size,0)) | M57: =L57*Device_Block_Cost/Device_Amort_Days | N57: =Fee_Keep*(Locals_Base*(1-(1-EXP(-B57/Marketing_Saturation_Spend)))*Local_AudioTour_Rate_Init*AudioTour_Price+(H57-Locals_Base*(1-(1-EXP(-B57/Marketing_Saturation_Spend))))*F57*E57-AudioLocal_Base*AudioTour_Price) | O57: =(K57-Total_Daily_AudioTour)*Headset_Cost | P57: =I57*D57+Locals_Base*(1-EXP(-B57/Marketing_Saturation_Spend))*F57*GiftShop_Spillover | Q57: =N57-O57-M57+P57 | R57: =Q57*Campaign_Days-B57
A58: 2. r3 c2 | B58: =Marketing_Spend | C58: =Locals_Share_Ceiling | D58: =GiftShop_Net_Spend_Local | E58: =Sensitivity!$B$19 | F58: =Sensitivity!D$16 | G58: =Percentage_Locals_Init+(C58-Percentage_Locals_Init)*(1-EXP(-B58/Marketing_Saturation_Spend)) | H58: =Tourists_Base*G58/(1-G58) | I58: =H58-Locals_Base | J58: =Locals_Base*(1-(1-EXP(-B58/Marketing_Saturation_Spend)))*Local_AudioTour_Rate_Init+(H58-Locals_Base*(1-(1-EXP(-B58/Marketing_Saturation_Spend))))*F58 | K58: =AudioTourist_Base+J58 | L58: =MAX(0,ROUNDUP((K58-Device_Capacity)/Device_Block_Size,0)) | M58: =L58*Device_Block_Cost/Device_Amort_Days | N58: =Fee_Keep*(Locals_Base*(1-(1-EXP(-B58/Marketing_Saturation_Spend)))*Local_AudioTour_Rate_Init*AudioTour_Price+(H58-Locals_Base*(1-(1-EXP(-B58/Marketing_Saturation_Spend))))*F58*E58-AudioLocal_Base*AudioTour_Price) | O58: =(K58-Total_Daily_AudioTour)*Headset_Cost | P58: =I58*D58+Locals_Base*(1-EXP(-B58/Marketing_Saturation_Spend))*F58*GiftShop_Spillover | Q58: =N58-O58-M58+P58 | R58: =Q58*Campaign_Days-B58
A59: 2. r3 c3 | B59: =Marketing_Spend | C59: =Locals_Share_Ceiling | D59: =GiftShop_Net_Spend_Local | E59: =Sensitivity!$B$19 | F59: =Sensitivity!E$16 | G59: =Percentage_Locals_Init+(C59-Percentage_Locals_Init)*(1-EXP(-B59/Marketing_Saturation_Spend)) | H59: =Tourists_Base*G59/(1-G59) | I59: =H59-Locals_Base | J59: =Locals_Base*(1-(1-EXP(-B59/Marketing_Saturation_Spend)))*Local_AudioTour_Rate_Init+(H59-Locals_Base*(1-(1-EXP(-B59/Marketing_Saturation_Spend))))*F59 | K59: =AudioTourist_Base+J59 | L59: =MAX(0,ROUNDUP((K59-Device_Capacity)/Device_Block_Size,0)) | M59: =L59*Device_Block_Cost/Device_Amort_Days | N59: =Fee_Keep*(Locals_Base*(1-(1-EXP(-B59/Marketing_Saturation_Spend)))*Local_AudioTour_Rate_Init*AudioTour_Price+(H59-Locals_Base*(1-(1-EXP(-B59/Marketing_Saturation_Spend))))*F59*E59-AudioLocal_Base*AudioTour_Price) | O59: =(K59-Total_Daily_AudioTour)*Headset_Cost | P59: =I59*D59+Locals_Base*(1-EXP(-B59/Marketing_Saturation_Spend))*F59*GiftShop_Spillover | Q59: =N59-O59-M59+P59 | R59: =Q59*Campaign_Days-B59
A60: 2. r3 c4 | B60: =Marketing_Spend | C60: =Locals_Share_Ceiling | D60: =GiftShop_Net_Spend_Local | E60: =Sensitivity!$B$19 | F60: =Sensitivity!F$16 | G60: =Percentage_Locals_Init+(C60-Percentage_Locals_Init)*(1-EXP(-B60/Marketing_Saturation_Spend)) | H60: =Tourists_Base*G60/(1-G60) | I60: =H60-Locals_Base | J60: =Locals_Base*(1-(1-EXP(-B60/Marketing_Saturation_Spend)))*Local_AudioTour_Rate_Init+(H60-Locals_Base*(1-(1-EXP(-B60/Marketing_Saturation_Spend))))*F60 | K60: =AudioTourist_Base+J60 | L60: =MAX(0,ROUNDUP((K60-Device_Capacity)/Device_Block_Size,0)) | M60: =L60*Device_Block_Cost/Device_Amort_Days | N60: =Fee_Keep*(Locals_Base*(1-(1-EXP(-B60/Marketing_Saturation_Spend)))*Local_AudioTour_Rate_Init*AudioTour_Price+(H60-Locals_Base*(1-(1-EXP(-B60/Marketing_Saturation_Spend))))*F60*E60-AudioLocal_Base*AudioTour_Price) | O60: =(K60-Total_Daily_AudioTour)*Headset_Cost | P60: =I60*D60+Locals_Base*(1-EXP(-B60/Marketing_Saturation_Spend))*F60*GiftShop_Spillover | Q60: =N60-O60-M60+P60 | R60: =Q60*Campaign_Days-B60
A61: 2. r3 c5 | B61: =Marketing_Spend | C61: =Locals_Share_Ceiling | D61: =GiftShop_Net_Spend_Local | E61: =Sensitivity!$B$19 | F61: =Sensitivity!G$16 | G61: =Percentage_Locals_Init+(C61-Percentage_Locals_Init)*(1-EXP(-B61/Marketing_Saturation_Spend)) | H61: =Tourists_Base*G61/(1-G61) | I61: =H61-Locals_Base | J61: =Locals_Base*(1-(1-EXP(-B61/Marketing_Saturation_Spend)))*Local_AudioTour_Rate_Init+(H61-Locals_Base*(1-(1-EXP(-B61/Marketing_Saturation_Spend))))*F61 | K61: =AudioTourist_Base+J61 | L61: =MAX(0,ROUNDUP((K61-Device_Capacity)/Device_Block_Size,0)) | M61: =L61*Device_Block_Cost/Device_Amort_Days | N61: =Fee_Keep*(Locals_Base*(1-(1-EXP(-B61/Marketing_Saturation_Spend)))*Local_AudioTour_Rate_Init*AudioTour_Price+(H61-Locals_Base*(1-(1-EXP(-B61/Marketing_Saturation_Spend))))*F61*E61-AudioLocal_Base*AudioTour_Price) | O61: =(K61-Total_Daily_AudioTour)*Headset_Cost | P61: =I61*D61+Locals_Base*(1-EXP(-B61/Marketing_Saturation_Spend))*F61*GiftShop_Spillover | Q61: =N61-O61-M61+P61 | R61: =Q61*Campaign_Days-B61
A62: 2. r4 c1 | B62: =Marketing_Spend | C62: =Locals_Share_Ceiling | D62: =GiftShop_Net_Spend_Local | E62: =Sensitivity!$B$20 | F62: =Sensitivity!C$16 | G62: =Percentage_Locals_Init+(C62-Percentage_Locals_Init)*(1-EXP(-B62/Marketing_Saturation_Spend)) | H62: =Tourists_Base*G62/(1-G62) | I62: =H62-Locals_Base | J62: =Locals_Base*(1-(1-EXP(-B62/Marketing_Saturation_Spend)))*Local_AudioTour_Rate_Init+(H62-Locals_Base*(1-(1-EXP(-B62/Marketing_Saturation_Spend))))*F62 | K62: =AudioTourist_Base+J62 | L62: =MAX(0,ROUNDUP((K62-Device_Capacity)/Device_Block_Size,0)) | M62: =L62*Device_Block_Cost/Device_Amort_Days | N62: =Fee_Keep*(Locals_Base*(1-(1-EXP(-B62/Marketing_Saturation_Spend)))*Local_AudioTour_Rate_Init*AudioTour_Price+(H62-Locals_Base*(1-(1-EXP(-B62/Marketing_Saturation_Spend))))*F62*E62-AudioLocal_Base*AudioTour_Price) | O62: =(K62-Total_Daily_AudioTour)*Headset_Cost | P62: =I62*D62+Locals_Base*(1-EXP(-B62/Marketing_Saturation_Spend))*F62*GiftShop_Spillover | Q62: =N62-O62-M62+P62 | R62: =Q62*Campaign_Days-B62
A63: 2. r4 c2 | B63: =Marketing_Spend | C63: =Locals_Share_Ceiling | D63: =GiftShop_Net_Spend_Local | E63: =Sensitivity!$B$20 | F63: =Sensitivity!D$16 | G63: =Percentage_Locals_Init+(C63-Percentage_Locals_Init)*(1-EXP(-B63/Marketing_Saturation_Spend)) | H63: =Tourists_Base*G63/(1-G63) | I63: =H63-Locals_Base | J63: =Locals_Base*(1-(1-EXP(-B63/Marketing_Saturation_Spend)))*Local_AudioTour_Rate_Init+(H63-Locals_Base*(1-(1-EXP(-B63/Marketing_Saturation_Spend))))*F63 | K63: =AudioTourist_Base+J63 | L63: =MAX(0,ROUNDUP((K63-Device_Capacity)/Device_Block_Size,0)) | M63: =L63*Device_Block_Cost/Device_Amort_Days | N63: =Fee_Keep*(Locals_Base*(1-(1-EXP(-B63/Marketing_Saturation_Spend)))*Local_AudioTour_Rate_Init*AudioTour_Price+(H63-Locals_Base*(1-(1-EXP(-B63/Marketing_Saturation_Spend))))*F63*E63-AudioLocal_Base*AudioTour_Price) | O63: =(K63-Total_Daily_AudioTour)*Headset_Cost | P63: =I63*D63+Locals_Base*(1-EXP(-B63/Marketing_Saturation_Spend))*F63*GiftShop_Spillover | Q63: =N63-O63-M63+P63 | R63: =Q63*Campaign_Days-B63
A64: 2. r4 c3 | B64: =Marketing_Spend | C64: =Locals_Share_Ceiling | D64: =GiftShop_Net_Spend_Local | E64: =Sensitivity!$B$20 | F64: =Sensitivity!E$16 | G64: =Percentage_Locals_Init+(C64-Percentage_Locals_Init)*(1-EXP(-B64/Marketing_Saturation_Spend)) | H64: =Tourists_Base*G64/(1-G64) | I64: =H64-Locals_Base | J64: =Locals_Base*(1-(1-EXP(-B64/Marketing_Saturation_Spend)))*Local_AudioTour_Rate_Init+(H64-Locals_Base*(1-(1-EXP(-B64/Marketing_Saturation_Spend))))*F64 | K64: =AudioTourist_Base+J64 | L64: =MAX(0,ROUNDUP((K64-Device_Capacity)/Device_Block_Size,0)) | M64: =L64*Device_Block_Cost/Device_Amort_Days | N64: =Fee_Keep*(Locals_Base*(1-(1-EXP(-B64/Marketing_Saturation_Spend)))*Local_AudioTour_Rate_Init*AudioTour_Price+(H64-Locals_Base*(1-(1-EXP(-B64/Marketing_Saturation_Spend))))*F64*E64-AudioLocal_Base*AudioTour_Price) | O64: =(K64-Total_Daily_AudioTour)*Headset_Cost | P64: =I64*D64+Locals_Base*(1-EXP(-B64/Marketing_Saturation_Spend))*F64*GiftShop_Spillover | Q64: =N64-O64-M64+P64 | R64: =Q64*Campaign_Days-B64
A65: 2. r4 c4 | B65: =Marketing_Spend | C65: =Locals_Share_Ceiling | D65: =GiftShop_Net_Spend_Local | E65: =Sensitivity!$B$20 | F65: =Sensitivity!F$16 | G65: =Percentage_Locals_Init+(C65-Percentage_Locals_Init)*(1-EXP(-B65/Marketing_Saturation_Spend)) | H65: =Tourists_Base*G65/(1-G65) | I65: =H65-Locals_Base | J65: =Locals_Base*(1-(1-EXP(-B65/Marketing_Saturation_Spend)))*Local_AudioTour_Rate_Init+(H65-Locals_Base*(1-(1-EXP(-B65/Marketing_Saturation_Spend))))*F65 | K65: =AudioTourist_Base+J65 | L65: =MAX(0,ROUNDUP((K65-Device_Capacity)/Device_Block_Size,0)) | M65: =L65*Device_Block_Cost/Device_Amort_Days | N65: =Fee_Keep*(Locals_Base*(1-(1-EXP(-B65/Marketing_Saturation_Spend)))*Local_AudioTour_Rate_Init*AudioTour_Price+(H65-Locals_Base*(1-(1-EXP(-B65/Marketing_Saturation_Spend))))*F65*E65-AudioLocal_Base*AudioTour_Price) | O65: =(K65-Total_Daily_AudioTour)*Headset_Cost | P65: =I65*D65+Locals_Base*(1-EXP(-B65/Marketing_Saturation_Spend))*F65*GiftShop_Spillover | Q65: =N65-O65-M65+P65 | R65: =Q65*Campaign_Days-B65
A66: 2. r4 c5 | B66: =Marketing_Spend | C66: =Locals_Share_Ceiling | D66: =GiftShop_Net_Spend_Local | E66: =Sensitivity!$B$20 | F66: =Sensitivity!G$16 | G66: =Percentage_Locals_Init+(C66-Percentage_Locals_Init)*(1-EXP(-B66/Marketing_Saturation_Spend)) | H66: =Tourists_Base*G66/(1-G66) | I66: =H66-Locals_Base | J66: =Locals_Base*(1-(1-EXP(-B66/Marketing_Saturation_Spend)))*Local_AudioTour_Rate_Init+(H66-Locals_Base*(1-(1-EXP(-B66/Marketing_Saturation_Spend))))*F66 | K66: =AudioTourist_Base+J66 | L66: =MAX(0,ROUNDUP((K66-Device_Capacity)/Device_Block_Size,0)) | M66: =L66*Device_Block_Cost/Device_Amort_Days | N66: =Fee_Keep*(Locals_Base*(1-(1-EXP(-B66/Marketing_Saturation_Spend)))*Local_AudioTour_Rate_Init*AudioTour_Price+(H66-Locals_Base*(1-(1-EXP(-B66/Marketing_Saturation_Spend))))*F66*E66-AudioLocal_Base*AudioTour_Price) | O66: =(K66-Total_Daily_AudioTour)*Headset_Cost | P66: =I66*D66+Locals_Base*(1-EXP(-B66/Marketing_Saturation_Spend))*F66*GiftShop_Spillover | Q66: =N66-O66-M66+P66 | R66: =Q66*Campaign_Days-B66
A67: 2. r5 c1 | B67: =Marketing_Spend | C67: =Locals_Share_Ceiling | D67: =GiftShop_Net_Spend_Local | E67: =Sensitivity!$B$21 | F67: =Sensitivity!C$16 | G67: =Percentage_Locals_Init+(C67-Percentage_Locals_Init)*(1-EXP(-B67/Marketing_Saturation_Spend)) | H67: =Tourists_Base*G67/(1-G67) | I67: =H67-Locals_Base | J67: =Locals_Base*(1-(1-EXP(-B67/Marketing_Saturation_Spend)))*Local_AudioTour_Rate_Init+(H67-Locals_Base*(1-(1-EXP(-B67/Marketing_Saturation_Spend))))*F67 | K67: =AudioTourist_Base+J67 | L67: =MAX(0,ROUNDUP((K67-Device_Capacity)/Device_Block_Size,0)) | M67: =L67*Device_Block_Cost/Device_Amort_Days | N67: =Fee_Keep*(Locals_Base*(1-(1-EXP(-B67/Marketing_Saturation_Spend)))*Local_AudioTour_Rate_Init*AudioTour_Price+(H67-Locals_Base*(1-(1-EXP(-B67/Marketing_Saturation_Spend))))*F67*E67-AudioLocal_Base*AudioTour_Price) | O67: =(K67-Total_Daily_AudioTour)*Headset_Cost | P67: =I67*D67+Locals_Base*(1-EXP(-B67/Marketing_Saturation_Spend))*F67*GiftShop_Spillover | Q67: =N67-O67-M67+P67 | R67: =Q67*Campaign_Days-B67
A68: 2. r5 c2 | B68: =Marketing_Spend | C68: =Locals_Share_Ceiling | D68: =GiftShop_Net_Spend_Local | E68: =Sensitivity!$B$21 | F68: =Sensitivity!D$16 | G68: =Percentage_Locals_Init+(C68-Percentage_Locals_Init)*(1-EXP(-B68/Marketing_Saturation_Spend)) | H68: =Tourists_Base*G68/(1-G68) | I68: =H68-Locals_Base | J68: =Locals_Base*(1-(1-EXP(-B68/Marketing_Saturation_Spend)))*Local_AudioTour_Rate_Init+(H68-Locals_Base*(1-(1-EXP(-B68/Marketing_Saturation_Spend))))*F68 | K68: =AudioTourist_Base+J68 | L68: =MAX(0,ROUNDUP((K68-Device_Capacity)/Device_Block_Size,0)) | M68: =L68*Device_Block_Cost/Device_Amort_Days | N68: =Fee_Keep*(Locals_Base*(1-(1-EXP(-B68/Marketing_Saturation_Spend)))*Local_AudioTour_Rate_Init*AudioTour_Price+(H68-Locals_Base*(1-(1-EXP(-B68/Marketing_Saturation_Spend))))*F68*E68-AudioLocal_Base*AudioTour_Price) | O68: =(K68-Total_Daily_AudioTour)*Headset_Cost | P68: =I68*D68+Locals_Base*(1-EXP(-B68/Marketing_Saturation_Spend))*F68*GiftShop_Spillover | Q68: =N68-O68-M68+P68 | R68: =Q68*Campaign_Days-B68
A69: 2. r5 c3 | B69: =Marketing_Spend | C69: =Locals_Share_Ceiling | D69: =GiftShop_Net_Spend_Local | E69: =Sensitivity!$B$21 | F69: =Sensitivity!E$16 | G69: =Percentage_Locals_Init+(C69-Percentage_Locals_Init)*(1-EXP(-B69/Marketing_Saturation_Spend)) | H69: =Tourists_Base*G69/(1-G69) | I69: =H69-Locals_Base | J69: =Locals_Base*(1-(1-EXP(-B69/Marketing_Saturation_Spend)))*Local_AudioTour_Rate_Init+(H69-Locals_Base*(1-(1-EXP(-B69/Marketing_Saturation_Spend))))*F69 | K69: =AudioTourist_Base+J69 | L69: =MAX(0,ROUNDUP((K69-Device_Capacity)/Device_Block_Size,0)) | M69: =L69*Device_Block_Cost/Device_Amort_Days | N69: =Fee_Keep*(Locals_Base*(1-(1-EXP(-B69/Marketing_Saturation_Spend)))*Local_AudioTour_Rate_Init*AudioTour_Price+(H69-Locals_Base*(1-(1-EXP(-B69/Marketing_Saturation_Spend))))*F69*E69-AudioLocal_Base*AudioTour_Price) | O69: =(K69-Total_Daily_AudioTour)*Headset_Cost | P69: =I69*D69+Locals_Base*(1-EXP(-B69/Marketing_Saturation_Spend))*F69*GiftShop_Spillover | Q69: =N69-O69-M69+P69 | R69: =Q69*Campaign_Days-B69
A70: 2. r5 c4 | B70: =Marketing_Spend | C70: =Locals_Share_Ceiling | D70: =GiftShop_Net_Spend_Local | E70: =Sensitivity!$B$21 | F70: =Sensitivity!F$16 | G70: =Percentage_Locals_Init+(C70-Percentage_Locals_Init)*(1-EXP(-B70/Marketing_Saturation_Spend)) | H70: =Tourists_Base*G70/(1-G70) | I70: =H70-Locals_Base | J70: =Locals_Base*(1-(1-EXP(-B70/Marketing_Saturation_Spend)))*Local_AudioTour_Rate_Init+(H70-Locals_Base*(1-(1-EXP(-B70/Marketing_Saturation_Spend))))*F70 | K70: =AudioTourist_Base+J70 | L70: =MAX(0,ROUNDUP((K70-Device_Capacity)/Device_Block_Size,0)) | M70: =L70*Device_Block_Cost/Device_Amort_Days | N70: =Fee_Keep*(Locals_Base*(1-(1-EXP(-B70/Marketing_Saturation_Spend)))*Local_AudioTour_Rate_Init*AudioTour_Price+(H70-Locals_Base*(1-(1-EXP(-B70/Marketing_Saturation_Spend))))*F70*E70-AudioLocal_Base*AudioTour_Price) | O70: =(K70-Total_Daily_AudioTour)*Headset_Cost | P70: =I70*D70+Locals_Base*(1-EXP(-B70/Marketing_Saturation_Spend))*F70*GiftShop_Spillover | Q70: =N70-O70-M70+P70 | R70: =Q70*Campaign_Days-B70
A71: 2. r5 c5 | B71: =Marketing_Spend | C71: =Locals_Share_Ceiling | D71: =GiftShop_Net_Spend_Local | E71: =Sensitivity!$B$21 | F71: =Sensitivity!G$16 | G71: =Percentage_Locals_Init+(C71-Percentage_Locals_Init)*(1-EXP(-B71/Marketing_Saturation_Spend)) | H71: =Tourists_Base*G71/(1-G71) | I71: =H71-Locals_Base | J71: =Locals_Base*(1-(1-EXP(-B71/Marketing_Saturation_Spend)))*Local_AudioTour_Rate_Init+(H71-Locals_Base*(1-(1-EXP(-B71/Marketing_Saturation_Spend))))*F71 | K71: =AudioTourist_Base+J71 | L71: =MAX(0,ROUNDUP((K71-Device_Capacity)/Device_Block_Size,0)) | M71: =L71*Device_Block_Cost/Device_Amort_Days | N71: =Fee_Keep*(Locals_Base*(1-(1-EXP(-B71/Marketing_Saturation_Spend)))*Local_AudioTour_Rate_Init*AudioTour_Price+(H71-Locals_Base*(1-(1-EXP(-B71/Marketing_Saturation_Spend))))*F71*E71-AudioLocal_Base*AudioTour_Price) | O71: =(K71-Total_Daily_AudioTour)*Headset_Cost | P71: =I71*D71+Locals_Base*(1-EXP(-B71/Marketing_Saturation_Spend))*F71*GiftShop_Spillover | Q71: =N71-O71-M71+P71 | R71: =Q71*Campaign_Days-B71
A72: 2. r6 c1 | B72: =Marketing_Spend | C72: =Locals_Share_Ceiling | D72: =GiftShop_Net_Spend_Local | E72: =Sensitivity!$B$22 | F72: =Sensitivity!C$16 | G72: =Percentage_Locals_Init+(C72-Percentage_Locals_Init)*(1-EXP(-B72/Marketing_Saturation_Spend)) | H72: =Tourists_Base*G72/(1-G72) | I72: =H72-Locals_Base | J72: =Locals_Base*(1-(1-EXP(-B72/Marketing_Saturation_Spend)))*Local_AudioTour_Rate_Init+(H72-Locals_Base*(1-(1-EXP(-B72/Marketing_Saturation_Spend))))*F72 | K72: =AudioTourist_Base+J72 | L72: =MAX(0,ROUNDUP((K72-Device_Capacity)/Device_Block_Size,0)) | M72: =L72*Device_Block_Cost/Device_Amort_Days | N72: =Fee_Keep*(Locals_Base*(1-(1-EXP(-B72/Marketing_Saturation_Spend)))*Local_AudioTour_Rate_Init*AudioTour_Price+(H72-Locals_Base*(1-(1-EXP(-B72/Marketing_Saturation_Spend))))*F72*E72-AudioLocal_Base*AudioTour_Price) | O72: =(K72-Total_Daily_AudioTour)*Headset_Cost | P72: =I72*D72+Locals_Base*(1-EXP(-B72/Marketing_Saturation_Spend))*F72*GiftShop_Spillover | Q72: =N72-O72-M72+P72 | R72: =Q72*Campaign_Days-B72
A73: 2. r6 c2 | B73: =Marketing_Spend | C73: =Locals_Share_Ceiling | D73: =GiftShop_Net_Spend_Local | E73: =Sensitivity!$B$22 | F73: =Sensitivity!D$16 | G73: =Percentage_Locals_Init+(C73-Percentage_Locals_Init)*(1-EXP(-B73/Marketing_Saturation_Spend)) | H73: =Tourists_Base*G73/(1-G73) | I73: =H73-Locals_Base | J73: =Locals_Base*(1-(1-EXP(-B73/Marketing_Saturation_Spend)))*Local_AudioTour_Rate_Init+(H73-Locals_Base*(1-(1-EXP(-B73/Marketing_Saturation_Spend))))*F73 | K73: =AudioTourist_Base+J73 | L73: =MAX(0,ROUNDUP((K73-Device_Capacity)/Device_Block_Size,0)) | M73: =L73*Device_Block_Cost/Device_Amort_Days | N73: =Fee_Keep*(Locals_Base*(1-(1-EXP(-B73/Marketing_Saturation_Spend)))*Local_AudioTour_Rate_Init*AudioTour_Price+(H73-Locals_Base*(1-(1-EXP(-B73/Marketing_Saturation_Spend))))*F73*E73-AudioLocal_Base*AudioTour_Price) | O73: =(K73-Total_Daily_AudioTour)*Headset_Cost | P73: =I73*D73+Locals_Base*(1-EXP(-B73/Marketing_Saturation_Spend))*F73*GiftShop_Spillover | Q73: =N73-O73-M73+P73 | R73: =Q73*Campaign_Days-B73
A74: 2. r6 c3 | B74: =Marketing_Spend | C74: =Locals_Share_Ceiling | D74: =GiftShop_Net_Spend_Local | E74: =Sensitivity!$B$22 | F74: =Sensitivity!E$16 | G74: =Percentage_Locals_Init+(C74-Percentage_Locals_Init)*(1-EXP(-B74/Marketing_Saturation_Spend)) | H74: =Tourists_Base*G74/(1-G74) | I74: =H74-Locals_Base | J74: =Locals_Base*(1-(1-EXP(-B74/Marketing_Saturation_Spend)))*Local_AudioTour_Rate_Init+(H74-Locals_Base*(1-(1-EXP(-B74/Marketing_Saturation_Spend))))*F74 | K74: =AudioTourist_Base+J74 | L74: =MAX(0,ROUNDUP((K74-Device_Capacity)/Device_Block_Size,0)) | M74: =L74*Device_Block_Cost/Device_Amort_Days | N74: =Fee_Keep*(Locals_Base*(1-(1-EXP(-B74/Marketing_Saturation_Spend)))*Local_AudioTour_Rate_Init*AudioTour_Price+(H74-Locals_Base*(1-(1-EXP(-B74/Marketing_Saturation_Spend))))*F74*E74-AudioLocal_Base*AudioTour_Price) | O74: =(K74-Total_Daily_AudioTour)*Headset_Cost | P74: =I74*D74+Locals_Base*(1-EXP(-B74/Marketing_Saturation_Spend))*F74*GiftShop_Spillover | Q74: =N74-O74-M74+P74 | R74: =Q74*Campaign_Days-B74
A75: 2. r6 c4 | B75: =Marketing_Spend | C75: =Locals_Share_Ceiling | D75: =GiftShop_Net_Spend_Local | E75: =Sensitivity!$B$22 | F75: =Sensitivity!F$16 | G75: =Percentage_Locals_Init+(C75-Percentage_Locals_Init)*(1-EXP(-B75/Marketing_Saturation_Spend)) | H75: =Tourists_Base*G75/(1-G75) | I75: =H75-Locals_Base | J75: =Locals_Base*(1-(1-EXP(-B75/Marketing_Saturation_Spend)))*Local_AudioTour_Rate_Init+(H75-Locals_Base*(1-(1-EXP(-B75/Marketing_Saturation_Spend))))*F75 | K75: =AudioTourist_Base+J75 | L75: =MAX(0,ROUNDUP((K75-Device_Capacity)/Device_Block_Size,0)) | M75: =L75*Device_Block_Cost/Device_Amort_Days | N75: =Fee_Keep*(Locals_Base*(1-(1-EXP(-B75/Marketing_Saturation_Spend)))*Local_AudioTour_Rate_Init*AudioTour_Price+(H75-Locals_Base*(1-(1-EXP(-B75/Marketing_Saturation_Spend))))*F75*E75-AudioLocal_Base*AudioTour_Price) | O75: =(K75-Total_Daily_AudioTour)*Headset_Cost | P75: =I75*D75+Locals_Base*(1-EXP(-B75/Marketing_Saturation_Spend))*F75*GiftShop_Spillover | Q75: =N75-O75-M75+P75 | R75: =Q75*Campaign_Days-B75
A76: 2. r6 c5 | B76: =Marketing_Spend | C76: =Locals_Share_Ceiling | D76: =GiftShop_Net_Spend_Local | E76: =Sensitivity!$B$22 | F76: =Sensitivity!G$16 | G76: =Percentage_Locals_Init+(C76-Percentage_Locals_Init)*(1-EXP(-B76/Marketing_Saturation_Spend)) | H76: =Tourists_Base*G76/(1-G76) | I76: =H76-Locals_Base | J76: =Locals_Base*(1-(1-EXP(-B76/Marketing_Saturation_Spend)))*Local_AudioTour_Rate_Init+(H76-Locals_Base*(1-(1-EXP(-B76/Marketing_Saturation_Spend))))*F76 | K76: =AudioTourist_Base+J76 | L76: =MAX(0,ROUNDUP((K76-Device_Capacity)/Device_Block_Size,0)) | M76: =L76*Device_Block_Cost/Device_Amort_Days | N76: =Fee_Keep*(Locals_Base*(1-(1-EXP(-B76/Marketing_Saturation_Spend)))*Local_AudioTour_Rate_Init*AudioTour_Price+(H76-Locals_Base*(1-(1-EXP(-B76/Marketing_Saturation_Spend))))*F76*E76-AudioLocal_Base*AudioTour_Price) | O76: =(K76-Total_Daily_AudioTour)*Headset_Cost | P76: =I76*D76+Locals_Base*(1-EXP(-B76/Marketing_Saturation_Spend))*F76*GiftShop_Spillover | Q76: =N76-O76-M76+P76 | R76: =Q76*Campaign_Days-B76
A77: 2. r7 c1 | B77: =Marketing_Spend | C77: =Locals_Share_Ceiling | D77: =GiftShop_Net_Spend_Local | E77: =Sensitivity!$B$23 | F77: =Sensitivity!C$16 | G77: =Percentage_Locals_Init+(C77-Percentage_Locals_Init)*(1-EXP(-B77/Marketing_Saturation_Spend)) | H77: =Tourists_Base*G77/(1-G77) | I77: =H77-Locals_Base | J77: =Locals_Base*(1-(1-EXP(-B77/Marketing_Saturation_Spend)))*Local_AudioTour_Rate_Init+(H77-Locals_Base*(1-(1-EXP(-B77/Marketing_Saturation_Spend))))*F77 | K77: =AudioTourist_Base+J77 | L77: =MAX(0,ROUNDUP((K77-Device_Capacity)/Device_Block_Size,0)) | M77: =L77*Device_Block_Cost/Device_Amort_Days | N77: =Fee_Keep*(Locals_Base*(1-(1-EXP(-B77/Marketing_Saturation_Spend)))*Local_AudioTour_Rate_Init*AudioTour_Price+(H77-Locals_Base*(1-(1-EXP(-B77/Marketing_Saturation_Spend))))*F77*E77-AudioLocal_Base*AudioTour_Price) | O77: =(K77-Total_Daily_AudioTour)*Headset_Cost | P77: =I77*D77+Locals_Base*(1-EXP(-B77/Marketing_Saturation_Spend))*F77*GiftShop_Spillover | Q77: =N77-O77-M77+P77 | R77: =Q77*Campaign_Days-B77
A78: 2. r7 c2 | B78: =Marketing_Spend | C78: =Locals_Share_Ceiling | D78: =GiftShop_Net_Spend_Local | E78: =Sensitivity!$B$23 | F78: =Sensitivity!D$16 | G78: =Percentage_Locals_Init+(C78-Percentage_Locals_Init)*(1-EXP(-B78/Marketing_Saturation_Spend)) | H78: =Tourists_Base*G78/(1-G78) | I78: =H78-Locals_Base | J78: =Locals_Base*(1-(1-EXP(-B78/Marketing_Saturation_Spend)))*Local_AudioTour_Rate_Init+(H78-Locals_Base*(1-(1-EXP(-B78/Marketing_Saturation_Spend))))*F78 | K78: =AudioTourist_Base+J78 | L78: =MAX(0,ROUNDUP((K78-Device_Capacity)/Device_Block_Size,0)) | M78: =L78*Device_Block_Cost/Device_Amort_Days | N78: =Fee_Keep*(Locals_Base*(1-(1-EXP(-B78/Marketing_Saturation_Spend)))*Local_AudioTour_Rate_Init*AudioTour_Price+(H78-Locals_Base*(1-(1-EXP(-B78/Marketing_Saturation_Spend))))*F78*E78-AudioLocal_Base*AudioTour_Price) | O78: =(K78-Total_Daily_AudioTour)*Headset_Cost | P78: =I78*D78+Locals_Base*(1-EXP(-B78/Marketing_Saturation_Spend))*F78*GiftShop_Spillover | Q78: =N78-O78-M78+P78 | R78: =Q78*Campaign_Days-B78
A79: 2. r7 c3 | B79: =Marketing_Spend | C79: =Locals_Share_Ceiling | D79: =GiftShop_Net_Spend_Local | E79: =Sensitivity!$B$23 | F79: =Sensitivity!E$16 | G79: =Percentage_Locals_Init+(C79-Percentage_Locals_Init)*(1-EXP(-B79/Marketing_Saturation_Spend)) | H79: =Tourists_Base*G79/(1-G79) | I79: =H79-Locals_Base | J79: =Locals_Base*(1-(1-EXP(-B79/Marketing_Saturation_Spend)))*Local_AudioTour_Rate_Init+(H79-Locals_Base*(1-(1-EXP(-B79/Marketing_Saturation_Spend))))*F79 | K79: =AudioTourist_Base+J79 | L79: =MAX(0,ROUNDUP((K79-Device_Capacity)/Device_Block_Size,0)) | M79: =L79*Device_Block_Cost/Device_Amort_Days | N79: =Fee_Keep*(Locals_Base*(1-(1-EXP(-B79/Marketing_Saturation_Spend)))*Local_AudioTour_Rate_Init*AudioTour_Price+(H79-Locals_Base*(1-(1-EXP(-B79/Marketing_Saturation_Spend))))*F79*E79-AudioLocal_Base*AudioTour_Price) | O79: =(K79-Total_Daily_AudioTour)*Headset_Cost | P79: =I79*D79+Locals_Base*(1-EXP(-B79/Marketing_Saturation_Spend))*F79*GiftShop_Spillover | Q79: =N79-O79-M79+P79 | R79: =Q79*Campaign_Days-B79
A80: 2. r7 c4 | B80: =Marketing_Spend | C80: =Locals_Share_Ceiling | D80: =GiftShop_Net_Spend_Local | E80: =Sensitivity!$B$23 | F80: =Sensitivity!F$16 | G80: =Percentage_Locals_Init+(C80-Percentage_Locals_Init)*(1-EXP(-B80/Marketing_Saturation_Spend)) | H80: =Tourists_Base*G80/(1-G80) | I80: =H80-Locals_Base | J80: =Locals_Base*(1-(1-EXP(-B80/Marketing_Saturation_Spend)))*Local_AudioTour_Rate_Init+(H80-Locals_Base*(1-(1-EXP(-B80/Marketing_Saturation_Spend))))*F80 | K80: =AudioTourist_Base+J80 | L80: =MAX(0,ROUNDUP((K80-Device_Capacity)/Device_Block_Size,0)) | M80: =L80*Device_Block_Cost/Device_Amort_Days | N80: =Fee_Keep*(Locals_Base*(1-(1-EXP(-B80/Marketing_Saturation_Spend)))*Local_AudioTour_Rate_Init*AudioTour_Price+(H80-Locals_Base*(1-(1-EXP(-B80/Marketing_Saturation_Spend))))*F80*E80-AudioLocal_Base*AudioTour_Price) | O80: =(K80-Total_Daily_AudioTour)*Headset_Cost | P80: =I80*D80+Locals_Base*(1-EXP(-B80/Marketing_Saturation_Spend))*F80*GiftShop_Spillover | Q80: =N80-O80-M80+P80 | R80: =Q80*Campaign_Days-B80
A81: 2. r7 c5 | B81: =Marketing_Spend | C81: =Locals_Share_Ceiling | D81: =GiftShop_Net_Spend_Local | E81: =Sensitivity!$B$23 | F81: =Sensitivity!G$16 | G81: =Percentage_Locals_Init+(C81-Percentage_Locals_Init)*(1-EXP(-B81/Marketing_Saturation_Spend)) | H81: =Tourists_Base*G81/(1-G81) | I81: =H81-Locals_Base | J81: =Locals_Base*(1-(1-EXP(-B81/Marketing_Saturation_Spend)))*Local_AudioTour_Rate_Init+(H81-Locals_Base*(1-(1-EXP(-B81/Marketing_Saturation_Spend))))*F81 | K81: =AudioTourist_Base+J81 | L81: =MAX(0,ROUNDUP((K81-Device_Capacity)/Device_Block_Size,0)) | M81: =L81*Device_Block_Cost/Device_Amort_Days | N81: =Fee_Keep*(Locals_Base*(1-(1-EXP(-B81/Marketing_Saturation_Spend)))*Local_AudioTour_Rate_Init*AudioTour_Price+(H81-Locals_Base*(1-(1-EXP(-B81/Marketing_Saturation_Spend))))*F81*E81-AudioLocal_Base*AudioTour_Price) | O81: =(K81-Total_Daily_AudioTour)*Headset_Cost | P81: =I81*D81+Locals_Base*(1-EXP(-B81/Marketing_Saturation_Spend))*F81*GiftShop_Spillover | Q81: =N81-O81-M81+P81 | R81: =Q81*Campaign_Days-B81
A82: 2. r8 c1 | B82: =Marketing_Spend | C82: =Locals_Share_Ceiling | D82: =GiftShop_Net_Spend_Local | E82: =Sensitivity!$B$24 | F82: =Sensitivity!C$16 | G82: =Percentage_Locals_Init+(C82-Percentage_Locals_Init)*(1-EXP(-B82/Marketing_Saturation_Spend)) | H82: =Tourists_Base*G82/(1-G82) | I82: =H82-Locals_Base | J82: =Locals_Base*(1-(1-EXP(-B82/Marketing_Saturation_Spend)))*Local_AudioTour_Rate_Init+(H82-Locals_Base*(1-(1-EXP(-B82/Marketing_Saturation_Spend))))*F82 | K82: =AudioTourist_Base+J82 | L82: =MAX(0,ROUNDUP((K82-Device_Capacity)/Device_Block_Size,0)) | M82: =L82*Device_Block_Cost/Device_Amort_Days | N82: =Fee_Keep*(Locals_Base*(1-(1-EXP(-B82/Marketing_Saturation_Spend)))*Local_AudioTour_Rate_Init*AudioTour_Price+(H82-Locals_Base*(1-(1-EXP(-B82/Marketing_Saturation_Spend))))*F82*E82-AudioLocal_Base*AudioTour_Price) | O82: =(K82-Total_Daily_AudioTour)*Headset_Cost | P82: =I82*D82+Locals_Base*(1-EXP(-B82/Marketing_Saturation_Spend))*F82*GiftShop_Spillover | Q82: =N82-O82-M82+P82 | R82: =Q82*Campaign_Days-B82
A83: 2. r8 c2 | B83: =Marketing_Spend | C83: =Locals_Share_Ceiling | D83: =GiftShop_Net_Spend_Local | E83: =Sensitivity!$B$24 | F83: =Sensitivity!D$16 | G83: =Percentage_Locals_Init+(C83-Percentage_Locals_Init)*(1-EXP(-B83/Marketing_Saturation_Spend)) | H83: =Tourists_Base*G83/(1-G83) | I83: =H83-Locals_Base | J83: =Locals_Base*(1-(1-EXP(-B83/Marketing_Saturation_Spend)))*Local_AudioTour_Rate_Init+(H83-Locals_Base*(1-(1-EXP(-B83/Marketing_Saturation_Spend))))*F83 | K83: =AudioTourist_Base+J83 | L83: =MAX(0,ROUNDUP((K83-Device_Capacity)/Device_Block_Size,0)) | M83: =L83*Device_Block_Cost/Device_Amort_Days | N83: =Fee_Keep*(Locals_Base*(1-(1-EXP(-B83/Marketing_Saturation_Spend)))*Local_AudioTour_Rate_Init*AudioTour_Price+(H83-Locals_Base*(1-(1-EXP(-B83/Marketing_Saturation_Spend))))*F83*E83-AudioLocal_Base*AudioTour_Price) | O83: =(K83-Total_Daily_AudioTour)*Headset_Cost | P83: =I83*D83+Locals_Base*(1-EXP(-B83/Marketing_Saturation_Spend))*F83*GiftShop_Spillover | Q83: =N83-O83-M83+P83 | R83: =Q83*Campaign_Days-B83
A84: 2. r8 c3 | B84: =Marketing_Spend | C84: =Locals_Share_Ceiling | D84: =GiftShop_Net_Spend_Local | E84: =Sensitivity!$B$24 | F84: =Sensitivity!E$16 | G84: =Percentage_Locals_Init+(C84-Percentage_Locals_Init)*(1-EXP(-B84/Marketing_Saturation_Spend)) | H84: =Tourists_Base*G84/(1-G84) | I84: =H84-Locals_Base | J84: =Locals_Base*(1-(1-EXP(-B84/Marketing_Saturation_Spend)))*Local_AudioTour_Rate_Init+(H84-Locals_Base*(1-(1-EXP(-B84/Marketing_Saturation_Spend))))*F84 | K84: =AudioTourist_Base+J84 | L84: =MAX(0,ROUNDUP((K84-Device_Capacity)/Device_Block_Size,0)) | M84: =L84*Device_Block_Cost/Device_Amort_Days | N84: =Fee_Keep*(Locals_Base*(1-(1-EXP(-B84/Marketing_Saturation_Spend)))*Local_AudioTour_Rate_Init*AudioTour_Price+(H84-Locals_Base*(1-(1-EXP(-B84/Marketing_Saturation_Spend))))*F84*E84-AudioLocal_Base*AudioTour_Price) | O84: =(K84-Total_Daily_AudioTour)*Headset_Cost | P84: =I84*D84+Locals_Base*(1-EXP(-B84/Marketing_Saturation_Spend))*F84*GiftShop_Spillover | Q84: =N84-O84-M84+P84 | R84: =Q84*Campaign_Days-B84
A85: 2. r8 c4 | B85: =Marketing_Spend | C85: =Locals_Share_Ceiling | D85: =GiftShop_Net_Spend_Local | E85: =Sensitivity!$B$24 | F85: =Sensitivity!F$16 | G85: =Percentage_Locals_Init+(C85-Percentage_Locals_Init)*(1-EXP(-B85/Marketing_Saturation_Spend)) | H85: =Tourists_Base*G85/(1-G85) | I85: =H85-Locals_Base | J85: =Locals_Base*(1-(1-EXP(-B85/Marketing_Saturation_Spend)))*Local_AudioTour_Rate_Init+(H85-Locals_Base*(1-(1-EXP(-B85/Marketing_Saturation_Spend))))*F85 | K85: =AudioTourist_Base+J85 | L85: =MAX(0,ROUNDUP((K85-Device_Capacity)/Device_Block_Size,0)) | M85: =L85*Device_Block_Cost/Device_Amort_Days | N85: =Fee_Keep*(Locals_Base*(1-(1-EXP(-B85/Marketing_Saturation_Spend)))*Local_AudioTour_Rate_Init*AudioTour_Price+(H85-Locals_Base*(1-(1-EXP(-B85/Marketing_Saturation_Spend))))*F85*E85-AudioLocal_Base*AudioTour_Price) | O85: =(K85-Total_Daily_AudioTour)*Headset_Cost | P85: =I85*D85+Locals_Base*(1-EXP(-B85/Marketing_Saturation_Spend))*F85*GiftShop_Spillover | Q85: =N85-O85-M85+P85 | R85: =Q85*Campaign_Days-B85
A86: 2. r8 c5 | B86: =Marketing_Spend | C86: =Locals_Share_Ceiling | D86: =GiftShop_Net_Spend_Local | E86: =Sensitivity!$B$24 | F86: =Sensitivity!G$16 | G86: =Percentage_Locals_Init+(C86-Percentage_Locals_Init)*(1-EXP(-B86/Marketing_Saturation_Spend)) | H86: =Tourists_Base*G86/(1-G86) | I86: =H86-Locals_Base | J86: =Locals_Base*(1-(1-EXP(-B86/Marketing_Saturation_Spend)))*Local_AudioTour_Rate_Init+(H86-Locals_Base*(1-(1-EXP(-B86/Marketing_Saturation_Spend))))*F86 | K86: =AudioTourist_Base+J86 | L86: =MAX(0,ROUNDUP((K86-Device_Capacity)/Device_Block_Size,0)) | M86: =L86*Device_Block_Cost/Device_Amort_Days | N86: =Fee_Keep*(Locals_Base*(1-(1-EXP(-B86/Marketing_Saturation_Spend)))*Local_AudioTour_Rate_Init*AudioTour_Price+(H86-Locals_Base*(1-(1-EXP(-B86/Marketing_Saturation_Spend))))*F86*E86-AudioLocal_Base*AudioTour_Price) | O86: =(K86-Total_Daily_AudioTour)*Headset_Cost | P86: =I86*D86+Locals_Base*(1-EXP(-B86/Marketing_Saturation_Spend))*F86*GiftShop_Spillover | Q86: =N86-O86-M86+P86 | R86: =Q86*Campaign_Days-B86
A87: 3. r1 c1 | B87: =Sensitivity!$B$29 | C87: =Sensitivity!C$28 | D87: =GiftShop_Net_Spend_Local | E87: =Average_PWYW | F87: =Local_AudioTour_Rate_PWYW | G87: =Percentage_Locals_Init+(C87-Percentage_Locals_Init)*(1-EXP(-B87/Marketing_Saturation_Spend)) | H87: =Tourists_Base*G87/(1-G87) | I87: =H87-Locals_Base | J87: =Locals_Base*(1-(1-EXP(-B87/Marketing_Saturation_Spend)))*Local_AudioTour_Rate_Init+(H87-Locals_Base*(1-(1-EXP(-B87/Marketing_Saturation_Spend))))*F87 | K87: =AudioTourist_Base+J87 | L87: =MAX(0,ROUNDUP((K87-Device_Capacity)/Device_Block_Size,0)) | M87: =L87*Device_Block_Cost/Device_Amort_Days | N87: =Fee_Keep*(Locals_Base*(1-(1-EXP(-B87/Marketing_Saturation_Spend)))*Local_AudioTour_Rate_Init*AudioTour_Price+(H87-Locals_Base*(1-(1-EXP(-B87/Marketing_Saturation_Spend))))*F87*E87-AudioLocal_Base*AudioTour_Price) | O87: =(K87-Total_Daily_AudioTour)*Headset_Cost | P87: =I87*D87+Locals_Base*(1-EXP(-B87/Marketing_Saturation_Spend))*F87*GiftShop_Spillover | Q87: =N87-O87-M87+P87 | R87: =Q87*Campaign_Days-B87
A88: 3. r1 c2 | B88: =Sensitivity!$B$29 | C88: =Sensitivity!D$28 | D88: =GiftShop_Net_Spend_Local | E88: =Average_PWYW | F88: =Local_AudioTour_Rate_PWYW | G88: =Percentage_Locals_Init+(C88-Percentage_Locals_Init)*(1-EXP(-B88/Marketing_Saturation_Spend)) | H88: =Tourists_Base*G88/(1-G88) | I88: =H88-Locals_Base | J88: =Locals_Base*(1-(1-EXP(-B88/Marketing_Saturation_Spend)))*Local_AudioTour_Rate_Init+(H88-Locals_Base*(1-(1-EXP(-B88/Marketing_Saturation_Spend))))*F88 | K88: =AudioTourist_Base+J88 | L88: =MAX(0,ROUNDUP((K88-Device_Capacity)/Device_Block_Size,0)) | M88: =L88*Device_Block_Cost/Device_Amort_Days | N88: =Fee_Keep*(Locals_Base*(1-(1-EXP(-B88/Marketing_Saturation_Spend)))*Local_AudioTour_Rate_Init*AudioTour_Price+(H88-Locals_Base*(1-(1-EXP(-B88/Marketing_Saturation_Spend))))*F88*E88-AudioLocal_Base*AudioTour_Price) | O88: =(K88-Total_Daily_AudioTour)*Headset_Cost | P88: =I88*D88+Locals_Base*(1-EXP(-B88/Marketing_Saturation_Spend))*F88*GiftShop_Spillover | Q88: =N88-O88-M88+P88 | R88: =Q88*Campaign_Days-B88
A89: 3. r1 c3 | B89: =Sensitivity!$B$29 | C89: =Sensitivity!E$28 | D89: =GiftShop_Net_Spend_Local | E89: =Average_PWYW | F89: =Local_AudioTour_Rate_PWYW | G89: =Percentage_Locals_Init+(C89-Percentage_Locals_Init)*(1-EXP(-B89/Marketing_Saturation_Spend)) | H89: =Tourists_Base*G89/(1-G89) | I89: =H89-Locals_Base | J89: =Locals_Base*(1-(1-EXP(-B89/Marketing_Saturation_Spend)))*Local_AudioTour_Rate_Init+(H89-Locals_Base*(1-(1-EXP(-B89/Marketing_Saturation_Spend))))*F89 | K89: =AudioTourist_Base+J89 | L89: =MAX(0,ROUNDUP((K89-Device_Capacity)/Device_Block_Size,0)) | M89: =L89*Device_Block_Cost/Device_Amort_Days | N89: =Fee_Keep*(Locals_Base*(1-(1-EXP(-B89/Marketing_Saturation_Spend)))*Local_AudioTour_Rate_Init*AudioTour_Price+(H89-Locals_Base*(1-(1-EXP(-B89/Marketing_Saturation_Spend))))*F89*E89-AudioLocal_Base*AudioTour_Price) | O89: =(K89-Total_Daily_AudioTour)*Headset_Cost | P89: =I89*D89+Locals_Base*(1-EXP(-B89/Marketing_Saturation_Spend))*F89*GiftShop_Spillover | Q89: =N89-O89-M89+P89 | R89: =Q89*Campaign_Days-B89
A90: 3. r1 c4 | B90: =Sensitivity!$B$29 | C90: =Sensitivity!F$28 | D90: =GiftShop_Net_Spend_Local | E90: =Average_PWYW | F90: =Local_AudioTour_Rate_PWYW | G90: =Percentage_Locals_Init+(C90-Percentage_Locals_Init)*(1-EXP(-B90/Marketing_Saturation_Spend)) | H90: =Tourists_Base*G90/(1-G90) | I90: =H90-Locals_Base | J90: =Locals_Base*(1-(1-EXP(-B90/Marketing_Saturation_Spend)))*Local_AudioTour_Rate_Init+(H90-Locals_Base*(1-(1-EXP(-B90/Marketing_Saturation_Spend))))*F90 | K90: =AudioTourist_Base+J90 | L90: =MAX(0,ROUNDUP((K90-Device_Capacity)/Device_Block_Size,0)) | M90: =L90*Device_Block_Cost/Device_Amort_Days | N90: =Fee_Keep*(Locals_Base*(1-(1-EXP(-B90/Marketing_Saturation_Spend)))*Local_AudioTour_Rate_Init*AudioTour_Price+(H90-Locals_Base*(1-(1-EXP(-B90/Marketing_Saturation_Spend))))*F90*E90-AudioLocal_Base*AudioTour_Price) | O90: =(K90-Total_Daily_AudioTour)*Headset_Cost | P90: =I90*D90+Locals_Base*(1-EXP(-B90/Marketing_Saturation_Spend))*F90*GiftShop_Spillover | Q90: =N90-O90-M90+P90 | R90: =Q90*Campaign_Days-B90
A91: 3. r1 c5 | B91: =Sensitivity!$B$29 | C91: =Sensitivity!G$28 | D91: =GiftShop_Net_Spend_Local | E91: =Average_PWYW | F91: =Local_AudioTour_Rate_PWYW | G91: =Percentage_Locals_Init+(C91-Percentage_Locals_Init)*(1-EXP(-B91/Marketing_Saturation_Spend)) | H91: =Tourists_Base*G91/(1-G91) | I91: =H91-Locals_Base | J91: =Locals_Base*(1-(1-EXP(-B91/Marketing_Saturation_Spend)))*Local_AudioTour_Rate_Init+(H91-Locals_Base*(1-(1-EXP(-B91/Marketing_Saturation_Spend))))*F91 | K91: =AudioTourist_Base+J91 | L91: =MAX(0,ROUNDUP((K91-Device_Capacity)/Device_Block_Size,0)) | M91: =L91*Device_Block_Cost/Device_Amort_Days | N91: =Fee_Keep*(Locals_Base*(1-(1-EXP(-B91/Marketing_Saturation_Spend)))*Local_AudioTour_Rate_Init*AudioTour_Price+(H91-Locals_Base*(1-(1-EXP(-B91/Marketing_Saturation_Spend))))*F91*E91-AudioLocal_Base*AudioTour_Price) | O91: =(K91-Total_Daily_AudioTour)*Headset_Cost | P91: =I91*D91+Locals_Base*(1-EXP(-B91/Marketing_Saturation_Spend))*F91*GiftShop_Spillover | Q91: =N91-O91-M91+P91 | R91: =Q91*Campaign_Days-B91
A92: 3. r1 c6 | B92: =Sensitivity!$B$29 | C92: =Sensitivity!H$28 | D92: =GiftShop_Net_Spend_Local | E92: =Average_PWYW | F92: =Local_AudioTour_Rate_PWYW | G92: =Percentage_Locals_Init+(C92-Percentage_Locals_Init)*(1-EXP(-B92/Marketing_Saturation_Spend)) | H92: =Tourists_Base*G92/(1-G92) | I92: =H92-Locals_Base | J92: =Locals_Base*(1-(1-EXP(-B92/Marketing_Saturation_Spend)))*Local_AudioTour_Rate_Init+(H92-Locals_Base*(1-(1-EXP(-B92/Marketing_Saturation_Spend))))*F92 | K92: =AudioTourist_Base+J92 | L92: =MAX(0,ROUNDUP((K92-Device_Capacity)/Device_Block_Size,0)) | M92: =L92*Device_Block_Cost/Device_Amort_Days | N92: =Fee_Keep*(Locals_Base*(1-(1-EXP(-B92/Marketing_Saturation_Spend)))*Local_AudioTour_Rate_Init*AudioTour_Price+(H92-Locals_Base*(1-(1-EXP(-B92/Marketing_Saturation_Spend))))*F92*E92-AudioLocal_Base*AudioTour_Price) | O92: =(K92-Total_Daily_AudioTour)*Headset_Cost | P92: =I92*D92+Locals_Base*(1-EXP(-B92/Marketing_Saturation_Spend))*F92*GiftShop_Spillover | Q92: =N92-O92-M92+P92 | R92: =Q92*Campaign_Days-B92
A93: 3. r2 c1 | B93: =Sensitivity!$B$30 | C93: =Sensitivity!C$28 | D93: =GiftShop_Net_Spend_Local | E93: =Average_PWYW | F93: =Local_AudioTour_Rate_PWYW | G93: =Percentage_Locals_Init+(C93-Percentage_Locals_Init)*(1-EXP(-B93/Marketing_Saturation_Spend)) | H93: =Tourists_Base*G93/(1-G93) | I93: =H93-Locals_Base | J93: =Locals_Base*(1-(1-EXP(-B93/Marketing_Saturation_Spend)))*Local_AudioTour_Rate_Init+(H93-Locals_Base*(1-(1-EXP(-B93/Marketing_Saturation_Spend))))*F93 | K93: =AudioTourist_Base+J93 | L93: =MAX(0,ROUNDUP((K93-Device_Capacity)/Device_Block_Size,0)) | M93: =L93*Device_Block_Cost/Device_Amort_Days | N93: =Fee_Keep*(Locals_Base*(1-(1-EXP(-B93/Marketing_Saturation_Spend)))*Local_AudioTour_Rate_Init*AudioTour_Price+(H93-Locals_Base*(1-(1-EXP(-B93/Marketing_Saturation_Spend))))*F93*E93-AudioLocal_Base*AudioTour_Price) | O93: =(K93-Total_Daily_AudioTour)*Headset_Cost | P93: =I93*D93+Locals_Base*(1-EXP(-B93/Marketing_Saturation_Spend))*F93*GiftShop_Spillover | Q93: =N93-O93-M93+P93 | R93: =Q93*Campaign_Days-B93
A94: 3. r2 c2 | B94: =Sensitivity!$B$30 | C94: =Sensitivity!D$28 | D94: =GiftShop_Net_Spend_Local | E94: =Average_PWYW | F94: =Local_AudioTour_Rate_PWYW | G94: =Percentage_Locals_Init+(C94-Percentage_Locals_Init)*(1-EXP(-B94/Marketing_Saturation_Spend)) | H94: =Tourists_Base*G94/(1-G94) | I94: =H94-Locals_Base | J94: =Locals_Base*(1-(1-EXP(-B94/Marketing_Saturation_Spend)))*Local_AudioTour_Rate_Init+(H94-Locals_Base*(1-(1-EXP(-B94/Marketing_Saturation_Spend))))*F94 | K94: =AudioTourist_Base+J94 | L94: =MAX(0,ROUNDUP((K94-Device_Capacity)/Device_Block_Size,0)) | M94: =L94*Device_Block_Cost/Device_Amort_Days | N94: =Fee_Keep*(Locals_Base*(1-(1-EXP(-B94/Marketing_Saturation_Spend)))*Local_AudioTour_Rate_Init*AudioTour_Price+(H94-Locals_Base*(1-(1-EXP(-B94/Marketing_Saturation_Spend))))*F94*E94-AudioLocal_Base*AudioTour_Price) | O94: =(K94-Total_Daily_AudioTour)*Headset_Cost | P94: =I94*D94+Locals_Base*(1-EXP(-B94/Marketing_Saturation_Spend))*F94*GiftShop_Spillover | Q94: =N94-O94-M94+P94 | R94: =Q94*Campaign_Days-B94
A95: 3. r2 c3 | B95: =Sensitivity!$B$30 | C95: =Sensitivity!E$28 | D95: =GiftShop_Net_Spend_Local | E95: =Average_PWYW | F95: =Local_AudioTour_Rate_PWYW | G95: =Percentage_Locals_Init+(C95-Percentage_Locals_Init)*(1-EXP(-B95/Marketing_Saturation_Spend)) | H95: =Tourists_Base*G95/(1-G95) | I95: =H95-Locals_Base | J95: =Locals_Base*(1-(1-EXP(-B95/Marketing_Saturation_Spend)))*Local_AudioTour_Rate_Init+(H95-Locals_Base*(1-(1-EXP(-B95/Marketing_Saturation_Spend))))*F95 | K95: =AudioTourist_Base+J95 | L95: =MAX(0,ROUNDUP((K95-Device_Capacity)/Device_Block_Size,0)) | M95: =L95*Device_Block_Cost/Device_Amort_Days | N95: =Fee_Keep*(Locals_Base*(1-(1-EXP(-B95/Marketing_Saturation_Spend)))*Local_AudioTour_Rate_Init*AudioTour_Price+(H95-Locals_Base*(1-(1-EXP(-B95/Marketing_Saturation_Spend))))*F95*E95-AudioLocal_Base*AudioTour_Price) | O95: =(K95-Total_Daily_AudioTour)*Headset_Cost | P95: =I95*D95+Locals_Base*(1-EXP(-B95/Marketing_Saturation_Spend))*F95*GiftShop_Spillover | Q95: =N95-O95-M95+P95 | R95: =Q95*Campaign_Days-B95
A96: 3. r2 c4 | B96: =Sensitivity!$B$30 | C96: =Sensitivity!F$28 | D96: =GiftShop_Net_Spend_Local | E96: =Average_PWYW | F96: =Local_AudioTour_Rate_PWYW | G96: =Percentage_Locals_Init+(C96-Percentage_Locals_Init)*(1-EXP(-B96/Marketing_Saturation_Spend)) | H96: =Tourists_Base*G96/(1-G96) | I96: =H96-Locals_Base | J96: =Locals_Base*(1-(1-EXP(-B96/Marketing_Saturation_Spend)))*Local_AudioTour_Rate_Init+(H96-Locals_Base*(1-(1-EXP(-B96/Marketing_Saturation_Spend))))*F96 | K96: =AudioTourist_Base+J96 | L96: =MAX(0,ROUNDUP((K96-Device_Capacity)/Device_Block_Size,0)) | M96: =L96*Device_Block_Cost/Device_Amort_Days | N96: =Fee_Keep*(Locals_Base*(1-(1-EXP(-B96/Marketing_Saturation_Spend)))*Local_AudioTour_Rate_Init*AudioTour_Price+(H96-Locals_Base*(1-(1-EXP(-B96/Marketing_Saturation_Spend))))*F96*E96-AudioLocal_Base*AudioTour_Price) | O96: =(K96-Total_Daily_AudioTour)*Headset_Cost | P96: =I96*D96+Locals_Base*(1-EXP(-B96/Marketing_Saturation_Spend))*F96*GiftShop_Spillover | Q96: =N96-O96-M96+P96 | R96: =Q96*Campaign_Days-B96
A97: 3. r2 c5 | B97: =Sensitivity!$B$30 | C97: =Sensitivity!G$28 | D97: =GiftShop_Net_Spend_Local | E97: =Average_PWYW | F97: =Local_AudioTour_Rate_PWYW | G97: =Percentage_Locals_Init+(C97-Percentage_Locals_Init)*(1-EXP(-B97/Marketing_Saturation_Spend)) | H97: =Tourists_Base*G97/(1-G97) | I97: =H97-Locals_Base | J97: =Locals_Base*(1-(1-EXP(-B97/Marketing_Saturation_Spend)))*Local_AudioTour_Rate_Init+(H97-Locals_Base*(1-(1-EXP(-B97/Marketing_Saturation_Spend))))*F97 | K97: =AudioTourist_Base+J97 | L97: =MAX(0,ROUNDUP((K97-Device_Capacity)/Device_Block_Size,0)) | M97: =L97*Device_Block_Cost/Device_Amort_Days | N97: =Fee_Keep*(Locals_Base*(1-(1-EXP(-B97/Marketing_Saturation_Spend)))*Local_AudioTour_Rate_Init*AudioTour_Price+(H97-Locals_Base*(1-(1-EXP(-B97/Marketing_Saturation_Spend))))*F97*E97-AudioLocal_Base*AudioTour_Price) | O97: =(K97-Total_Daily_AudioTour)*Headset_Cost | P97: =I97*D97+Locals_Base*(1-EXP(-B97/Marketing_Saturation_Spend))*F97*GiftShop_Spillover | Q97: =N97-O97-M97+P97 | R97: =Q97*Campaign_Days-B97
A98: 3. r2 c6 | B98: =Sensitivity!$B$30 | C98: =Sensitivity!H$28 | D98: =GiftShop_Net_Spend_Local | E98: =Average_PWYW | F98: =Local_AudioTour_Rate_PWYW | G98: =Percentage_Locals_Init+(C98-Percentage_Locals_Init)*(1-EXP(-B98/Marketing_Saturation_Spend)) | H98: =Tourists_Base*G98/(1-G98) | I98: =H98-Locals_Base | J98: =Locals_Base*(1-(1-EXP(-B98/Marketing_Saturation_Spend)))*Local_AudioTour_Rate_Init+(H98-Locals_Base*(1-(1-EXP(-B98/Marketing_Saturation_Spend))))*F98 | K98: =AudioTourist_Base+J98 | L98: =MAX(0,ROUNDUP((K98-Device_Capacity)/Device_Block_Size,0)) | M98: =L98*Device_Block_Cost/Device_Amort_Days | N98: =Fee_Keep*(Locals_Base*(1-(1-EXP(-B98/Marketing_Saturation_Spend)))*Local_AudioTour_Rate_Init*AudioTour_Price+(H98-Locals_Base*(1-(1-EXP(-B98/Marketing_Saturation_Spend))))*F98*E98-AudioLocal_Base*AudioTour_Price) | O98: =(K98-Total_Daily_AudioTour)*Headset_Cost | P98: =I98*D98+Locals_Base*(1-EXP(-B98/Marketing_Saturation_Spend))*F98*GiftShop_Spillover | Q98: =N98-O98-M98+P98 | R98: =Q98*Campaign_Days-B98
A99: 3. r3 c1 | B99: =Sensitivity!$B$31 | C99: =Sensitivity!C$28 | D99: =GiftShop_Net_Spend_Local | E99: =Average_PWYW | F99: =Local_AudioTour_Rate_PWYW | G99: =Percentage_Locals_Init+(C99-Percentage_Locals_Init)*(1-EXP(-B99/Marketing_Saturation_Spend)) | H99: =Tourists_Base*G99/(1-G99) | I99: =H99-Locals_Base | J99: =Locals_Base*(1-(1-EXP(-B99/Marketing_Saturation_Spend)))*Local_AudioTour_Rate_Init+(H99-Locals_Base*(1-(1-EXP(-B99/Marketing_Saturation_Spend))))*F99 | K99: =AudioTourist_Base+J99 | L99: =MAX(0,ROUNDUP((K99-Device_Capacity)/Device_Block_Size,0)) | M99: =L99*Device_Block_Cost/Device_Amort_Days | N99: =Fee_Keep*(Locals_Base*(1-(1-EXP(-B99/Marketing_Saturation_Spend)))*Local_AudioTour_Rate_Init*AudioTour_Price+(H99-Locals_Base*(1-(1-EXP(-B99/Marketing_Saturation_Spend))))*F99*E99-AudioLocal_Base*AudioTour_Price) | O99: =(K99-Total_Daily_AudioTour)*Headset_Cost | P99: =I99*D99+Locals_Base*(1-EXP(-B99/Marketing_Saturation_Spend))*F99*GiftShop_Spillover | Q99: =N99-O99-M99+P99 | R99: =Q99*Campaign_Days-B99
A100: 3. r3 c2 | B100: =Sensitivity!$B$31 | C100: =Sensitivity!D$28 | D100: =GiftShop_Net_Spend_Local | E100: =Average_PWYW | F100: =Local_AudioTour_Rate_PWYW | G100: =Percentage_Locals_Init+(C100-Percentage_Locals_Init)*(1-EXP(-B100/Marketing_Saturation_Spend)) | H100: =Tourists_Base*G100/(1-G100) | I100: =H100-Locals_Base | J100: =Locals_Base*(1-(1-EXP(-B100/Marketing_Saturation_Spend)))*Local_AudioTour_Rate_Init+(H100-Locals_Base*(1-(1-EXP(-B100/Marketing_Saturation_Spend))))*F100 | K100: =AudioTourist_Base+J100 | L100: =MAX(0,ROUNDUP((K100-Device_Capacity)/Device_Block_Size,0)) | M100: =L100*Device_Block_Cost/Device_Amort_Days | N100: =Fee_Keep*(Locals_Base*(1-(1-EXP(-B100/Marketing_Saturation_Spend)))*Local_AudioTour_Rate_Init*AudioTour_Price+(H100-Locals_Base*(1-(1-EXP(-B100/Marketing_Saturation_Spend))))*F100*E100-AudioLocal_Base*AudioTour_Price) | O100: =(K100-Total_Daily_AudioTour)*Headset_Cost | P100: =I100*D100+Locals_Base*(1-EXP(-B100/Marketing_Saturation_Spend))*F100*GiftShop_Spillover | Q100: =N100-O100-M100+P100 | R100: =Q100*Campaign_Days-B100
...

Sheet Lists
A1: Marketing ($)
A2: 0
A3: 2500
A4: 5000
A5: 7500
A6: 10000
A7: 12500
A8: 15000
A9: 17500
A10: 20000
